{
  "sources": [
    {
      "title": "0x资讯",
      "feedUrl": "https://0xzx.com/feed/",
      "siteUrl": "https://0xzx.com",
      "articles": [
        {
          "id": "https://0xzx.com/2022121313222959475.html",
          "author": "0x资讯",
          "description": "山姆·班克曼·弗里德 (Sam Bankman Fried) 是加密货币交易所 FTX 的创始人，周一晚间因美 […]",
          "link": "https://0xzx.com/2022121313222959475.html",
          "publishedOn": "2022-12-13T05:22:10.000Z",
          "wordCount": 2400,
          "title": "名誉扫地的 FTX 创始人 SBF 被捕，他会在美国国会作证吗？",
          "imageUrl": null
        },
        {
          "id": "https://0xzx.com/2022121313212959472.html",
          "author": "0x资讯",
          "description": "破产的加密货币交易所 FTX.com 的新任首席执行官约翰·J·雷三世 (John J. Ray III) 在 […]",
          "link": "https://0xzx.com/2022121313212959472.html",
          "publishedOn": "2022-12-13T05:21:53.000Z",
          "wordCount": 2360,
          "title": "FTX 新任首席执行官表示，他在交易所发现了“不可接受的做法”",
          "imageUrl": null
        },
        {
          "id": "https://0xzx.com/2022121313212959471.html",
          "author": "0x资讯",
          "description": "BlockBeats 消息，12 月 13 日，Web3 操作系统 dappOS 宣布与 Avalanche  […]",
          "link": "https://0xzx.com/2022121313212959471.html",
          "publishedOn": "2022-12-13T05:21:17.000Z",
          "wordCount": 2350,
          "title": "Web3操作系统dappOS与Avalanche达成战略合作，将支持Avalanche生态发展",
          "imageUrl": null
        },
        {
          "id": "https://0xzx.com/2022121313212959470.html",
          "author": "0x资讯",
          "description": "像 Dogecoin (DOGE)、Shiba Inu 和 Big Eyes 这样的 Memecoins 不再 […]",
          "link": "https://0xzx.com/2022121313212959470.html",
          "publishedOn": "2022-12-13T05:21:16.000Z",
          "wordCount": 2482,
          "title": "需要提防的狗狗币 (DOGE)、柴犬 (SHIB) 和大眼币、Memecoins",
          "imageUrl": null
        },
        {
          "id": "https://0xzx.com/2022121313212959468.html",
          "author": "0x资讯",
          "description": "巴哈马当局拘留了 Sam Bankman-Fried，他是 FTX 加密货币交易所的创始人和前首席执行官，也是 […]",
          "link": "https://0xzx.com/2022121313212959468.html",
          "publishedOn": "2022-12-13T05:21:10.000Z",
          "wordCount": 2434,
          "title": "巴哈马警方应美国要求逮捕山姆·班克曼-弗里德",
          "imageUrl": null
        }
      ]
    },
    {
      "title": "DeFi之道",
      "feedUrl": "https://www.defidaonews.com/feed",
      "siteUrl": "https://www.defidaonews.com",
      "articles": [
        {
          "id": "https://www.defidaonews.com/article/6793196",
          "author": "东寻",
          "description": "加密货币正处于熊市中，但仍有少数领域和项目正在蓬勃发展。",
          "link": "https://www.defidaonews.com/article/6793196",
          "publishedOn": "2022-12-13T06:16:38.000Z",
          "wordCount": 687,
          "title": "一文了解熊市中仍在增长的领域以及 5 个项目",
          "imageUrl": "https://appserversrc.8btc.cn/FtB-1pzq0Xx9FOaYwsvZWnKY_FIt.png?imageView2/1/w/500/h/300"
        },
        {
          "id": "https://www.defidaonews.com/article/6793192",
          "author": "Kyle",
          "description": "据 The Block 报道，12 月 13 日，美国众议院金融服务委员会主席、加利福尼亚州民主党人 Maxine Waters 表示，她对前 FTX 首席执行官 Sam Bankman-Fried（SBF）被捕的时间感到“失望”和“惊讶”，因为他计划于明天参加众议院金融服务委员会主席就 FTX 崩盘所召开的听证会。\nWaters 在针对 Bankman-Fried 被捕发表的声明中表示，“现在是时候开始将 Bankman-Fried 绳之以法了，然而，公众所知，在过去的一个月里，我和我的同时一...",
          "link": "https://www.defidaonews.com/article/6793192",
          "publishedOn": "2022-12-13T05:53:16.000Z",
          "wordCount": 206,
          "title": "美国众议院金融服务委员会主席：质疑听证会前夕逮捕 SBF，对 SBF 无法出席听证会感到“失望”",
          "imageUrl": "https://appserversrc.8btc.cn/images/28094f8e91211fbd40cd0a91adfc7c3d.png"
        },
        {
          "id": "https://www.defidaonews.com/article/6793178",
          "author": "Foresight News",
          "description": "即便币安真的面临诉讼，最坏的结果是退出美国市场。",
          "link": "https://www.defidaonews.com/article/6793178",
          "publishedOn": "2022-12-13T03:54:32.000Z",
          "wordCount": 228,
          "title": "观点：为什么无需担心币安会因美国起诉而倒闭",
          "imageUrl": "https://appserversrc.8btc.cn/Fq8N0CffRicwOeliYeUO2Q_p2N-F.png?imageView2/1/w/500/h/300"
        },
        {
          "id": "https://www.defidaonews.com/article/6793176",
          "author": "Kyle",
          "description": "据彭博社 12 月 13 日报道，据 FTX 律师在法庭文件中表示，巴哈马政府官员与前 FTX 首席执行官 Sam Bankman-Fried（SBF）密切合作，并试图帮助他重新获得对破产的 FTX Trading 主要计算机系统的访问权。FTX 的法律团队表示，在 SBF 被阻止进入 FTX 系统之前，巴哈马要求他铸造价值数亿美元的新代币，然后将这些代币转移到巴哈马官员的控制之下。而当 FTX 现任 CEO John J Ray III 和他的团队试图控制 FTX 的计算机系统时，他们看到有人...",
          "link": "https://www.defidaonews.com/article/6793176",
          "publishedOn": "2022-12-13T03:26:41.000Z",
          "wordCount": 189,
          "title": "FTX 律师：巴哈马政府曾要求 SBF 铸造数亿美元的新代币并上交",
          "imageUrl": "https://appserversrc.8btc.cn/images/28094f8e91211fbd40cd0a91adfc7c3d.png"
        },
        {
          "id": "https://www.defidaonews.com/article/6793172",
          "author": "元宇宙之道",
          "description": "奋力向“西北元宇宙第一城”目标迈进",
          "link": "https://www.defidaonews.com/article/6793172",
          "publishedOn": "2022-12-13T03:21:11.000Z",
          "wordCount": 110,
          "title": "陕西宝鸡出台元宇宙产业发展行动计划，重塑数字产业经济体系",
          "imageUrl": "https://appserversrc.8btc.cn/FsNRMxuch44U50zU5ueXTxb4ncC7.png?imageView2/1/w/500/h/300"
        },
        {
          "id": "https://www.defidaonews.com/article/6793170",
          "author": "区块链资讯",
          "description": "我们需要成为火，而不是害怕风。我们不仅要在风中坚持下去，而且要希望风来。",
          "link": "https://www.defidaonews.com/article/6793170",
          "publishedOn": "2022-12-13T03:11:44.000Z",
          "wordCount": 415,
          "title": "烈火无惧风吹：给 DAO 设计做减法",
          "imageUrl": "https://appserversrc.8btc.cn/Fvh2pNbRW1Rg2IRODT6LCbe9UGxg.png?imageView2/1/w/500/h/300"
        },
        {
          "id": "https://www.defidaonews.com/article/6793168",
          "author": "Kyle",
          "description": "12 月 13 日，据福克斯新闻节目披露，FTX 创始人 Sam Bankman-Fried（SBF）被指控电汇欺诈、证券欺诈和洗钱等罪名，这意味着如果指控罪名成立，SBF 可能会面临终身监禁。",
          "link": "https://www.defidaonews.com/article/6793168",
          "publishedOn": "2022-12-13T03:11:12.000Z",
          "wordCount": 108,
          "title": "福克斯：如果指控罪名成立，SBF 可能会面临终身监禁",
          "imageUrl": "https://appserversrc.8btc.cn/images/28094f8e91211fbd40cd0a91adfc7c3d.png"
        },
        {
          "id": "https://www.defidaonews.com/article/6793120",
          "author": "DAOrayaki",
          "description": "本文根据各个债权人公司发布的新闻，整理出FTX与50家债权人的关系。",
          "link": "https://www.defidaonews.com/article/6793120",
          "publishedOn": "2022-12-13T02:58:32.000Z",
          "wordCount": 137,
          "title": "一图披露FTX与50家投资人、债权人的关系",
          "imageUrl": "https://appserversrc.8btc.cn/FqjeCy2JnogTgcCDPNrg13zIQOn_.png?imageView2/1/w/500/h/300"
        },
        {
          "id": "https://www.defidaonews.com/article/6793164",
          "author": "隔夜的粥",
          "description": "GEAR 提供了一种创造代币流动性的新思路",
          "link": "https://www.defidaonews.com/article/6793164",
          "publishedOn": "2022-12-13T02:49:07.000Z",
          "wordCount": 689,
          "title": "三分钟了解 Gearbox 创新的流动性引导方案",
          "imageUrl": "https://appserversrc.8btc.cn/FtTxxXP9YJyj_z9lTMW-rY7h-baM.png?imageView2/1/w/500/h/300"
        },
        {
          "id": "https://www.defidaonews.com/article/6793154",
          "author": "IOSG Ventures",
          "description": "去满足那些真实的用户需求和最日常的使用场景，一切内容产品最终都会回归内容为王的理性。",
          "link": "https://www.defidaonews.com/article/6793154",
          "publishedOn": "2022-12-13T02:33:50.000Z",
          "wordCount": 1142,
          "title": "IOSG ：梳理 Web3 Games 背后的资本和人才流向",
          "imageUrl": "https://appserversrc.8btc.cn/Fhi0Cg6z2YXi__18EtnqDLGhcSmW.png?imageView2/1/w/500/h/300"
        }
      ]
    },
    {
      "title": "Web3.0世界",
      "feedUrl": "https://www.web3sj.com/feed/",
      "siteUrl": "https://www.web3sj.com",
      "articles": [
        {
          "id": "https://www.web3sj.com/?p=33149",
          "author": "Gao",
          "description": "彼时，Quest3 刚发布 Beta 版本，产品逻辑初见雏形。同时做相似业务的竞品林立，在肯定部分产品体验创新的同时，也不由怀疑 Quest3 能否在激烈的竞争环境中获取一席之地，站稳并走远。",
          "link": "https://www.web3sj.com/project/33149/",
          "publishedOn": "2022-12-13T05:56:47.000Z",
          "wordCount": 1038,
          "title": "不断进化的Quest3，会是Web3广告平台的最佳形态吗？",
          "imageUrl": "https://www.web3sj.com/wp-content/uploads/2022/12/1670906606021.png"
        },
        {
          "id": "https://www.web3sj.com/?p=33145",
          "author": "Gao",
          "description": "如果在元宇宙中，用户是他们自己数据和数字身份的保管人，什么样的规则和条例将适用于他们？他们将如何维护和保护自己的数据？如果他们的整个数字身份本身被盗、修改或克隆，他们会有什么追索权？",
          "link": "https://www.web3sj.com/news/33145/",
          "publishedOn": "2022-12-13T04:41:59.000Z",
          "wordCount": 579,
          "title": "为什么需要在元宇宙中规范数字身份？",
          "imageUrl": "https://www.web3sj.com/wp-content/uploads/2022/12/1670906314914.png"
        },
        {
          "id": "https://www.web3sj.com/?p=33142",
          "author": "Gao",
          "description": "根据社区成员的叙述，黑猫社区的核心 builder 们一直在自掏腰包维持社区的运营和举办主题活动，这是基于核心 builder 们对黑猫理念的共识，这种自发性的去中心化社区传播也让黑猫在短时间内快速出圈。",
          "link": "https://www.web3sj.com/nftnews/33142/",
          "publishedOn": "2022-12-13T04:35:41.000Z",
          "wordCount": 654,
          "title": "黑猫社区发生利益冲突，NFT艺术家应该干涉社区建设吗？",
          "imageUrl": "https://www.web3sj.com/wp-content/uploads/2022/12/1670906086174.png"
        },
        {
          "id": "https://www.web3sj.com/?p=33130",
          "author": "Gao",
          "description": "随着加密货币采用的增加，对协议及其用户来说，如何防止被利用是很重要的。审计和代码审查是第一个也是最明显的步骤（但它们并不意味着被利用的可能性为 0）。协议和用户如何保护自己免受这些攻击？正如 TradFi 的情况，保险可能是最好的答案。",
          "link": "https://www.web3sj.com/news/33130/",
          "publishedOn": "2022-12-13T04:32:34.000Z",
          "wordCount": 861,
          "title": "一文了解加密保险领域现状",
          "imageUrl": "https://www.web3sj.com/wp-content/uploads/2022/12/1670905899848.png"
        },
        {
          "id": "https://www.web3sj.com/?p=33116",
          "author": "Gao",
          "description": "先来看看 web3 游戏的用户数趋势，值得注意的是，不同项目上链的程度不同，与 smart contract 交互的模块也不一样，且不同项目对多账号羊毛党的容忍度不一，通过链上数据获得的用户数只能作为参考。",
          "link": "https://www.web3sj.com/gamefinews/33116/",
          "publishedOn": "2022-12-13T04:13:02.000Z",
          "wordCount": 1176,
          "title": "IOSG Weekly Brief：Web3 Games背后的资本和人才流向",
          "imageUrl": "https://www.web3sj.com/wp-content/uploads/2022/12/1670904246639.png"
        },
        {
          "id": "https://www.web3sj.com/?p=33107",
          "author": "Gao",
          "description": "本文将详细阐述 Hooked Protocol 整体产品策略和计划、产品里程碑、以及每个里程碑的详细信息，后续 Hooked Protocol 将在每个季度初发布季度产品计划。",
          "link": "https://www.web3sj.com/project/33107/",
          "publishedOn": "2022-12-13T03:28:49.000Z",
          "wordCount": 802,
          "title": "一文读懂Hooked Protocol的2023年发展路线图",
          "imageUrl": "https://www.web3sj.com/wp-content/uploads/2022/12/1670901842078.png"
        },
        {
          "id": "https://www.web3sj.com/?p=33069",
          "author": "Gao",
          "description": "以太坊扩容方案Fuel计划于2023年推出完整主网。Sushi CEO：一年内已花费3000万美元引导流动性，新代币经济学将重新设计引导流动性。Solv Protocol 半同质化代币标准 ERC-3525 已完成参考实现并开源代码。",
          "link": "https://www.web3sj.com/news/33069/",
          "publishedOn": "2022-12-12T12:59:43.000Z",
          "wordCount": 733,
          "title": "Web3.0世界日报（12月12日）",
          "imageUrl": "https://www.web3sj.com/wp-content/uploads/2022/12/2022121212574212.jpg"
        },
        {
          "id": "https://www.web3sj.com/?p=33049",
          "author": "Gao",
          "description": "Flashbots 是 MEV 的核心参与者，此后继续取得了巨大成功；近 90% 的以太坊验证者现在正在运行其 MEV-boost 客户端。这意味着他们会收到额外的付款（在协议奖励之外）以重新排序或将交易添加到他们提议的区块中。",
          "link": "https://www.web3sj.com/news/33049/",
          "publishedOn": "2022-12-12T11:56:32.000Z",
          "wordCount": 802,
          "title": "Flashbots如何通过SUAVE来管理所有区块链的MEV市场？",
          "imageUrl": "https://www.web3sj.com/wp-content/uploads/2022/12/1670846137564.png"
        },
        {
          "id": "https://www.web3sj.com/?p=33036",
          "author": "Gao",
          "description": "Validator Infra Provider、Pooled Staking Protocol、CEX 和 Staker 能够从 Validator Staking Income 中分一杯羹；Searcher、Block Builder 能够从 Validator Uncaptured Value 中分一杯羹。",
          "link": "https://www.web3sj.com/news/33036/",
          "publishedOn": "2022-12-12T11:48:19.000Z",
          "wordCount": 1376,
          "title": "以太坊质押可提取价值中有哪些投资机会？",
          "imageUrl": "https://www.web3sj.com/wp-content/uploads/2022/12/1670845642958.png"
        },
        {
          "id": "https://www.web3sj.com/?p=33030",
          "author": "Gao",
          "description": "Dune Analytics 统计数据显示，以太坊信标链上质押数呈持续上升趋势，截至 12 月 12 日已突破 1560 万枚 ETH，占当前以太坊总流通量的 12.9%，验证者总量为 48.8 万。按当前市场计算，信标链质押 ETH 总价值已逾 194 亿美元。其中，流动性质押占比 33%，中心化交易所占比 29%，巨鲸占比 23%，质押池占比 10.2%，即大部分 ETH 质押通过第三方平台进行。",
          "link": "https://www.web3sj.com/news/33030/",
          "publishedOn": "2022-12-12T11:28:01.000Z",
          "wordCount": 800,
          "title": "以太坊上海升级将启动提款功能，验证者的ETH会如何解锁？",
          "imageUrl": "https://www.web3sj.com/wp-content/uploads/2022/12/1670844368320.png"
        }
      ]
    },
    {
      "title": "PANews - 快讯",
      "feedUrl": "https://rsshub.app/panewslab/news",
      "siteUrl": "https://panewslab.com/zh/news/index.html",
      "articles": [
        {
          "id": "https://panewslab.com/zh/articledetails/xh79r15p.html",
          "author": "PA一线",
          "description": "PANews 12月13日消息，据The Block报道，美国众议院金融服务委员会主席、加利福尼亚州民主党人Maxine Waters表示，她对前FTX首席执行官Sam Bankman-Fried（SBF）被捕的时间感到“失望”和“惊讶”，因为他计划于明天参加众议院金融服务委员会主席就FTX崩盘而召开的听证会。\nWaters在针对Bankman-Fried被捕发表的声明中表示：“现在是时候开始将SBF绳之以法了，然而，公众所知，在过去的一个月里，我和我的同事一直在努力工作，以确保SBF明天早上在我们的委员会面前作证。尽管SBF必须​​被追究责任，但美国公众应该直接从SBF那里了解到伤害了100多万人，并摧毁了许多人辛苦赚来的毕生积蓄的行为， 公众一直热切等待在国会宣誓后得到这些答案，而这次逮捕的时机剥夺了公众这个机会。”\n此前今日早些时候消息，SBF已被巴哈马警方逮捕，美国已对SBF提出刑事指控，并可能要求引渡他。美国纽约南区检察官Damian Williams表示，预计将在当地时间周二上午公布起诉书，届时将有更多消息。纽约时报报道称美国对SBF的刑事指控包括电汇欺诈、证券欺诈和洗钱等多项罪名。",
          "link": "https://panewslab.com/zh/articledetails/xh79r15p.html",
          "publishedOn": "2022-12-13T04:19:08.000Z",
          "wordCount": 3559,
          "title": "美众议院金融服务委员会主席对SBF因被捕而无法出席听证会感到“失望”",
          "imageUrl": "https://image.panewslab.com/images/logo1.jpg"
        },
        {
          "id": "https://panewslab.com/zh/articledetails/4gh1j8x5.html",
          "author": "PA一线",
          "description": "PANews 12月13日消息，据韩国媒体每日经济新闻报道，韩国釜山数字资产交易所设立推进委员会将于12月19日启动，由15名产学界专家组成，将在落实交易所设立计划中发挥实际作用。釜山市计划明年上半年成立交易所控股公司，明年下半年成立市场管理机构，目标是明年底开始提供服务。根据釜山市的具体计划，釜山市将于明年共设立7家法人，包括1家控股公司、3家子公司和3家市场管理机构。釜山数字资产交易所负责发行、上市、交易和管理数字资产，建立将交易标的分为证券类和非证券类数字资产的制度，设置上市评估、市场监测监管、存管结算三个市场管理机构。\n釜山市计划实施由私营部门牵头的项目，明年上半年，将选定运营“釜山数字资产交易所设立基金”的资产运营公司并建立基金。它还招募交易所成员以确保资金设立。以此为基础，上半年将成立一家交易所控股公司。明年下半年，将成立交易所子公司和市场管理机构，申报为虚拟资产运营商。釜山市计划仅投资最低限度的股份以确保宣传，并在交易所成立后的一段时间内将股份出售给私营部门。\n此前消息，韩国釜山市与币安、FTX、Houbi、Crypto.com和Gate.io签署关于成立釜山数字资产交易所的合作协议，且多个区块链风投公司拟在韩国釜山投资1亿美元用于生态系统发展。不过在FTX破产后，韩联社曾报道称，釜山市因FTX破产等因素重新考虑是否建立数字资产交易所。",
          "link": "https://panewslab.com/zh/articledetails/4gh1j8x5.html",
          "publishedOn": "2022-12-13T04:03:19.000Z",
          "wordCount": 3544,
          "title": "韩国釜山数字资产交易所计划于明年底开始提供服务",
          "imageUrl": "https://image.panewslab.com/images/logo1.jpg"
        },
        {
          "id": "https://panewslab.com/zh/articledetails/plnb105z.html",
          "author": "PA一线",
          "description": "PANews 12月13日消息，MakerDAO执行捆绑8个提案的治理行动，包括：支付代表工资、提高DAI利率至1%、取消renBTC作为DAI抵押品、将GnosisDAO治理代币GNO作为抵押品、Starknet DAI桥参数更改、上线BlockTower真实世界资产Vault、MKR归属、MOMC参数变化，上述提案均已由社区投票通过。",
          "link": "https://panewslab.com/zh/articledetails/plnb105z.html",
          "publishedOn": "2022-12-13T03:49:00.000Z",
          "wordCount": 3542,
          "title": "MakerDAO执行8个提案捆绑治理行动，包括提高DAI利率至1%",
          "imageUrl": "https://image.panewslab.com/images/logo1.jpg"
        },
        {
          "id": "https://panewslab.com/zh/articledetails/ww9dw4kf.html",
          "author": "PA一线",
          "description": "PANews 12月13日消息，区块链情报平台Nansen的数据显示，加密交易所持有的ETH共计2530万枚。其中，Coinbase是最大的ETH交易所持有者，持有约871万枚ETH（约110亿美元），占全部交易所持有ETH的34%。币安持有519万枚ETH，位列第二，占比20%。",
          "link": "https://panewslab.com/zh/articledetails/ww9dw4kf.html",
          "publishedOn": "2022-12-13T03:33:54.000Z",
          "wordCount": 3547,
          "title": "数据：Coinbase持有约871万枚ETH，是最大的ETH交易所持有者",
          "imageUrl": "https://image.panewslab.com/images/logo1.jpg"
        },
        {
          "id": "https://panewslab.com/zh/articledetails/i9ijxayx.html",
          "author": "PA一线",
          "description": "PANews 12月13日消息，据官方公告，币安宣布上线新一批BTC云算力挖矿产品，将于今日12点已开放申购，此批云算力挖矿产品预计挖矿开始时间为2022年12月18日12:00。\n此前消息，币安矿池10月14日宣布推出5亿美元矿工贷款项目，之前已推出两批云算力挖矿产品。据介绍，与Bitdeer和BitFuFu等提供自营算力不同，币安从第三方购买算力。",
          "link": "https://panewslab.com/zh/articledetails/i9ijxayx.html",
          "publishedOn": "2022-12-13T03:24:59.000Z",
          "wordCount": 3543,
          "title": "币安上线新一批BTC云算力挖矿产品，预计挖矿开始时间为12月18日",
          "imageUrl": "https://image.panewslab.com/images/logo1.jpg"
        },
        {
          "id": "https://panewslab.com/zh/articledetails/bvvidixc.html",
          "author": "PA一线",
          "description": "PANews 12月13日消息，据彭博社报道，在一份法庭文件中，FTX的美国重组团队指责巴哈马政府干预美国的重组工作。FTX的法律团队表示，在前FTX首席执行官Sam Bankman-Fried（SBF）被阻止进入FTX系统之前，巴哈马要求他铸造价值数亿美元的新代币，然后将这些代币转移到巴哈马官员的控制之下。而当FTX现任CEO John J Ray III和他的团队试图控制FTX的计算机系统时，他们看到有人在铸造新代币。最终，他们得出结论，这是SBF和Gary Wang在巴哈马的要求下工作。\n巴哈马政府官员与SBF密切合作，FTX的美国律师表示，SBF在破产前向巴哈马官方表示可以为当地用户开放提款后的第二天，该平台就流出了1亿美元。\n此前今日早些时候消息，SBF已被巴哈马警方逮捕，美国已对SBF提出刑事指控，并可能要求引渡他。美国纽约南区检察官Damian Williams表示，预计将在当地时间周二上午公布起诉书，届时将有更多消息。纽约时报报道称美国对SBF的刑事指控包括电汇欺诈、证券欺诈和洗钱等多项罪名。",
          "link": "https://panewslab.com/zh/articledetails/bvvidixc.html",
          "publishedOn": "2022-12-13T03:17:31.000Z",
          "wordCount": 3570,
          "title": "FTX律师：巴哈马政府曾要求SBF铸造数亿美元的新代币并上交",
          "imageUrl": "https://image.panewslab.com/images/logo1.jpg"
        },
        {
          "id": "https://panewslab.com/zh/articledetails/up2j83he.html",
          "author": "PA一线",
          "description": "PANews 12月13日消息，据官方公告，Solana的EVM兼容网络开发商Neon Labs今日宣布，因为近期充满挑战的市场环境，许多涉及第三方的业务流程放缓，尽管没有直接受到FTX崩溃的影响，但基金会仍在确定与相关方的文件，从而导致Neon EVM的发布延迟，但Neon EVM的底层代码和机制从技术角度来看已经准备就绪。\n此外，Neon基金会计划在本月发布“早期建设者计划”（Early Builders Program），以将开拓性项目纳入Neon EVM。\n此前11月7日消息，Neon Labs计划于12月12日在Solana上部署以太坊虚拟机Neon EVM。",
          "link": "https://panewslab.com/zh/articledetails/up2j83he.html",
          "publishedOn": "2022-12-13T02:53:04.000Z",
          "wordCount": 3572,
          "title": "Neon Labs：Neon EVM主网启动已推迟，因第三方业务流程放缓",
          "imageUrl": "https://image.panewslab.com/images/logo1.jpg"
        },
        {
          "id": "https://panewslab.com/zh/articledetails/0hwbf1cu.html",
          "author": "PA一线",
          "description": "PANews 12月13日消息，据雅虎体育报道，NBA金州勇士队球星史蒂芬·库里（Stephen Curry）又因为推广NFT系列“无聊猿”Bored Ape Yacht Club面临新的加密诉讼。据悉，两名购买ApeCoin的投资者在洛杉矶联邦法院起诉了“无聊猿”BAYC NFT系列母公司Yuga Labs以及公司高管、董事会成员、以及史蒂芬·库里、麦当娜、帕丽斯·希尔顿、塞雷娜·威廉姆斯、贾斯汀·比伯、吉米·法伦等一众名人。\n据悉，由于FTX Ventures是Yuga Labs的投资方，作为Ape DAO董事会成员的Amy Wu利用她在加密货币交易平台FTX的关系招募史蒂芬·库里以推动BAYC的销售，这些所谓的“名人代言”均未“披露相关的潜在经济利益和关系”。\n此前11月22日消息，美国德州监管机构正调查推广FTX的名人，包括NBA球星库里和NFL球星布拉迪。",
          "link": "https://panewslab.com/zh/articledetails/0hwbf1cu.html",
          "publishedOn": "2022-12-13T02:46:34.000Z",
          "wordCount": 3570,
          "title": "NBA球星斯蒂芬·库里因推广BAYC面临新的加密诉讼",
          "imageUrl": "https://image.panewslab.com/images/logo1.jpg"
        },
        {
          "id": "https://panewslab.com/zh/articledetails/pgwsiaxx.html",
          "author": "PA一线",
          "description": "PANews 12月13日消息，据加密KOL Autism Capital在推特上分享的美国破产法院的文件，该文件披露的一则邮件显示，SBF曾在UTC时间11月10日2:27（北京时间11月10日10:27），即FTX破产前一日与巴哈马官方的邮件交流中表示，可以为当地用户开放提款，使得巴哈马用户可以取得全部资金。\n有网友评论，SBF允许巴哈马提款是为了讨好巴哈马监管机构，而不是应他们的明确要求或由于法规而这样做。根据FTX 11月11日发布的公告，FTX以遵循巴哈马监管机构的规定为由，向巴哈马用户开放提款。该公告的发布早于SBF宣布FTX进入破产程序的推文。\n此前据彭博社报道，巴哈马官员正就FTX资产被冻结（即11月11日FTX宣布破产）后部分用户还可提现一事进行调查，包括FTX高管是否知道此事，或他们在此事中发挥的作用。其中SBF已多次接受调查人员的问询。",
          "link": "https://panewslab.com/zh/articledetails/pgwsiaxx.html",
          "publishedOn": "2022-12-13T02:40:33.000Z",
          "wordCount": 3558,
          "title": "SBF曾在破产前主动向巴哈马官方表示可为当地用户开放提款",
          "imageUrl": "https://image.panewslab.com/images/logo1.jpg"
        },
        {
          "id": "https://panewslab.com/zh/articledetails/0vh66hb5.html",
          "author": "PA一线",
          "description": "PANews 12月13日消息，据欧科云链OKLink多链浏览器数据显示，被标记为孙宇晨的地址(0x176F3DAb24a159341c0509bB36B833E7fdd0a132) 10小时前向Poloniex交易所转入6500枚ETH。目前该地址剩余233,780.57枚ETH，价值2.96亿美元。",
          "link": "https://panewslab.com/zh/articledetails/0vh66hb5.html",
          "publishedOn": "2022-12-13T02:30:46.000Z",
          "wordCount": 3546,
          "title": "数据：孙宇晨钱包地址向Poloniex交易所转入6500枚ETH",
          "imageUrl": "https://image.panewslab.com/images/logo1.jpg"
        },
        {
          "id": "https://panewslab.com/zh/articledetails/kyl5g213.html",
          "author": "PA一线",
          "description": "PANews 12月13日消息，据CoinDesk报道，美国加州北区地方法院上周就CFTC对Ooki DAO的诉讼案举行了听证会，虽然法官William Orrick当天没有做出裁决，但周一他命令CFTC对Ooki DAO的前身实体bZeroX的创始人Tom Bean和Kyle Kistner提起同样的诉讼。\n法官在命令中写道：“在听证会上，CFTC声称其知道Ooki DAO的一些代币持有者居住在美国并在美国开展业务，因为Ooki DAO的前身实体bZeroX的两位创始人是居住在美国的代币持有者。这对我来说是新信息。无论是诉状还是CFTC的替代服务动议，都没有提到前创始人Tom Bean和Kyle Kistner是或曾经是代币持有者。为了提供最佳的可行通知，CFTC应在可能的情况下至少向一位可识别的代币持有人提供告知诉讼的服务。我将推迟输入CFTC关于替代服务动议的动议，直到CFTC做出尝试。”\n此前9月份消息，美国CFTC对Ooki DAO提起诉讼，指控其利用DAO结构逃避监管。随后CFTC向法院申请一项替代服务动议，要求法院批准使用聊天机器人和论坛帖子作为对被告（包括Ooki DAO成员）的送达告知和传票的方式。\n相关阅读：DAO法律结构的探讨：从美国CFTC对Ooki DAO的诉讼说起",
          "link": "https://panewslab.com/zh/articledetails/kyl5g213.html",
          "publishedOn": "2022-12-13T02:04:05.000Z",
          "wordCount": 3585,
          "title": "美国法官命令CFTC对Ooki DAO的两位原创始人提起诉讼",
          "imageUrl": "https://image.panewslab.com/images/logo1.jpg"
        },
        {
          "id": "https://panewslab.com/zh/articledetails/x51lhvao.html",
          "author": "PA一线",
          "description": "PANews 12月13日消息，据纽约时报报道，知情人士透露，美国对前FTX首席执行官Sam Bankman-Fried（SBF）的刑事指控指控包括电汇欺诈、共谋电汇欺诈、证券欺诈、共谋证券欺诈和洗钱。此外，这位知情人士提到，SBF是起诉书中唯一被指控的人。\n福克斯新闻节目对此评论称，如果这些指控罪名成立，SBF可能会面临终身监禁。\n此前今日早些时候消息，SBF已被巴哈马警方逮捕，美国已对SBF提出刑事指控，并可能要求引渡他。美国纽约南区检察官Damian Williams表示，预计将在当地时间周二上午公布起诉书，届时将有更多消息。",
          "link": "https://panewslab.com/zh/articledetails/x51lhvao.html",
          "publishedOn": "2022-12-13T01:39:40.000Z",
          "wordCount": 3548,
          "title": "外媒：美国对SBF的刑事指控包括电汇欺诈、证券欺诈和洗钱等多项罪名",
          "imageUrl": "https://image.panewslab.com/images/logo1.jpg"
        },
        {
          "id": "https://panewslab.com/zh/articledetails/5j6f45zj.html",
          "author": "PA一线",
          "description": "PANews 12月13日消息，据Coindesk报道，链上数据显示，从12月3日至12月7日，106万枚LINK代币通过三笔交易从Aave撤回并转入0xC54开头的地址，该地址在OpenSea上标记为“Oldwhite”。随后，Oldwhite向150多个独立钱包地址各发送了7000枚LINK。而在12月8日Chainlink面向一般用户开放质押后，这150多个独立钱包地址均质押了各自的7000枚LINK代币。\n据悉，Chainlink官方通过将每个钱包地址限制在7000个LINK代币来让更多用户参与质押。而Chainlink社区大使ChainLinkGod.eth在12月8日的推文中承认，没有完美的解决方案可以100%防止鲸鱼在没有交易的情况下进行抵押。\n此前消息，Chainlink质押协议v0.1测试版于12月7日上线以太坊主网，并已于12月9日凌晨向一般用户开放。",
          "link": "https://panewslab.com/zh/articledetails/5j6f45zj.html",
          "publishedOn": "2022-12-13T01:24:59.000Z",
          "wordCount": 3547,
          "title": "某LINK巨鲸使用150多个钱包来规避质押限制，共质押超100万枚LINK",
          "imageUrl": "https://image.panewslab.com/images/logo1.jpg"
        },
        {
          "id": "https://panewslab.com/zh/articledetails/65u38od8.html",
          "author": "PA一线",
          "description": "PANews 12月13日消息，据CoinDesk报道，区块链情报平台Nansen的数据显示，过去24小时内，币安资金净流出达到9.02亿美元，已超过所有其他中心化交易所，几乎是第二大资金流出量的九倍；这也是币安自11月13日（FTX申请破产保护两天后）以来资金净流出的最高水平。\n区块链数据显示，过去7天，大型加密货币做市商Jump Trading和Wintermute等从币安转移了大量资金。Nansen分析师Andrew Thurman在推文中写道，Jump Trading似乎是币安最大的退出者，在过去7天里，与 Jump Trading相关的加密钱包从币安净提取的数字资产达到1.46亿美元。\n此前昨日消息，美国检察官之间的分歧正在推迟对币安的调查的结论，司法部官员已与币安的律师讨论了可能的认罪协议。一些司法部检察官认为有证据证明对包括首席执行官赵在内的高管提出指控是正当的。作为回应，币安称内部安全团队自2021年11月以来已响应超4.7万个执法请求。",
          "link": "https://panewslab.com/zh/articledetails/65u38od8.html",
          "publishedOn": "2022-12-13T00:55:10.000Z",
          "wordCount": 3567,
          "title": "数据：币安过去24小时内资金净流出达9.02亿美元",
          "imageUrl": "https://image.panewslab.com/images/logo1.jpg"
        },
        {
          "id": "https://panewslab.com/zh/articledetails/l4bfmlnp.html",
          "author": "PA一线",
          "description": "PANews 12月13日消息，Web3工具开发商Horizen Labs在推特上宣布，质押APE的奖励现已上线并累积。\n数据显示，ApeCoin官方质押合约内已有超6830万枚APE（或含APE奖励），价值约2.98亿美元。ApeStake.io页面数据显示，APE、BAYC、MAYC、BAKC四个质押池中的APE质押量分别为22218402.36枚、23249624.87枚、8756673.49枚、1897512.32枚，共计约合5612万枚。\n此前12月6日消息，ApeCoin质押系统ApeStake.io已正式上线并开启预存期。",
          "link": "https://panewslab.com/zh/articledetails/l4bfmlnp.html",
          "publishedOn": "2022-12-13T00:39:11.000Z",
          "wordCount": 3555,
          "title": "ApeCoin质押系统ApeStake.io的质押奖励已上线并开始积累",
          "imageUrl": "https://image.panewslab.com/images/logo1.jpg"
        },
        {
          "id": "https://panewslab.com/zh/articledetails/uh9l1ye0.html",
          "author": "PA一线",
          "description": "PANews 12月13日消息，据巴哈马司法部长Ryan Pinder KC发布的一份声明，巴哈马总检察长办公室宣布巴哈马皇家警察部队逮捕了前FTX首席执行官Sam Bankman-Fried（SBF）。SBF是在收到美国的正式通知后被捕的，美国已对SBF提出刑事指控，并可能要求引渡他。文件称，根据收到的通知和所提供的材料，司法部长根据该国的《引渡法》寻求逮捕并拘留SBF是合适的。在提出正式引渡请求时，巴哈马打算根据巴哈马法律及其与美国的条约义务迅速予以处理。该国总理Davis在回应SBF被捕一事时说：“巴哈马和美国在追究所有与FTX有关的人的责任方面有共同利益，他们可能背叛了公众的信任并违反了法律。虽然美国正在对SBF单独提出刑事指控，但巴哈马将继续对FTX的崩溃进行监管和刑事调查，并与美国和其他地方的执法和监管伙伴继续合作。”\n美国纽约南区检察官Damian Williams在推特上表示：“今晚早些时候，巴哈马当局根据其提交的密封起诉书，应美国政府的要求逮捕了SBF，我们预计将在当地时间周二上午公布起诉书，届时将有更多消息。”\n此外据彭博社报道，巴哈马官员正就FTX资产被冻结（即11月11日FTX宣布破产）后部分用户还可提现一事进行调查，包括FTX高管是否知道此事，或他们在此事中发挥的作用。其中SBF已多次接受调查人员的问询。",
          "link": "https://panewslab.com/zh/articledetails/uh9l1ye0.html",
          "publishedOn": "2022-12-12T23:58:48.000Z",
          "wordCount": 3560,
          "title": "SBF已被巴哈马警方逮捕，美国可能会将其引渡",
          "imageUrl": "https://image.panewslab.com/images/logo1.jpg"
        },
        {
          "id": "https://panewslab.com/zh/articledetails/7sdbh1x5.html",
          "author": "PA一线",
          "description": "PANews 12月13日消息，据CoinDesk报道，总部位于百慕大的Jewel Bank周一宣布，它正在发行一种完全由美元支持的稳定币Jewel USD (JUSD)，可以通过Polygon网络访问。Jewel表示，JUSD与美元保持最低1:1的准备金率，确保银行始终有储备资金来支持流通中的每个JUSD。该银行还将对其稳定币储备进行定期审计，并将发布月度和季度报告。Jewel将利用Polygon生态系统实现未来基于商业和零售稳定币的支付解决方案。 据此前消息，今年6月，Jewel Bank获得百慕大金融管理局颁发的全银行和数字资产业务牌照，成为该国第一家数字资产银行。",
          "link": "https://panewslab.com/zh/articledetails/7sdbh1x5.html",
          "publishedOn": "2022-12-12T23:47:01.000Z",
          "wordCount": 3556,
          "title": "百慕大数字银行Jewel Bank将在Polygon发行美元稳定币JUSD",
          "imageUrl": "https://image.panewslab.com/images/logo1.jpg"
        },
        {
          "id": "https://panewslab.com/zh/articledetails/fw2eplgn.html",
          "author": "PA一线",
          "description": "PANews 12月13日消息，据CoinDesk报道，Coinbase周一发布的最新透明度报告显示，其收到的全球执法请求总数同比增加66%，达到12320份。其中来自美国的请求数量最多，共计5304份，同比增长6%，占总数的43%。其次是英国，共有1744份。约80%的请求来自美国、英国、德国和西班牙。超过95%的要求与刑事执法有关，包括传票、法庭命令、搜查令和其他正式法律程序。Coinbase表示，执法请求的增加是由于公司的扩张以及“执法和监管机构对加密行业兴趣的整体增加”。该报告涵盖了2021年10月1日至2022年9月30日。",
          "link": "https://panewslab.com/zh/articledetails/fw2eplgn.html",
          "publishedOn": "2022-12-12T23:44:02.000Z",
          "wordCount": 3539,
          "title": "Coinbase报告：全球执法请求数量同比增加66%，美国占比43%",
          "imageUrl": "https://image.panewslab.com/images/logo1.jpg"
        },
        {
          "id": "https://panewslab.com/zh/articledetails/3uzqdagb.html",
          "author": "PA一线",
          "description": "PANews 12月13日消息，美国众议院金融服务委员会公布了FTX现任首席执行官John Ray准备的证词。Ray表示，FTX的“很大一部分”资产仍然“失踪、被挪用或无法获得”。团队正在继续艰苦的取证工作，以查明所有资产去向。他的新团队迄今为止已经获得了超过10亿美元的数字资产，尽管这只是FTX欠客户和其他债权人数十亿美元的一小部分。FTX US并非独立于母公司FTX.com运营，因此对FTX US申请破产保护是必要的。他还表示，FTX缺乏安全控制，允许Alameda“在没有任何有效限制的情况下”借用FTX的资金，缺乏可靠的财务报表和独立治理。他还证实，FTX在各种投资和收购上花费了大约50亿美元，另外还向内部人士发放了10亿美元的贷款及其它支付。Ray表示，尽管调查仍在进行中，但FTX崩溃似乎源于控制权集中在极少数缺乏经验的个人手中，他们几乎没有实施内部控制。",
          "link": "https://panewslab.com/zh/articledetails/3uzqdagb.html",
          "publishedOn": "2022-12-12T23:29:42.000Z",
          "wordCount": 3546,
          "title": "FTX新任CEO：FTX在投资和收购上花费了大约50亿美元，FTX崩溃源于控制权过度集中",
          "imageUrl": "https://image.panewslab.com/images/logo1.jpg"
        },
        {
          "id": "https://panewslab.com/zh/articledetails/5vhj033a.html",
          "author": "PA一线",
          "description": "PANews 12月13日消息，据The Block报道，FTX创始人SBF在接受Twitter Spaces采访时表示，他将远程参加周二举行的美国众议院金融服务委员会听证会并作证。由于日程繁忙以及担心狗仔队带来的安全问题，他无法亲自前往华盛顿特区。但另一方面，SBF尚未承诺出席美国参议院银行委员会的听证会。该听证会将于周三举行，此前参议院银行委员会主席威胁要向SBF发出传票。SBF表示，他目前暂无出席参议院听证会的计划。但他持开放态度，愿意与委员会主席或高级成员进行对话。他认为这两次听证会在前后两天内举行，因此将“非常相似”。",
          "link": "https://panewslab.com/zh/articledetails/5vhj033a.html",
          "publishedOn": "2022-12-12T23:09:01.000Z",
          "wordCount": 3545,
          "title": "SBF：将远程参加美国众议院听证会，暂无计划出席参议院听证会",
          "imageUrl": "https://image.panewslab.com/images/logo1.jpg"
        }
      ]
    },
    {
      "title": "白话区块链 - 快讯",
      "feedUrl": "https://rsshub.app/hellobtc/news",
      "siteUrl": "https://www.hellobtc.com/news",
      "articles": [
        {
          "id": "https://www.hellobtc.com/news/202212/19080.html",
          "author": null,
          "description": "据火币联合创始人杜均在社交媒体披露，ABCDECapital8月正式对外投资，目前已经领投7个项目，覆盖安全、数据、社交、ZK、NFT等赛道，如@MetatrustLabs、@ScopeProtocol等。 今天Binance占据了75%的市场份额，无论愿意与否，CZ面对监管的态度代表了整个行业的态度，对于CZ这是一个巨大的挑战。FTX事件的影响力远超预期，最近几年传统机构入场最大功臣一个是Coinbase、一个是Circle、另外一个就是FTX。FTX的暴雷，让传统老钱和政府机构对于Crypto世界的混沌无序害怕甚至厌恶，未来很长一段时间里政府不会有更宽松的政策支持Crypto的发展与创新，主权基金也不会把钱放进来。",
          "link": "https://www.hellobtc.com/news/202212/19080.html",
          "publishedOn": "2022-12-13T05:32:00.000Z",
          "wordCount": null,
          "title": "杜均：CZ面对监管的态度是一个巨大挑战",
          "imageUrl": null
        },
        {
          "id": "https://www.hellobtc.com/news/202212/19079.html",
          "author": null,
          "description": "12月13日消息，据韩国媒体报道，韩国釜山数字资产交易所设立推进委员会将于12月19日启动，由15名产学界专家组成，将在落实交易所设立计划中发挥实际作用。釜山市计划明年上半年成立交易所控股公司，明年下半年成立市场管理机构，目标是明年底开始提供服务。根据釜山市的具体计划，釜山市将于明年共设立7家法人，包括1家控股公司、3家子公司和3家市场管理机构。釜山数字资产交易所负责发行、上市、交易和管理数字资产，建立将交易标的分为证券类和非证券类数字资产的制度，设置上市评估、市场监测监管、存管结算三个市场管理机构。（每日经济新闻）",
          "link": "https://www.hellobtc.com/news/202212/19079.html",
          "publishedOn": "2022-12-13T05:32:00.000Z",
          "wordCount": null,
          "title": "韩国釜山数字资产交易所计划于明年底开始提供服务",
          "imageUrl": null
        },
        {
          "id": "https://www.hellobtc.com/news/202212/19078.html",
          "author": null,
          "description": "12月13日消息，美国纽约联储称，最新调查结果显示，美国11月一年期通胀预期下降0.7个百分点，至5.20%，至2021年8月份以来新低。11月三年期通胀预期下降0.1个百分点，至3.00%。（金十）",
          "link": "https://www.hellobtc.com/news/202212/19078.html",
          "publishedOn": "2022-12-13T04:31:00.000Z",
          "wordCount": null,
          "title": "美联储：美国一年期通胀预期下降至2021年以来新低",
          "imageUrl": null
        },
        {
          "id": "https://www.hellobtc.com/news/202212/19077.html",
          "author": null,
          "description": "12月13日消息，Nansen的数据显示，加密交易所持有的ETH共计2530万枚。其中，Coinbase是最大的ETH交易所持有者，持有约871万枚ETH（约110亿美元），占全部交易所持有ETH的34%。币安持有519万枚ETH，位列第二，占比20%。",
          "link": "https://www.hellobtc.com/news/202212/19077.html",
          "publishedOn": "2022-12-13T04:31:00.000Z",
          "wordCount": null,
          "title": "数据：Coinbase持有约871万枚ETH，是最大的ETH交易所持有者",
          "imageUrl": null
        },
        {
          "id": "https://www.hellobtc.com/news/202212/19076.html",
          "author": null,
          "description": "12月13日消息，据Big Crypto Alert，FTX创始人正在取消推特关注其他加密人士，包括知名KOL Cobie等。",
          "link": "https://www.hellobtc.com/news/202212/19076.html",
          "publishedOn": "2022-12-13T04:31:00.000Z",
          "wordCount": null,
          "title": "SBF 正在取消推特关注其他加密人士",
          "imageUrl": null
        },
        {
          "id": "https://www.hellobtc.com/news/202212/19075.html",
          "author": null,
          "description": "12月13日消息，在一份法庭文件中，FTX的美国重组团队指责巴哈马政府干预美国的重组工作。FTX的法律团队表示，在前FTX首席执行官Sam Bankman-Fried（SBF）被阻止进入FTX系统之前，巴哈马要求他铸造价值数亿美元的新代币，然后将这些代币转移到巴哈马官员的控制之下。而当FTX现任CEO John J Ray III和他的团队试图控制FTX的计算机系统时，他们看到有人在铸造新代币。最终，他们得出结论，这是SBF和Gary Wang在巴哈马的要求下工作。 巴哈马政府官员与SBF密切合作，FTX的美国律师表示，SBF在破产前向巴哈马官方表示可以为当地用户开放提款后的第二天，该平台就流出了1亿美元。 此前今日早些时候消息，SBF已被巴哈马警方逮捕，美国已对SBF提出刑事指控，并可能要求引渡他。美国纽约南区检察官Damian Williams表示，预计将在当地时间周二上午公布起诉书，届时将有更多消息。纽约时报报道称美国对SBF的刑事指控包括电汇欺诈、证券欺诈和洗钱等多项罪名。（彭博社）",
          "link": "https://www.hellobtc.com/news/202212/19075.html",
          "publishedOn": "2022-12-13T04:30:00.000Z",
          "wordCount": null,
          "title": "FTX律师：巴哈马政府曾要求SBF铸造数亿美元的新代币并上交",
          "imageUrl": null
        },
        {
          "id": "https://www.hellobtc.com/news/202212/19074.html",
          "author": null,
          "description": "12月13日消息，据福克斯新闻节目披露，FTX创始人Sam Bankman-Fried（SBF）被指控电汇欺诈、证券欺诈和洗钱等罪名，这意味着如果指控罪名成立，SBF可能会面临终身监禁。",
          "link": "https://www.hellobtc.com/news/202212/19074.html",
          "publishedOn": "2022-12-13T04:29:00.000Z",
          "wordCount": null,
          "title": "福克斯：如果指控罪名成立，SBF可能会面临终身监禁",
          "imageUrl": null
        },
        {
          "id": "https://www.hellobtc.com/news/202212/19073.html",
          "author": null,
          "description": "12月13日消息，NBA金州勇士队球星史蒂芬·库里又因为推广NFT系列“无聊猿”Bored Ape Yacht Club面临新的加密诉讼。据悉，两名购买ApeCoin的投资者在洛杉矶联邦法院起诉了“无聊猿”BAYC NFT系列母公司Yuga Labs以及公司高管、董事会成员、以及史蒂芬·库里、麦当娜、帕丽斯·希尔顿、塞雷娜·威廉姆斯、贾斯汀·比伯、吉米·法伦等一众名人。 据悉，由于FTX Ventures是Yuga Labs的投资方，作为Ape DAO董事会成员的Amy Wu利用她在加密货币交易平台FTX的关系招募史蒂芬·库里以推动BAYC的销售，这些所谓的“名人代言”均未“披露相关的潜在经济利益和关系”。",
          "link": "https://www.hellobtc.com/news/202212/19073.html",
          "publishedOn": "2022-12-13T01:45:00.000Z",
          "wordCount": null,
          "title": "库里因推广“无聊猿”BAYC遭投资者起诉",
          "imageUrl": null
        },
        {
          "id": "https://www.hellobtc.com/news/202212/19072.html",
          "author": null,
          "description": "12月13日消息，据《纽约时报》援引知情人士消息称，SBF被起诉的指控包括电汇欺诈、共谋电汇欺诈、证券欺诈、共谋证券欺诈和洗钱。此外，这位知情人士提到，SBF是起诉书中唯一被指控的人，已被巴哈马当局拘留。 此前消息，美国纽约南区检察官 Damian Williams 表示，预计将在周二早上（美国当地时间）公开起诉书，届时会有更多信息披露。（纽约时报）",
          "link": "https://www.hellobtc.com/news/202212/19072.html",
          "publishedOn": "2022-12-13T01:44:00.000Z",
          "wordCount": null,
          "title": "知情人士：SBF被指控电汇欺诈、共谋电汇欺诈、证券欺诈、共谋证券欺诈和洗钱",
          "imageUrl": null
        },
        {
          "id": "https://www.hellobtc.com/news/202212/19071.html",
          "author": null,
          "description": "摩根大通的新研究显示，大约13%的美国人口约4300万人持有加密货币，报告显示这个数字相比较于2020年之前大幅上升，当时这个数字只有3%左右。该研究还指出，加密货币持有人通常在加密货币价格飙升期间进行首次加密货币购买。（Cointelegraph）",
          "link": "https://www.hellobtc.com/news/202212/19071.html",
          "publishedOn": "2022-12-13T01:44:00.000Z",
          "wordCount": null,
          "title": "摩根大通报告：13%的美国人持有加密货币",
          "imageUrl": null
        }
      ]
    },
    {
      "title": "TheBlockBeats - 快讯",
      "feedUrl": "https://rsshub.app/blockbeats/flash",
      "siteUrl": "https://www.theblockbeats.info",
      "articles": [
        {
          "id": "https://www.theblockbeats.info/flash/119171",
          "author": null,
          "description": "BlockBeats 消息，12 月 13 日，据 ApeCoin 官方质押合约数据显示，当前 APE 质押量已经突破 7000 万枚，达 7015 万枚，价值逾 3 亿美元。",
          "link": "https://www.theblockbeats.info/flash/119171",
          "publishedOn": "2022-12-13T02:36:23.000Z",
          "wordCount": null,
          "title": "数据：APE质押量超7000万枚，价值逾3亿美元",
          "imageUrl": null
        },
        {
          "id": "https://www.theblockbeats.info/flash/119162",
          "author": null,
          "description": "BlockBeats 消息，12 月 13 日，据披露邮件显示，SBF 曾在 11 月 10 日，即 FTX 崩盘当日与巴哈马官方的邮件交流中表示，可以为当地用户开放提款，使得巴哈马用户可以取得全部资金。",
          "link": "https://www.theblockbeats.info/flash/119162",
          "publishedOn": "2022-12-13T01:57:23.000Z",
          "wordCount": null,
          "title": "SBF曾在崩盘当日向巴哈马官方表示可以为当地用户开放提款",
          "imageUrl": null
        },
        {
          "id": "https://www.theblockbeats.info/flash/119159",
          "author": null,
          "description": "BlockBeats 消息，12 月 13 日，据纽约时报援引消息人士报道，FTX 创始人 Sam Bankman-Fried（SBF）被指控犯有电汇欺诈、电汇欺诈共谋、证券欺诈、证券欺诈共谋和洗钱罪。此外 DB NEWSWIRE 发推表示「他也是目前唯一被起诉的人」。此前巴哈马当局应美国政府的要求逮捕了 SBF，美国纽约南区检察官表示将公布起诉书。",
          "link": "https://www.theblockbeats.info/flash/119159",
          "publishedOn": "2022-12-13T01:57:23.000Z",
          "wordCount": null,
          "title": "《纽约时报》：SBF被指控电汇欺诈、证券欺诈和洗钱等罪名",
          "imageUrl": null
        },
        {
          "id": "https://www.theblockbeats.info/flash/119129",
          "author": null,
          "description": "BlockBeats 消息，12 月 13 日，FTX 新任首席执行官兼首席重组官 John J. Ray III 的听证会证词讲稿显示，FTX 资产的「很大一部分」仍然「丢失、被挪用或无法获得」，此外他表示 FTX US 不是独立于 FTX 运营的，FTX 缺乏安全控制，允许 Alameda「没有任何有效限制」借入 FTX 的资金，同时资产混合以及缺乏「可靠的财务报表」和独立治理只是他发现的问题的一部分。\n\n此外，他还证实，FTX 在各种投资和收购上花费了约 50 亿美元，另外 10 亿美元作为贷款和其他付款流向内部人士，特别是这些收购和投资可能不再具有最初的价值。",
          "link": "https://www.theblockbeats.info/flash/119129",
          "publishedOn": "2022-12-13T00:57:23.000Z",
          "wordCount": null,
          "title": "FTX新任CEO：FTX曾在各种投资和收购上花费约50亿美元",
          "imageUrl": null
        },
        {
          "id": "https://www.theblockbeats.info/flash/119126",
          "author": null,
          "description": "BlockBeats 消息，12 月 13 日，据彭博社援引消息人士报道，巴哈马官员正在调查 FTX 高管是否知道或在 FTX 资产被冻结后的用户提现中发挥了作用，其中 SBF 已多次接受调查人员的问询。",
          "link": "https://www.theblockbeats.info/flash/119126",
          "publishedOn": "2022-12-13T00:57:23.000Z",
          "wordCount": null,
          "title": "知情人士：巴哈马正调查 FTX 资产被冻结后的用户提现事件",
          "imageUrl": null
        },
        {
          "id": "https://www.theblockbeats.info/flash/119123",
          "author": null,
          "description": "BlockBeats 消息，12 月 13 日，美国纽约南区检察官 Damian Williams 表示，今晚早些时候，巴哈马当局根据 SDNY（美国纽约南区法院）提交的密封起诉书，应美国政府的要求逮捕了 Samuel Bankman-Fried。法院预计将在明天早上公开起诉书，届时将披露更多信息。",
          "link": "https://www.theblockbeats.info/flash/119123",
          "publishedOn": "2022-12-13T00:57:23.000Z",
          "wordCount": null,
          "title": "美国纽约南区法院：预计将于明日公布针对SBF的起诉书",
          "imageUrl": null
        },
        {
          "id": "https://www.theblockbeats.info/flash/119141",
          "author": null,
          "description": "BlockBeats 消息，12 月 13 日，美国纽约联储称，最新调查结果显示，美国 11 月一年期通胀预期下降 0.7 个百分点，至 5.20%，至 2021 年 8 月份以来新低。11 月三年期通胀预期下降 0.1 个百分点，至 3.00%。（金十）",
          "link": "https://www.theblockbeats.info/flash/119141",
          "publishedOn": "2022-12-13T00:54:51.000Z",
          "wordCount": null,
          "title": "美联储：美国一年期通胀预期下降至2021年以来新低",
          "imageUrl": null
        },
        {
          "id": "https://www.theblockbeats.info/flash/119117",
          "author": null,
          "description": "BlockBeats 消息，12 月 13 日，FTX 创始人 SBF 已被巴哈马警方逮捕。\n\n文件显示，巴哈马警方在收到美国正式通知后逮捕了 SBF，该通知表示美国已经对 SBF 提出刑事指控，并可能要求引渡 SBF。",
          "link": "https://www.theblockbeats.info/flash/119117",
          "publishedOn": "2022-12-12T23:57:23.000Z",
          "wordCount": null,
          "title": "FTX创始人SBF已被巴哈马警方逮捕",
          "imageUrl": null
        }
      ]
    },
    {
      "title": "深潮TechFlow - 快讯",
      "feedUrl": "https://rsshub.app/techflowpost/express",
      "siteUrl": "https://www.techflowpost.com/express",
      "articles": [
        {
          "id": "https://www.techflowpost.com/express/5846",
          "author": null,
          "description": "深潮 TechFlow 消息，据彭博社报道，在一份法庭文件中，FTX的美国重组团队指责巴哈马政府干预美国的重组工作。FTX的法律团队表示，在前FTX首席执行官Sam Bankman-Fried（SBF）被阻止进入FTX系统之前，巴哈马要求他铸造价值数亿美元的新代币，然后将这些代币转移到巴哈马官员的控制之下。而当FTX现任CEO John J Ray III和他的团队试图控制FTX的计算机系统时，他们看到有人在铸造新代币。最终，他们得出结论，这是SBF和Gary Wang在巴哈马的要求下工作。\n巴哈马政府官员与SBF密切合作，FTX的美国律师表示，SBF在破产前向巴哈马官方表示可以为当地用户开放提款后的第二天，该平台就流出了1亿美元。\n此前今日早些时候消息，SBF已被巴哈马警方逮捕，美国已对SBF提出刑事指控，并可能要求引渡他。美国纽约南区检察官Damian Williams表示，预计将在当地时间周二上午公布起诉书，届时将有更多消息。纽约时报报道称美国对SBF的刑事指控包括电汇欺诈、证券欺诈和洗钱等多项罪名。原文链接",
          "link": "https://www.techflowpost.com/express/5846",
          "publishedOn": "2022-12-13T03:20:36.000Z",
          "wordCount": null,
          "title": "FTX律师：巴哈马政府曾要求SBF铸造数亿美元的新代币并上交",
          "imageUrl": null
        },
        {
          "id": "https://www.techflowpost.com/express/5845",
          "author": null,
          "description": "深潮 TechFlow 消息，12月13日，据 Big Crypto Alert，FTX创始人SBF正在取消关注推特加密人士，包括知名 KOL Cobie 等。原文链接",
          "link": "https://www.techflowpost.com/express/5845",
          "publishedOn": "2022-12-13T03:07:04.000Z",
          "wordCount": null,
          "title": "SBF 正在取消关注推特加密人士",
          "imageUrl": null
        },
        {
          "id": "https://www.techflowpost.com/express/5844",
          "author": null,
          "description": "深潮 TechFlow 消息，Solana EVM兼容方案Neon发文表示，由于涉及第三方的备案程序，Neon EVM兼容主网的发布已推迟，但关于底层代码和机制等技术准备已就绪，此外Neon基金会计划在本月发布“早期建设者计划”（Early Builders Program），以将开拓性项目纳入Neon EVM。原文链接",
          "link": "https://www.techflowpost.com/express/5844",
          "publishedOn": "2022-12-13T02:48:06.000Z",
          "wordCount": null,
          "title": "Solana EVM兼容方案Neon已推迟发布，“早期建设者计划”将纳入其中",
          "imageUrl": null
        },
        {
          "id": "https://www.techflowpost.com/express/5843",
          "author": null,
          "description": "深潮 TechFlow 消息，12 月 12 日，全球顶级加密货币交易所 BitMart 宣布正式加入 Pyth Network 数据发布者生态，为 Pyth 贡献其独有的交易所数字资产市场数据，同时寻求更多使用 Pyth 喂价数据的用户场景。\nBitMart 是一个全球领先的数字资产交易平台，在全世界拥有数百万用户，是 CoinGecko 上的顶级加密货币交易所。BitMart 目前提供 1,000+ 交易对，是行业内费率最低的交易所之一。\nBitMart 还在持续发展和增长，并对推动 Crypto 创新和促进金融包容性发展充满兴趣。\n来自 Jump Crypto 特别项目部门的 Pyth 核心贡献者 Stephen Kaminsky 表示：“虽然行业最近正在经历动荡时期，但我们仍然致力于与真正有用并能够为行业提供价值的核心项目达成合作。Pyth Network 正是如此，BitMart 与 Pyth 的合作共同推进 Pyth 的使命，这恰恰证明了这个行业的持续发展。”\n截止目前，Pyth network 已拥有 75+ 世界领先金融机构、交易所等一手数据所有者组成的数据发布者网络。阅读原文",
          "link": "https://www.techflowpost.com/express/5843",
          "publishedOn": "2022-12-13T01:55:24.000Z",
          "wordCount": null,
          "title": "顶级加密货币交易所 BitMart 宣布正式加入 Pyth Network 数据发布者生态",
          "imageUrl": null
        },
        {
          "id": "https://www.techflowpost.com/express/5842",
          "author": null,
          "description": "深潮 TechFlow 消息，据SBF发给巴哈马政府的邮件披露，SBF曾在11月10日，即FTX崩盘当日与巴哈马官方的邮件交流中表示，可以为当地用户开放提款，使得巴哈马用户可以取得全部资金。\n此前报道，11月13日，巴哈马证券委员会（SCB）表示，FTX近期已经开始处理部分巴哈马用户的提现，但是SCB没有指示、授权或建议FTX Digital Markets优先处理巴哈马客户的提现。原文链接",
          "link": "https://www.techflowpost.com/express/5842",
          "publishedOn": "2022-12-13T01:51:34.000Z",
          "wordCount": null,
          "title": "SBF曾在崩盘当日向巴哈马官方表示可以为当地客户开放提款",
          "imageUrl": null
        },
        {
          "id": "https://www.techflowpost.com/express/5841",
          "author": null,
          "description": "深潮 TechFlow 消息，据CoinDesk报道，区块链情报平台Nansen的数据显示，过去24小时内，币安资金净流出达到9.02亿美元，已超过所有其他中心化交易所，几乎是第二大资金流出量的九倍；这也是币安自11月13日（FTX申请破产保护两天后）以来资金净流出的最高水平。\n区块链数据显示，过去7天，大型加密货币做市商Jump Trading和Wintermute等从币安转移了大量资金。Nansen分析师Andrew Thurman在推文中写道，Jump Trading似乎是币安最大的退出者，在过去7天里，与 Jump Trading相关的加密钱包从币安净提取的数字资产达到1.46亿美元。\n此前昨日消息，美国检察官之间的分歧正在推迟对币安的调查的结论，司法部官员已与币安的律师讨论了可能的认罪协议。一些司法部检察官认为有证据证明对包括首席执行官赵在内的高管提出指控是正当的。作为回应，币安称内部安全团队自2021年11月以来已响应超4.7万个执法请求。原文链接",
          "link": "https://www.techflowpost.com/express/5841",
          "publishedOn": "2022-12-13T01:35:36.000Z",
          "wordCount": null,
          "title": "数据：币安过去24小时内资金净流出达9.02亿美元",
          "imageUrl": null
        },
        {
          "id": "https://www.techflowpost.com/express/5840",
          "author": null,
          "description": "深潮 TechFlow 消息，NBA金州勇士队球星史蒂芬·库里又因为推广NFT系列“无聊猿”Bored Ape Yacht Club面临新的加密诉讼。据悉，两名购买ApeCoin的投资者在洛杉矶联邦法院起诉了“无聊猿”BAYC NFT系列母公司Yuga Labs以及公司高管、董事会成员、以及史蒂芬·库里、麦当娜、帕丽斯·希尔顿、塞雷娜·威廉姆斯、贾斯汀·比伯、吉米·法伦等一众名人。\n据悉，由于FTX Ventures是Yuga Labs的投资方，作为Ape DAO董事会成员的Amy Wu利用她在加密货币交易平台FTX的关系招募史蒂芬·库里以推动BAYC的销售，这些所谓的“名人代言”均未“披露相关的潜在经济利益和关系”。原文链接",
          "link": "https://www.techflowpost.com/express/5840",
          "publishedOn": "2022-12-13T01:33:15.000Z",
          "wordCount": null,
          "title": "库里因推广“无聊猿”BAYC遭投资者起诉",
          "imageUrl": null
        },
        {
          "id": "https://www.techflowpost.com/express/5839",
          "author": null,
          "description": "深潮 TechFlow 消息，据《纽约时报》援引知情人士消息称，SBF 被起诉的指控包括电汇欺诈、共谋电汇欺诈、证券欺诈、共谋证券欺诈和洗钱。此外，这位知情人士提到，SBF 是起诉书中唯一被指控的人，已被巴哈马当局拘留。\n此前消息，美国纽约南区检察官 Damian Williams 表示，预计将在周二早上（美国当地时间）公开起诉书，届时会有更多信息披露。纽约时报",
          "link": "https://www.techflowpost.com/express/5839",
          "publishedOn": "2022-12-13T01:31:56.000Z",
          "wordCount": null,
          "title": "知情人士：SBF 被指控电汇欺诈、证券欺诈和洗钱等",
          "imageUrl": null
        },
        {
          "id": "https://www.techflowpost.com/express/5838",
          "author": null,
          "description": "深潮 TechFlow 消息，百慕大数字资产银行Jewel Bank计划发行Polygon网络的锚定美元稳定币Jewel USD（JUSD），将与美元保持至少1:1的准备金率，确保始终在其储备中拥有足额资金来支持每个流通中的JUSD。Jewel Bank表示还将对其稳定币储备进行定期审计，并将提供月度和季度报告。\n此前报道，百慕大数字资产银行Jewel Bank宣布已获得百慕大金融管理局（BMA）颁发的完整的银行和数字资产业务许可证。Jewel Bank将发行稳定币，并为全球数字资产机构提供与银行存款直接绑定的实时结算服务。原文链接",
          "link": "https://www.techflowpost.com/express/5838",
          "publishedOn": "2022-12-13T01:27:18.000Z",
          "wordCount": null,
          "title": "数字资产银行Jewel Bank计划发行基于Polygon的美元稳定币JUSD",
          "imageUrl": null
        },
        {
          "id": "https://www.techflowpost.com/express/5837",
          "author": null,
          "description": "深潮 TechFlow 消息，据FTX现任首席执行官兼首席重组官John J. Ray III的听证会证词讲稿显示，FTX的“很大一部分”资产仍然“失踪、被挪用或无法获得”。团队正在继续艰苦的取证工作，以查明所有资产去向。他的新团队迄今为止已经获得了超过10亿美元的数字资产，尽管这只是FTX欠客户和其他债权人数十亿美元的一小部分。FTX US并非独立于母公司FTX.com运营，因此对FTX US申请破产保护是必要的。FTX缺乏安全控制，允许Alameda“在没有任何有效限制的情况下”借用FTX的资金，缺乏可靠的财务报表和独立治理。\n此外，他还证实，FTX在各种投资和收购上花费了约50亿美元，另外10亿美元作为贷款和其他付款流向内部人士，特别是这些收购和投资可能不再具有最初的价值。原文链接",
          "link": "https://www.techflowpost.com/express/5837",
          "publishedOn": "2022-12-13T01:26:27.000Z",
          "wordCount": null,
          "title": "FTX现任CEO：FTX在各种投资和收购上花费约50亿美元",
          "imageUrl": null
        },
        {
          "id": "https://www.techflowpost.com/express/5836",
          "author": null,
          "description": "深潮 TechFlow 消息，Web3 元宇宙初创公司 MetaVersusWorld 宣布完成 200 万美元种子轮融资，Alphabit Digital Currency Fund、Xeta Capital、Launchpool、Westridge Markets、NetZero Capital、XSquared Ventures、GBIC、Alpha Sigma Capital 和 FBG Capital 等参投。部分资金已用于 Steam 封闭式 alpha 产品发布的虚幻引擎 5 开发，计划于 2022 年第四季度发布。\n据悉，MetaVersusWorld 开发超现实且支持互动的虚拟多元宇宙，主要提供元宇宙商务、游戏和 Web3 IP 市场拓展等服务，该公司正在寻求额外筹集 300 万美元，以进一步扩展其平台和产品。来源链接",
          "link": "https://www.techflowpost.com/express/5836",
          "publishedOn": "2022-12-13T01:25:12.000Z",
          "wordCount": null,
          "title": "元宇宙公司 MetaVersusWorld 完成 200 万美元种子轮融资",
          "imageUrl": null
        },
        {
          "id": "https://www.techflowpost.com/express/5835",
          "author": null,
          "description": "深潮 TechFlow 消息 12月13日，美国纽约南区检察官 Damian Williams 表示，今晚早些时候，巴哈马当局根据 SDNY （美国纽约南区法院）提交的密封起诉书，应美国政府的要求逮捕了 Samuel Bankman-Fried，我们预计将在明天早上公开起诉书，届时会有更多话要说。",
          "link": "https://www.techflowpost.com/express/5835",
          "publishedOn": "2022-12-13T00:14:31.000Z",
          "wordCount": null,
          "title": "美国纽约南区法院：预计将于明天早上公布针对 SBF 的起诉书",
          "imageUrl": null
        },
        {
          "id": "https://www.techflowpost.com/express/5834",
          "author": null,
          "description": "深潮 TechFlow 消息 12 月 13 日，FTX 创始人 SBF 已被巴哈马警方逮捕。巴哈马总检察长参议员 Ryan Pinder KC发布了 关于逮捕 Sam Bankman-Fried 的声明，显示巴哈马警方在收到美国正式通知后逮捕了 SBF，并表示已经对 SBF 提出刑事指控，可能要求引渡 SBF。",
          "link": "https://www.techflowpost.com/express/5834",
          "publishedOn": "2022-12-12T23:51:20.000Z",
          "wordCount": null,
          "title": "收到美国正式通知后，FTX创始人SBF已被巴哈马警方逮捕",
          "imageUrl": null
        },
        {
          "id": "https://www.techflowpost.com/express/5833",
          "author": null,
          "description": "深潮 TechFlow 消息，加密保险公司Evertas完成1400万美元A轮融资，Polychain Capital领投，SinoGlobal Capital、CMT Digital Ventures、Foundation Capital、Morgan Creek、Bloccelerate、network0、Matrixport和HashKey、Balaji Srinivasan、Andrew Keys、Colleen Sullivan、Patrick McDonald和David Roebuck等参投。加上去年获得的580万美元种子资金Evertas的外部投资总额达到1980万美元。原文链接",
          "link": "https://www.techflowpost.com/express/5833",
          "publishedOn": "2022-12-12T14:24:24.000Z",
          "wordCount": 7817,
          "title": "加密保险公司Evertas完成1400万美元A轮融资，Polychain Capital领投",
          "imageUrl": null
        },
        {
          "id": "https://www.techflowpost.com/express/5832",
          "author": null,
          "description": "深潮 TechFlow 消息，针对路透社的报道，币安回应表示，路透社正在攻击其执法团队，并发布发给记者的完整声明和的执法团队的博客。\n币安表示，在2022年，其执法团队响应超过47,000项执法请求；安全和合规人员人数增加了500%以上；与全球执法部门一起参加了70多个反网络犯罪研讨会；成为第一家加入国家网络取证和培训联盟 (NCFTA) 的区块链和加密货币公司。原文链接",
          "link": "https://www.techflowpost.com/express/5832",
          "publishedOn": "2022-12-12T13:33:45.000Z",
          "wordCount": null,
          "title": "币安：路透社正在攻击其执法团队，今年已响应超过47,000项执法请求",
          "imageUrl": null
        },
        {
          "id": "https://www.techflowpost.com/express/5831",
          "author": null,
          "description": "深潮 TechFlow 消息，据 TechCrunch 报道，Web3 初创公司 Nillion 宣布完成 2000 万美元融资，Distributed Global 领投，AU21、Big Brain Holdings、Chapter One、GSR、HashKey、OP Crypto 和 SALT Fund 等参投。\nNillion 旨在建立一个不基于区块链的去中心化网络，并提供一个全新的互联网基础设施以保护存储和数据计算，让企业和竞争对手可以在不传递关键信息的情况下进行合作。另外，该公司早期文件透露未来将会发行 Token。来源链接",
          "link": "https://www.techflowpost.com/express/5831",
          "publishedOn": "2022-12-12T13:32:06.000Z",
          "wordCount": 7857,
          "title": "Web3 初创公司 Nillion 完成 2000 万美元融资，Distributed Global 领投",
          "imageUrl": null
        },
        {
          "id": "https://www.techflowpost.com/express/5830",
          "author": null,
          "description": "深潮 TechFlow 消息 12月12日，据路透社援引消息人士报道，美国司法部的检察官对是否向币安提起包括洗钱在内的诉讼产生了分歧，部分检察官认为已掌握到了最够的证据，可以对赵长鹏在内的币安高管提起诉讼，部分检察官则认为需要时间来审查更多证据。知情人士表示，美国司法部对币安的调查始于 2018 年，内容包括无证汇款、洗钱和违反刑事制裁。此外，消息人士称司法部的官员已与币安律师讨论了可能的认罪协议。",
          "link": "https://www.techflowpost.com/express/5830",
          "publishedOn": "2022-12-12T12:46:15.000Z",
          "wordCount": null,
          "title": "路透社：美国司法部对是否向币安提起诉讼产生了内部分歧",
          "imageUrl": null
        },
        {
          "id": "https://www.techflowpost.com/express/5829",
          "author": null,
          "description": "深潮 TechFlow 消息，12月12日，USDD官方推特发文透露USDD当前抵押率超过200%，USDD官方推特表示，目前USDD储备资产为14040.6枚BTC、109亿枚TRX和3.92亿枚USDC，以当前价计共14.55亿美金，是USDD发行总额7.25亿美金的2倍，USDD当前实时抵押率为200.77%。综上，波联储的储备资产是稳定的、充足的、健康的，USDD的币值是稳定可靠的。持有者应对此有理性的认知。\nUSDD团队表示，欢迎持有者随时通过USDD官网（usdd.io) 以及波联储TRON DAO Reserve官网 (tdr.org) 公开查询USDD抵押率，保持理性认知。\nUSDD是全球首个去中心化超抵押稳定币。目前，USDD已获得Huobi、Poloniex、Kucoin、Bybit、Gate等一批CEX和Sun.io、ellipsis等DeFi协议的支持，并于10月7日在多米尼克获得法定数字货币地位。USDD是继比特币之后，世界上第二批被授予法定数字货币资格的加密货币之一。",
          "link": "https://www.techflowpost.com/express/5829",
          "publishedOn": "2022-12-12T09:54:54.000Z",
          "wordCount": null,
          "title": "USDD实时抵押率超200%，抵押资产总价值远高于USDD流通总价值",
          "imageUrl": null
        },
        {
          "id": "https://www.techflowpost.com/express/5828",
          "author": null,
          "description": "深潮 TechFlow 消息，12月12日，波场TRON创始人、火必Huobi全球顾问委员会成员孙宇晨在其官方推特账号连发两条USDD相关推文，他首先表示，USDD目前抵押率超200%。您可以24 * 7查询所有实时数据。孙宇晨还在此条推文中附上了USDD官网链接以供实时查询。孙宇晨随后在第二条USDD相关推文中表示，未来将为USDD部署更多资金。\n官方数据显示，去中心化超抵押稳定币USDD当前抵押率超 200%，抵押率远高于DAI、USDT等主要稳定币。\n截至发稿时为止，USDD抵押资产包括14040.6枚BTC、392,588,333枚USDC、4枚USDT和10,911,996,879枚TRX，实时抵押率为200.84%，抵押资产经过第三方严格审计，并由去中心化组织管理，资金流动透明公开。\n请用户勿信传言，一切数据以USDD官网为准。原文链接",
          "link": "https://www.techflowpost.com/express/5828",
          "publishedOn": "2022-12-12T09:27:54.000Z",
          "wordCount": null,
          "title": "孙宇晨：USDD抵押率超200%，将部署更多资金，实时抵押率7*24可查",
          "imageUrl": null
        },
        {
          "id": "https://www.techflowpost.com/express/5827",
          "author": null,
          "description": "深潮 TechFlow 消息，针对USDD脱锚，孙宇晨表示部署更多资本。查询链上数据发现，孙宇晨地址通过1inch v5购买约101.8万USDD。\n此外，Curve上的USDD/3Crv流动性池USDD下降至82.33%。\n此前消息，数据：USDD脱锚至0.97美元，Curve上USDD/3Crv池的倾斜占比超85%。原文链接",
          "link": "https://www.techflowpost.com/express/5827",
          "publishedOn": "2022-12-12T09:24:48.000Z",
          "wordCount": null,
          "title": "孙宇晨通过1inch v5购买约101.8万USDD",
          "imageUrl": null
        },
        {
          "id": "https://www.techflowpost.com/express/5826",
          "author": null,
          "description": "深潮 TechFlow 消息，12月13日， THUBA将邀请多位重量级嘉宾，从Web3明星企业项目负责人到BAYC中国代表，以及清北高校Web3学子，一起交流NFT和web3行业经历与思考。详情链接",
          "link": "https://www.techflowpost.com/express/5826",
          "publishedOn": "2022-12-12T09:24:28.000Z",
          "wordCount": null,
          "title": "从NFT看Web3.0：清北学生联盟与大咖的鸡尾酒夜会即将开始",
          "imageUrl": null
        },
        {
          "id": "https://www.techflowpost.com/express/5825",
          "author": null,
          "description": "深潮 TechFlow 消息，波卡生态DeFi平台Parallel Finance旗下NFT借贷协议ParaSpace发文表示，计划在12月16日前转向时间锁合约并启动论坛，以使得团队和社区可以就提案进行讨论。此外，原本计划于2023年第二季度发行治理Token和创建DAO的计划将提前至第一季度进行。原文链接",
          "link": "https://www.techflowpost.com/express/5825",
          "publishedOn": "2022-12-12T09:24:05.000Z",
          "wordCount": null,
          "title": "NFT借贷协议ParaSpace拟于2023年第一季度发行治理Token",
          "imageUrl": null
        },
        {
          "id": "https://www.techflowpost.com/express/5824",
          "author": null,
          "description": "深潮 TechFlow 消息，Huobi定于2022年12月12日上线MAGIC（Magic）。\nMAGIC 存款将于 12 月 12 日 09:30（UTC）开放。\nMAGIC现货交易（MAGIC/USDT）将在充值量满足市场交易需求时开启，具体时间以官方公告为准。\nMAGIC 提款将于 12 月 13 日 14:00（UTC）开放。\n合约地址（Arbitrum）： 0x539bdE0d7Dbd336b79148AA742883198BBF60342\nMAGIC官网\n原文链接",
          "link": "https://www.techflowpost.com/express/5824",
          "publishedOn": "2022-12-12T09:14:36.000Z",
          "wordCount": null,
          "title": "Huobi将于今日17:30上线MAGIC",
          "imageUrl": null
        },
        {
          "id": "https://www.techflowpost.com/express/5823",
          "author": null,
          "description": "深潮 TechFlow 消息，0xPlasma Labs 在 Uniswap 社区发起新提案，建议在 BNB Chain 上部署 Uniswap V3。提案指出，BNB Chain 拥有庞大且不断增长的用户群，为 Uniswap v3 提供了一个潜在的新市场。目前该提案尚在社区讨论阶段。原文链接",
          "link": "https://www.techflowpost.com/express/5823",
          "publishedOn": "2022-12-12T08:56:27.000Z",
          "wordCount": null,
          "title": "Uniswap社区新提案：建议在BNB Chain上部署Uniswap V3",
          "imageUrl": null
        },
        {
          "id": "https://www.techflowpost.com/express/5822",
          "author": null,
          "description": "深潮 TechFlow 消息，12月12日，Nansen 创始人 Alex Svanevik 发布推特表示，2023 年将是针对加密初创公司的一场大屠杀：\n1. 大多数 21/22 年诞生的种子初创公司都没有钱；\n2. 一些被收购；\n3. 少数能进行新一轮融资（ >80%不得不以低于前一轮融资的估值来融资）；\n4.技术人员工资下降；\n5. 技术职位缩水；\n6. VC投资其他领域（人工智能等）。\n原文链接",
          "link": "https://www.techflowpost.com/express/5822",
          "publishedOn": "2022-12-12T05:51:28.000Z",
          "wordCount": 7875,
          "title": "Nansen 创始人：2023 年将是针对加密初创公司的一场大屠杀",
          "imageUrl": null
        },
        {
          "id": "https://www.techflowpost.com/express/5821",
          "author": null,
          "description": "深潮 TechFlow 消息，官方消息，波场Poloniex全新合约交易大赛正式开启，奖品包括玛莎拉蒂Ghibli、特斯拉Model 3、iPhone 14 Pro Max等，总价值高达百万美金。本次合约交易大赛一共设置五大奖项：任务奖、战队奖、大师奖、豪车奖、幸运奖，100%有奖。参赛用户邀请好友注册并报名，即享高达80%返佣奖励。\nPoloniex合约产品自上线两年以来，服务了全球数百万用户，深受广大用户喜爱。本次合约交易大赛旨在回馈平台用户长期的关注与支持。\n即刻报名：https://poloniex.com/campaigns/futures-championship-2nd/home",
          "link": "https://www.techflowpost.com/express/5821",
          "publishedOn": "2022-12-12T04:35:05.000Z",
          "wordCount": 7832,
          "title": "波场Poloniex全新合约交易大赛，玛莎拉蒂等百万美金奖励放送",
          "imageUrl": null
        },
        {
          "id": "https://www.techflowpost.com/express/5820",
          "author": null,
          "description": "深潮 TechFlow 消息，币安创新区将于2022年12月12日16:00（东八区时间）上线Magic（MAGIC），并开放以下现货交易对：\n现货交易对： MAGIC/BTC、MAGIC/BUSD、MAGIC/USDT\nMAGIC充值通道现已开放\nMAGIC 提现预计于2022年12月13日16:00（东八区时间）开放\nMAGIC 的上币费用为0 BNB。\n此外，币安全仓杠杆及逐仓杠杆将于2022年12月12日16:00（东八区时间）起的48 小时内新增MAGIC 资产，并开放以下交易对：\n全仓杠杆交易对： MAGIC/BUSD、 MAGIC/USDT\n逐仓杠杆交易对： MAGIC/BUSD、 MAGIC/USDT\n原文链接",
          "link": "https://www.techflowpost.com/express/5820",
          "publishedOn": "2022-12-12T04:16:27.000Z",
          "wordCount": null,
          "title": "币安将于今日16点在创新区上线Magic（MAGIC）",
          "imageUrl": null
        },
        {
          "id": "https://www.techflowpost.com/express/5819",
          "author": null,
          "description": "深潮 TechFlow 消息，以太坊模块化执行层 Fuel 发文表示，随着以太坊明年推出分片原型，Fuel 也将与以太坊路线图保持一致，计划于 2023 年推出完整的主网。\n此前报道，Fuel 于 11 月推出第二个公共测试网 Beta-2。Beta-2 测试网的主要特点包括连接以太坊的 Goerli 网络、单一共享网络、Faucet、GraphQL 端点、无白名单限制、区块浏览器。参与 Beta-2 的开发人员可以构建和测试跨链 dApp。来源链接",
          "link": "https://www.techflowpost.com/express/5819",
          "publishedOn": "2022-12-12T03:03:26.000Z",
          "wordCount": 7844,
          "title": "模块化执行层 Fuel： 计划于 2023 年推出完整主网",
          "imageUrl": null
        },
        {
          "id": "https://www.techflowpost.com/express/5818",
          "author": null,
          "description": "深潮 TechFlow 消息，12月12日，据官方动态，Binance Labs 将与 Web3Port 联合举办系列Binance Labs Twitter Spaces。据悉，该活动主要由Web3行业的投资人、项目运营者、生态参与者等多方参与，为对Web3感兴趣的用户分享业内前沿知识、投资动态、有趣观点。同时，也欢迎Web3业内人士报名参与。\n该活动第一次分享将在UTC+8 December 12th 9:00PM 开始，由Binance Labs与Web3Port共同主持，嘉宾来自DCG、Pantera Capital、HashKey Capital、Outlier Ventures，将以Crypto Builder and Trader为主题进行分享。",
          "link": "https://www.techflowpost.com/express/5818",
          "publishedOn": "2022-12-12T02:47:19.000Z",
          "wordCount": null,
          "title": "Binance Labs 与 Web3Port 将联合举办系列 Twitter Space 活动",
          "imageUrl": null
        },
        {
          "id": "https://www.techflowpost.com/express/5817",
          "author": null,
          "description": "深潮 TechFlow 消息，区块链分析公司Messari创始人Ryan Selkis发推表示，“在第二季度和第三季度，Genesis解除了超过100亿美元的贷款。考虑到Alameda和Genesis是世界上最大的两家加密借贷对手方，其中或许有涉及FTX与Alameda的合同。看起来Genesis在负责任地减少他们的很多头寸并取消借贷。目前看来，Alameda和FTX似乎不是Genesis的债权人。如果这是真的，那么这两个巨头要么没有关系(不太可能)，要么就关闭了自己的头寸”。原文链接",
          "link": "https://www.techflowpost.com/express/5817",
          "publishedOn": "2022-12-12T02:11:10.000Z",
          "wordCount": null,
          "title": "Messari创始人：Genesis于Q2和Q3解除超100亿美元贷款，正在减少头寸并取消借贷",
          "imageUrl": null
        },
        {
          "id": "https://www.techflowpost.com/express/5816",
          "author": null,
          "description": "深潮 TechFlow 消息，SushiSwap 新任 CEO Jared Grey 在推特上表示，目前正在采取多种方案，旨在 2023 年第一季度改进 Sushi 和商业模式破裂的长期问题。此外，Jared Grey 将通过发布 DAO 和财政部活动的公共仪表板来提供完全的财务透明度。\n具体而言，临时方案 Kanpai 将 100% 的费用重定向到 Sushi 的财政部，它允许该协议重建其现金储备，以继续支付有竞争力的工资，支付关键基础设施的费用，并通过在基本资产对（如 ETH、稳定币等）中收集的资金使其国库多样化。\nSushi 即将推出的代币经济学侧重于重新调整其最具可操作性的资产 TVL 与 LP，该机制重新设计了 SushiSwap 引导流动性的方式，不再完全通过排放来补贴流动性，而是通过更公平的机制。Sushi 通过创新其 DEX 技术堆栈来帮助实现其业务模型的多样化。\nxSushi 仍然在新的代币经济学中，但重新调整了它在协议价值链中的位置。Jared Grey 将在下周提供 Sushi 的财务预算和公开快照。\n据 ChainCatcher 此前报道，SushiSwap 金库资金即将耗尽，Jared Grey 提议将支付给 xSushi 持有者的费用重新分配给金库，但随后该提案被撤回，Jared Grey 将重新发布新版提案以供讨论。来源链接",
          "link": "https://www.techflowpost.com/express/5816",
          "publishedOn": "2022-12-12T02:05:20.000Z",
          "wordCount": null,
          "title": "SushiSwap CEO 发布关于 Kanpai 提案、新代币经济学、Sushi 商业模式的看法",
          "imageUrl": null
        },
        {
          "id": "https://www.techflowpost.com/express/5815",
          "author": null,
          "description": "深潮 TechFlow 消息，Dragonfly Capital合伙人Haseeb Qureshi在Unchained节目中表示，Genesis债权人可能会要求DCG赎回Genesis价值11亿美元的十年期票据，而这将引发DCG的流动性枯竭从而导致其破产。目前，Genesis债权人长时间的沉默或许意味着其正在给DCG和Genesis时间来解决此问题。原文链接",
          "link": "https://www.techflowpost.com/express/5815",
          "publishedOn": "2022-12-12T01:51:46.000Z",
          "wordCount": 7803,
          "title": "Dragonfly Capital合伙人：Genesis清算或将迫使DCG破产",
          "imageUrl": null
        },
        {
          "id": "https://www.techflowpost.com/express/5814",
          "author": null,
          "description": "深潮 TechFlow 消息，12 月 12 日，据链上数据，过去 24 小时，中国台湾歌手黄立成的「machibigbrother.eth」地址从 Binance 提取近 60 万枚 APE（约 254 万美元）并进行质押，此外他又在 Uniswap 将 1087 枚 ETH 兑换为约 30 万枚 APE（约 136 万美元）并进行质押。原文链接",
          "link": "https://www.techflowpost.com/express/5814",
          "publishedOn": "2022-12-12T01:50:43.000Z",
          "wordCount": null,
          "title": "数据：黄立成地址新增质押约90万枚APE",
          "imageUrl": null
        },
        {
          "id": "https://www.techflowpost.com/express/5813",
          "author": null,
          "description": "深潮 TechFlow 消息，据派盾PeckShield监测显示，加密交易公司Orthogonal Trading通过机构借贷协议Maple Finance推出1690万美元的USDC贷款，期限为30天，年利率为0%，据团队确认这是向Maple v2迁移过程的一部分。\n据悉，Orthogonal Trading拖欠Maple Finance总计3600万美元的贷款。原文链接",
          "link": "https://www.techflowpost.com/express/5813",
          "publishedOn": "2022-12-12T01:21:13.000Z",
          "wordCount": 7819,
          "title": "加密交易公司Orthogonal Trading通过Maple Finance推出1690万美元USDC贷款",
          "imageUrl": null
        },
        {
          "id": "https://www.techflowpost.com/express/5812",
          "author": null,
          "description": "深潮 TechFlow 消息，据链上数据显示，一标记为“Justin Sun”的地址在6个小时前向币安充值地址（0xd1开头）转入总计约1140万美元稳定币（648万TUSD、493万USDC）。原文链接",
          "link": "https://www.techflowpost.com/express/5812",
          "publishedOn": "2022-12-12T01:20:15.000Z",
          "wordCount": null,
          "title": "数据：孙宇晨一地址向币安转入约1140万美元稳定币",
          "imageUrl": null
        },
        {
          "id": "https://www.techflowpost.com/express/5811",
          "author": null,
          "description": "深潮 TechFlow 消息，据CO NEWS发推表示，FTX前首席执行官SBF表示，正计划开展一项新业务，以便能够补偿受FTX破产影响的用户。\n此外，SBF在接受BBC采访时表示，其不知道FTX客户的资金被Alameda用于高风险的金融操作。但SBF同时表示，其作为首席执行官，应该对任何资金处理不当负责，但其“并没有故意欺诈”。原文链接",
          "link": "https://www.techflowpost.com/express/5811",
          "publishedOn": "2022-12-12T01:19:32.000Z",
          "wordCount": null,
          "title": "消息人士：SBF计划开展新业务，补偿受FTX破产影响的用户",
          "imageUrl": null
        },
        {
          "id": "https://www.techflowpost.com/express/5810",
          "author": null,
          "description": "深潮 TechFlow 消息，NFT项目Bubble Observers - Observers 将于北京时间 12 月 15 日 8:00 在 MOOAR 平台开启铸造，铸造价格为 100GMT。该 NFT 基于以太坊，总数为 6000 个。12 月 8 日至 12 月 12 日期间在 MOOAR 平台开启投票，为Bubble Observers - Observers 投票可以抽取NFT或者优先Mint。原文链接",
          "link": "https://www.techflowpost.com/express/5810",
          "publishedOn": "2022-12-10T16:23:06.000Z",
          "wordCount": null,
          "title": "NFT项目Bubble Observers - Observers即将在StepN新NFT市场MOOAR平台开启铸造",
          "imageUrl": null
        },
        {
          "id": "https://www.techflowpost.com/express/5809",
          "author": null,
          "description": "深潮 TechFlow 消息，AvatarDAO 将于12月22日举办“WEB3 XMAS”圣诞活动，活动以线上圆桌论坛和线下酒会组成，邀请WEB3行业头部领袖、机构、研究者参与探讨2023年行业趋势。\n本次活动由OKX赞助，联合胡子观币、UneMeta、K24 Ventures、FinanceRun共同举办。",
          "link": "https://www.techflowpost.com/express/5809",
          "publishedOn": "2022-12-10T16:19:31.000Z",
          "wordCount": null,
          "title": "AvatarDAO将于12月22日举办“WEB3 XMAS”圣诞活动",
          "imageUrl": null
        },
        {
          "id": "https://www.techflowpost.com/express/5808",
          "author": null,
          "description": "深潮 TechFlow 消息，12月10日，据Seer社交协议团队透露，平台现已接入ChatGPT机器人，用户可以加入Seer 平台和社区伙伴一起进行AI问答。\n此外，Seer生态分布式节点容器-DSN 动态NFT 也将于10日晚8点在官网(Seer.eco/#/dsn) 公开发售，本次首发400个。DSN持有者可以享受Seer内嵌活动View2Earn推广收益、DAO治理体系加入权以及未来增值效益。原文链接",
          "link": "https://www.techflowpost.com/express/5808",
          "publishedOn": "2022-12-10T10:47:47.000Z",
          "wordCount": null,
          "title": "Web3社交协议Seer 已实现社区内畅玩ChatGPT",
          "imageUrl": null
        },
        {
          "id": "https://www.techflowpost.com/express/5807",
          "author": null,
          "description": "深潮 TechFlow 消息，消息人士称，此前暂停提款的加密货币借贷机构Vauld声称一交易对手对其有1.3亿美元欠款，而该交易对手正是Amber Group。\n外媒The Block表示，依据其获得的一份文件，Vauld首席执行官Darshan Bathija以其个人名义将该笔资金借予了Amber Group。据Vauld提供的文件显示，该笔借款的最迟归还日期为2023年6月。原文链接",
          "link": "https://www.techflowpost.com/express/5807",
          "publishedOn": "2022-12-09T13:55:41.000Z",
          "wordCount": null,
          "title": "消息人士：Amber Group对Vauld的欠款达1.3亿美元",
          "imageUrl": null
        },
        {
          "id": "https://www.techflowpost.com/express/5806",
          "author": null,
          "description": "深潮 TechFlow 消息，12月9日，波场TRON创始人、火必Huobi全球顾问委员会成员孙宇晨在线上直播时表示，未来波场TRON将继续加强与主权国家的合作，并争取将波场系代币列为这些支持元宇宙主权国家的法定货币，拓展更多的去中心化元宇宙公民。近期波场TRON与多米尼克达成了一系列历史性合作，多米尼克在元宇宙中率先“建国”。孙宇晨表示，未来将持续推动波场TRON1亿多的用户成为元宇宙公民。他同时“剧透”，波场TRON将在不远的将来与更多的主权国家达成类似与多米尼克的合作。\n孙宇晨预测，明年支持元宇宙身份的国家将超过10个，未来5年将超过50个。\n据悉，截至目前，波场TRON账户总数正式突破1.26亿。在孙宇晨的引领下，波场TRON已被指定成为多米尼克的“国家公链”，TRX等七种波场系代币已成为多米尼克法定数字货币，近期，波场TRON被授权发行国家代币DMC和数字身份DID。据孙宇晨透露，目前申请获得多米尼克数字身份的人数已经超过15万。这一数字约为多米尼克人口的2倍。",
          "link": "https://www.techflowpost.com/express/5806",
          "publishedOn": "2022-12-09T12:39:12.000Z",
          "wordCount": null,
          "title": "孙宇晨：持续推动数亿用户成为元宇宙公民，波场TRON将继续加强与主权国家合作",
          "imageUrl": null
        },
        {
          "id": "https://www.techflowpost.com/express/5805",
          "author": null,
          "description": "深潮 TechFlow 消息，12月9日，波场TRON创始人，火必Huobi全球顾问委员会成员，格林纳达常驻世界贸易组织（WTO）代表、特命全权大使孙宇晨在内部员工大会中表示，波场、火必定位于去中心化元宇宙（DM，Decentralize Metaverse）的建设者，其作用是将用户转化为元宇宙世界的公民。数字公民身份系统将在明年上线，这是一个能容纳全球80亿人的元宇宙世界，预计明年去中心化元宇宙用户会超过越南人口，即突破1亿人。过去一年，波场、火必的用户已经达到1.2亿，尤其是火必的用户在去中心化元宇宙推出后，每日新增用户达到数万人，是所有交易所中唯一逆势增长的。\n孙宇晨认为，在2023年，支持去中心化元宇宙的国家将不低于10个，未来五年不会低于50个。目前注册火必元宇宙公民的用户已经达到15万余人。元宇宙世界是开放包容的，希望未来波场、火必甚至其他平台的用户都能以自己的地址来申领元宇宙公民。\n孙宇晨表示，与多米尼克、格林纳达的合作只是一个开始，将进一步推动与主权国家的合作，同时，进一步拓展元宇宙公民的公民权益，赋能HT、波场体系内的代币，赋能去中心化元宇宙生态。元宇宙世界数字身份可以用来通过KYC认证，元宇宙公民将会拥有自己的银行卡、护照和元宇宙的家园。",
          "link": "https://www.techflowpost.com/express/5805",
          "publishedOn": "2022-12-09T12:31:48.000Z",
          "wordCount": null,
          "title": "孙宇晨：波场、火必致力于建设去中心化元宇宙，明年将有1亿人加入",
          "imageUrl": null
        },
        {
          "id": "https://www.techflowpost.com/express/5804",
          "author": null,
          "description": "深潮 TechFlow 消息，据 Finsmes 报道，Web3 数字资产软件即服务 (SaaS) 平台 Liquid Access 宣布完成 300 万美元种子轮融资，Flintera 领投。Liquid Access 的 SaaS 平台将帮助品牌组织与机构创建和管理 Web3 数字资产，将其整合至自己业务中，也将帮助机构将现有忠诚度计划转移至链上等。原文链接",
          "link": "https://www.techflowpost.com/express/5804",
          "publishedOn": "2022-12-09T09:55:49.000Z",
          "wordCount": null,
          "title": "Web3 SaaS平台Liquid Access完成300万美元种子轮融资，Flintera领投",
          "imageUrl": null
        },
        {
          "id": "https://www.techflowpost.com/express/5803",
          "author": null,
          "description": "深潮 TechFlow 消息，Binance 创始人 CZ 发布推文再次阐述与 FTX 之间的投资关系始末。 CZ 表示，Binance 于 2021 年 7 月退出 FTX 投资，在进行投资之后，Binance 仍会继续进行尽职调查。「作为 FTX 的早期投资者，Binance 对 Alameda/SBF 越来越不满意，并在一年半之前启动退出程序。」 「当 Binance 决定不再继续作为 FTX 投资者时，Sam 气急败坏，以至于向多个 Binance 团队成员发送了一系列带攻击性的长文，包括威胁要「竭尽全力让 Binance 付出代价」。\nCZ 补充道：「Binance 至今仍存有这些短信。」 CZ 还表示，SBF 不久之后就开始「投资」身居高位的朋友，从媒体到政策制定者，再到名人。SBF 利用他的网络来操纵舆论，包括攻击 CZ 和业内其他人。 CZ 还表示，自己的身份是这些攻击的焦点，包括在媒体上和将于下周举行的参议院听证会上。CZ 再次强调：「我是加拿大人，Binance 不是中国公司。」原文链接",
          "link": "https://www.techflowpost.com/express/5803",
          "publishedOn": "2022-12-09T09:36:59.000Z",
          "wordCount": null,
          "title": "CZ：SBF 在币安退出 FTX 投资后通过操纵舆论来攻击币安",
          "imageUrl": null
        },
        {
          "id": "https://www.techflowpost.com/express/5802",
          "author": null,
          "description": "深潮 TechFlow 消息，12 月 9 日，SBF 针对此前 ZhuSu 指责其「猎杀三箭」的言论发布回应表示，其本人今年犯了许多严重错误，但猎杀三箭资本不是其中之一，Zhu Su 说的不是真的，也没有证据能证明。 ZhuSu 随后转载 SBF 推文回应表示：「你确定？毕竟你声称不知道 Alameda 发生的事情。没关系，我们可以让司法部（DoJ）决定。」原文链接",
          "link": "https://www.techflowpost.com/express/5802",
          "publishedOn": "2022-12-09T09:05:52.000Z",
          "wordCount": null,
          "title": "SBF否认猎杀3AC，遭ZhuSu质疑或将走法律程序",
          "imageUrl": null
        },
        {
          "id": "https://www.techflowpost.com/express/5801",
          "author": null,
          "description": "深潮 TechFlow 消息，推特用户建议Elon Musk收购Substack，可以与推特平台产生协同效应，即推特作为信息层，Substack作为叙事层。Elon Musk回应称，对该建议持开放态度。原文链接",
          "link": "https://www.techflowpost.com/express/5801",
          "publishedOn": "2022-12-09T08:53:45.000Z",
          "wordCount": null,
          "title": "Elon Musk：对收购Substack持开放态度",
          "imageUrl": null
        },
        {
          "id": "https://www.techflowpost.com/express/5800",
          "author": null,
          "description": "深潮 TechFlow 消息，Avalanche生态借贷协议Yeti Finance宣布推出锚定稳定模块Peg Stability Module（PSM），可以进行稳定币YUSD与USDC的1:1兑换。原文链接",
          "link": "https://www.techflowpost.com/express/5800",
          "publishedOn": "2022-12-09T08:51:16.000Z",
          "wordCount": null,
          "title": "Avalanche生态借贷协议Yeti Finance推出PSM，支持1:1兑换YUSD与USDC",
          "imageUrl": null
        },
        {
          "id": "https://www.techflowpost.com/express/5799",
          "author": null,
          "description": "深潮 TechFlow 消息，CNBC主持人Ran Neuner发推称：“如果启动FTX交易所并发行新的FTT代币，并将代币分发给债权人/存款人，且将100%的利润分配给代币持有者。它将成为世界上最大的交易所，用户能挽回更多的损失。”\n对此，前FTX首席执行官Sam Bankman-Fried（SBF）表示：“我仍然认为这将是各方探索的富有成效的途径，我希望现有的团队会这样做。”原文链接",
          "link": "https://www.techflowpost.com/express/5799",
          "publishedOn": "2022-12-09T08:49:06.000Z",
          "wordCount": null,
          "title": "SBF：支持重启FTX交易所并发行新FTT代币，希望现有团队会这样做",
          "imageUrl": null
        },
        {
          "id": "https://www.techflowpost.com/express/5798",
          "author": null,
          "description": "深潮 TechFlow 消息，据金融时报报道，加密货币公司 Amber Group 表示，该公司已从一个新的主权基金筹集约 5000 万美元资金，交易将于明年 1 月宣布。新资本对该公司的估值为 30 亿美元，与 2 月份持平。\nAmber Group 执行合伙人 Annabelle Huang 表示，Amber 本月还将宣布对新加坡一家持牌企业的重大收购。Huang 称，该公司只有不到 10% 的交易资本滞留在 FTX 上，但她也承认，在欧洲和美国的扩张计划已被搁置，新的元宇宙平台等项目正被“优先考虑”。\n另据彭博社援引知情人士报道，Amber Group 正取消零售业务并终止与切尔西足球俱乐部的赞助协议，该公司的裁员比例超 40%，会将约 700 人的团队削减至不到 400 人。知情人士称，Amber Group 与切尔西足球俱乐部的赞助协议为每年价值 2000 万英镑，Amber 正在走法律程序以终止协议。来源链接",
          "link": "https://www.techflowpost.com/express/5798",
          "publishedOn": "2022-12-09T08:19:58.000Z",
          "wordCount": null,
          "title": "Amber Group 已完成 5000 万美元融资，暂停扩张计划并取消零售业务",
          "imageUrl": null
        },
        {
          "id": "https://www.techflowpost.com/express/5797",
          "author": null,
          "description": "深潮 TechFlow 消息，据官方消息，Cosmos生态MEV基础设施Skip Protocol新增支持Terra 2.0。原文链接",
          "link": "https://www.techflowpost.com/express/5797",
          "publishedOn": "2022-12-09T07:59:18.000Z",
          "wordCount": null,
          "title": "Cosmos生态MEV基础设施Skip Protocol已支持Terra 2.0",
          "imageUrl": null
        }
      ]
    }
  ],
  "cliVersion": "1.15.1"
}