{
  "sources": [
    {
      "title": "Web3世界",
      "feedUrl": "https://www.web3sj.com/feed/",
      "siteUrl": "https://www.web3sj.com",
      "articles": [
        {
          "id": "https://www.web3sj.com/?p=116191",
          "author": "Gao",
          "description": "可以说，Pump.fun 不是一个典型的 Web3 项目，没有复杂的代币经济学模型，也没有 DAO 治理机制，但凭借精准的市场定位，Pump.fun 开创了一门稳赚不赔的生意市场。在注意力经济的主导下，很多人会把持续繁荣 meme 币赛道潜力解释为短视频之于长视频的优势，那么在「全民发币」时代，还能有后来者分一杯羹吗？",
          "link": "https://www.web3sj.com/project/116191/",
          "publishedOn": "2024-07-02T04:46:26.000Z",
          "wordCount": 1173,
          "title": "如果Pump.fun成为「币圈快手」",
          "imageUrl": "https://www.web3sj.com/wp-content/uploads/2024/07/1719895557488.png"
        },
        {
          "id": "https://www.web3sj.com/?p=116174",
          "author": "Gao",
          "description": "通货紧缩代币：代币供应随着时间的推移而减少的情况。当项目回购代币并销毁时，就会发生这种情况。理论上，减少供给应该会增加价值，但这只是理论上。",
          "link": "https://www.web3sj.com/transaction/116174/",
          "publishedOn": "2024-07-02T04:43:16.000Z",
          "wordCount": 914,
          "title": "代币经济学概览：投资前需要看哪些指标？",
          "imageUrl": "https://www.web3sj.com/wp-content/uploads/2024/07/1719895343832.png"
        },
        {
          "id": "https://www.web3sj.com/?p=116168",
          "author": "Gao",
          "description": "让人意想不到的是，空投没有如期而至，等来的却是该项目长达 5 个月的销声匿迹——项目官推停止更新，也再没有其他消息传出，也因此成为不少人感叹「NFT 果然已经死了，连宣布做 NFT L2 的都活不下去，直接跑路了」。",
          "link": "https://www.web3sj.com/nftnews/116168/",
          "publishedOn": "2024-07-02T03:51:10.000Z",
          "wordCount": 1286,
          "title": "收购Frame、打造抽象链、颠覆Base，胖企鹅能否扛起消费者经济的大旗？",
          "imageUrl": "https://www.web3sj.com/wp-content/uploads/2024/07/1719892252269.png"
        },
        {
          "id": "https://www.web3sj.com/?p=116149",
          "author": "Gao",
          "description": "稳定币（stablecoins）从字面理解就是价值稳定的加密货币，国际清算银行（Bank of International Settlements）对稳定币的定义是：价值与法定货币或其他资产挂钩的加密货币。延伸而言，稳定币的主要设立目的是其相对于挂钩的特定资产或一揽子资产保持稳定的价值，以实现稳定的价值存储和交换媒介，这点上其实与金本位制度非常相似。",
          "link": "https://www.web3sj.com/news/116149/",
          "publishedOn": "2024-07-02T03:47:13.000Z",
          "wordCount": 1946,
          "title": "万字详述稳定币赛道：模式、运行原理、趋势及香港稳定币的思考",
          "imageUrl": "https://www.web3sj.com/wp-content/uploads/2024/07/1719892015623.png"
        },
        {
          "id": "https://www.web3sj.com/?p=116146",
          "author": "Gao",
          "description": "TON 实现「千里马」蜕变背后离不开「伯乐」的慧眼。据 CoinCarp 数据显示，TON 迄今完成了七轮融资，但仅公开披露其中 2 轮 1600 万美元的投资，剩余五轮并未对外公布更多信息。其中，从投资机构来看，参投机构包括 Runa Capital、RTP Global、DWF Labs、Mask Network、Mexc Ventures、Animoca Brands、Mirana Ventures 和 Pantera Capital 等。",
          "link": "https://www.web3sj.com/project/116146/",
          "publishedOn": "2024-07-02T03:37:37.000Z",
          "wordCount": 1345,
          "title": "10家TON投资机构战绩盘点：最低建仓成本低于0.78美元，最高回报率或超14 倍",
          "imageUrl": "https://www.web3sj.com/wp-content/uploads/2024/07/1719891432180.png"
        },
        {
          "id": "https://www.web3sj.com/?p=116140",
          "author": "Gao",
          "description": "最新的美国制造业活动数据显示，美国制造业 PMI 在 6 月份进一步跌入收缩区域，触及四个月低点，这增强了投资者对美联储可能在 9 月份降息的希望，因为经济似乎显示出疲软迹象。投资者仍在等待将于周五发布的 6 月份就业报告，如果该报告显示出劳动力市场进一步降温的迹象，将为降息提供更多支持。",
          "link": "https://www.web3sj.com/transaction/116140/",
          "publishedOn": "2024-07-02T03:33:25.000Z",
          "wordCount": 1006,
          "title": "比特币收复6.3万美元，Coinbase溢价指数暗示「黎明前至暗时刻」",
          "imageUrl": "https://www.web3sj.com/wp-content/uploads/2024/07/1719891175182.png"
        },
        {
          "id": "https://www.web3sj.com/?p=116125",
          "author": "Gao",
          "description": "Curve 创始人把自己筹码卖了，然后和 Curve 没啥关系了是否会有影响？没啥问题。基建层协议在一定阶段后就没必要开发了。已经足够成熟了。抛开市场层面，不开发了也不会影响对他的使用。很多救市的人意识到了这个点，因此有这个动力。",
          "link": "https://www.web3sj.com/definews/116125/",
          "publishedOn": "2024-07-02T03:27:21.000Z",
          "wordCount": 1094,
          "title": "币圈大佬们有什么动机「救火」Curve",
          "imageUrl": "https://www.web3sj.com/wp-content/uploads/2024/07/1719890825993.png"
        },
        {
          "id": "https://www.web3sj.com/?p=116122",
          "author": "Gao",
          "description": "以太坊当前 Gasper 共识机制采取了 Slot（时隙）和 Epoch（时段）的核心概念，每个 Slot 持续 12s，会选择一部分 Validators 来验证链的当前的交易状态进行投票，每 32 个 Slot 也就是 6.4min 会构成一个时段，基本一个时段内所有的 validators 都会完成投票。",
          "link": "https://www.web3sj.com/news/116122/",
          "publishedOn": "2024-07-02T03:23:51.000Z",
          "wordCount": 929,
          "title": "如何理解Vitalik对以太坊交易确认方法的思考？",
          "imageUrl": "https://www.web3sj.com/wp-content/uploads/2024/07/1719890600273.png"
        },
        {
          "id": "https://www.web3sj.com/?p=116109",
          "author": "Gao",
          "description": "WLD将从7月24日起迎来大额线性解锁，730天每天解锁662万枚。索尼此前从Amber Group处收购的Amber Japan今日起更名为S.BLOX。Polymarket 6月份交易量达1亿美元创历史记录，或由美国总统竞选升温所推动。",
          "link": "https://www.web3sj.com/news/116109/",
          "publishedOn": "2024-07-01T11:22:10.000Z",
          "wordCount": 886,
          "title": "Web3世界日报（2024-7.1）",
          "imageUrl": "https://www.web3sj.com/wp-content/uploads/2024/07/2024070111190834.jpg"
        },
        {
          "id": "https://www.web3sj.com/?p=116091",
          "author": "Gao",
          "description": "现在以太坊的 Gasper 共识采用 slot 和 epoch 架构。每隔 12 秒（单个 slot 的时长），验证者子集会在区块链的最新区块上发布投票，在 32 个 slot（6.4 分钟，一个 epoch 包含 32 个 slot）内，所有验证者都有机会投票一次。",
          "link": "https://www.web3sj.com/news/116091/",
          "publishedOn": "2024-07-01T07:13:35.000Z",
          "wordCount": 1157,
          "title": "Vitalik新作：如何缩短以太坊的交易确认时间？",
          "imageUrl": "https://www.web3sj.com/wp-content/uploads/2024/07/1719817997099.png"
        }
      ]
    },
    {
      "title": "PANews - 快讯",
      "feedUrl": "https://rsshub.app/panewslab/news",
      "siteUrl": "https://panewslab.com/zh/news/index.html",
      "articles": [
        {
          "id": "https://panewslab.com/zh/articledetails/dmwjlxtd.html",
          "author": "PA一线",
          "description": "PANews 7月2日消息，据明报报道，香港投资者及理财教育委员会表示，在香港上市的虚拟资产现货ETF受证监会监管，投资者可以通过证券行或银行买卖虚拟资产现货ETF，交易方法跟股票或其他ETF一样方便和简单，然而投资者要了解虚拟资产现货ETF的风险程度评估是否适合。由于虚拟资产现货ETF极为波动，亦未必能够带来分散风险的效果。因此，在投资组合中，虚拟资产现货ETF应只视作辅助性的投资。",
          "link": "https://panewslab.com/zh/articledetails/dmwjlxtd.html",
          "publishedOn": "2024-07-02T03:56:49.000Z",
          "wordCount": 340,
          "title": "香港投委会：投资者对虚拟资产现货ETF应只视作辅助性投资",
          "imageUrl": "https://image.panewslab.com/images/logo1.jpg"
        },
        {
          "id": "https://panewslab.com/zh/articledetails/9fvpkwl7.html",
          "author": "PA一线",
          "description": "PANews 7月2日消息，据官方消息，Solana生态再质押协议Solayer宣布完成Builders Round轮融资，投资者包括Solana Labs联创Anatoly Yakovenko、Marinade核心贡献者Michael Repetny、Solend创始人Rooter、Tensor联创Richard Wu、加密KOL“Ansem”、Anza首席战略官Jed Halfon、Drift Protocol联创Cindy Leow、Bonk核心贡献者Nom、Babylon Chain的Xinshu Dong、Bison Trail联创Joseph Lallouz、Switchboard联创Chris Hermantis、Rio Network联创Alan Curtis、DCF God、wsbmod、Solana创始人Adam Jin、Initia联创Stan Liu、Blockworks联创Michael lppolito、Sershoku、Polygon联创Sandeep Nailwal、Apeindaily。\n据介绍，Solayer是一个Solana生态再质押协议，于6月初发布了在Solana上的再质押标准，即Endogenous-主动验证服务(AVS)。",
          "link": "https://panewslab.com/zh/articledetails/9fvpkwl7.html",
          "publishedOn": "2024-07-02T03:54:12.000Z",
          "wordCount": 410,
          "title": "Solana生态再质押协议Solayer完成Builders Round轮融资，Solana Labs联创等参投",
          "imageUrl": "https://image.panewslab.com/images/logo1.jpg"
        },
        {
          "id": "https://panewslab.com/zh/articledetails/7kqvv617.html",
          "author": "PA一线",
          "description": "PANews 7月2日消息，据官方公告，币安将支持MultiversX（EGLD）及Ronin（RON）网络升级及硬分叉。\nMultiversX（EGLD）项目方预计将于东八区时间2024年07月03日00:20）进行网络升级。币安预计将于东八区时间2024年07月02日23:20暂停MultiversX（EGLD）网络的代币充值、提现业务；Ronin（RON）项目方将于区块高度 36,052,600（预计东八区时间2024年07月03日15:00）进行网络升级及硬分叉。币安预计将于东八区时间2024年07月03日14:00暂停Ronin（RON）网络的代币充值、提现业务。",
          "link": "https://panewslab.com/zh/articledetails/7kqvv617.html",
          "publishedOn": "2024-07-02T03:36:17.000Z",
          "wordCount": 343,
          "title": "币安将支持MultiversX（EGLD）及Ronin（RON）网络升级及硬分叉",
          "imageUrl": "https://image.panewslab.com/images/logo1.jpg"
        },
        {
          "id": "https://panewslab.com/zh/articledetails/4cjhp04r.html",
          "author": "PA一线",
          "description": "PANews 7月2日消息，The ETF Store总裁Nate Geraci在X平台引援CNBC政治金融记者的分析，如果特朗普成为美国总统，那么美国证券交易委员会委员（SEC）的主席人选包括Robinhood首席法务官、前SEC委员Dan Gallagher。",
          "link": "https://panewslab.com/zh/articledetails/4cjhp04r.html",
          "publishedOn": "2024-07-02T03:34:13.000Z",
          "wordCount": 356,
          "title": "分析：若特朗普当选美国总统，Robinhood CLO或会成为美SEC主席人选之一",
          "imageUrl": "https://image.panewslab.com/images/logo1.jpg"
        },
        {
          "id": "https://panewslab.com/zh/articledetails/xsj6yd85.html",
          "author": "PA一线",
          "description": "PANews 7月2日消息，据The Data Nerd监测，1小时前， Wintermute在币安卖出12,695枚ETH（约合4384万美元）。这些 ETH是从Coinbase、Kraken、Crypto.com等其他交易所转入。\n昨天，他们也做了同样的操作，卖出12,608枚ETH（约合4427万美元）。",
          "link": "https://panewslab.com/zh/articledetails/xsj6yd85.html",
          "publishedOn": "2024-07-02T03:25:18.000Z",
          "wordCount": 356,
          "title": "Wintermute于1小时前在币安卖出12695枚ETH，约合4384万美元",
          "imageUrl": "https://image.panewslab.com/images/logo1.jpg"
        },
        {
          "id": "https://panewslab.com/zh/articledetails/2a1ygi4s.html",
          "author": "PA一线",
          "description": "PANews 7月2日消息，Dune Analytics数据显示，当前Base链上Gas总消耗量接近1.5万枚ETH，触及14,948.3114枚ETH，平均Gas使用金额约0.1354美元（0.000044391 ETH）。\n此外，Base链上用户地址数突破1500万，达15,206,412；Base链上区块总量约为1615万，链上总交易量超过3.5亿笔。",
          "link": "https://panewslab.com/zh/articledetails/2a1ygi4s.html",
          "publishedOn": "2024-07-02T03:23:47.000Z",
          "wordCount": 358,
          "title": "Base链上Gas总消耗量接近1.5万枚ETH，用户地址数突破1500万",
          "imageUrl": "https://image.panewslab.com/images/logo1.jpg"
        },
        {
          "id": "https://panewslab.com/zh/articledetails/z7nfgx74.html",
          "author": "PA一线",
          "description": "PANews 7月2日消息，据DL News报道，DeFi协议Pendle因多个市场产品到期，用户自上周三以来提取近30亿美元存款，其中大部分是流动性再质押代币。周一，用户总存款价值降至37亿美元，Pendle总锁仓价值（TVL）在过去一周内下降40%。\nKairos Research创始人Ian Unsworth表示，资金流出主要是因为一些产品到期。Pendle市场上ether.fi的eETH、Renzo的 ezETH、Puffer的pufETH、Kelp的rsETH和Swell的rswETH相关产品于6月27日到期，投资者本可以将这些代币转入新的Pendle市场，但这种回报并不一定像以前那样丰厚。Pendle的资金流出也影响了相关协议，比如Zircuit，其存款价值一周内下降15%。",
          "link": "https://panewslab.com/zh/articledetails/z7nfgx74.html",
          "publishedOn": "2024-07-02T03:17:31.000Z",
          "wordCount": 357,
          "title": "Pendle TVL过去一周下降40%，用户自上周三以来已提取近30亿美元存款",
          "imageUrl": "https://image.panewslab.com/images/logo1.jpg"
        },
        {
          "id": "https://panewslab.com/zh/articledetails/i63790y1.html",
          "author": "PA一线",
          "description": "PANews 7月2日消息，分布式验证器技术提供商Obol Labs在X平台宣布，经过3年的开发、测试和主网采用，中间件客户端Charon的v1.0.0版本现已发布。这将分布式验证器 (DV) 从早期技术转变为可成为所有Ethereum验证器标准的技术。Charon 1.0是Charon的第一个长期支持 (LTS) 版本，它将与未来版本保持兼容，并作为DV大规模用例和部署的基础。\nObol Labs还表示，其即将推出其他产品的1.0版本：DV Launchpad、Obol Splits、Obol SDK。这些版本将继续使DV更易于部署并被以太坊生态系统中的更多验证者采用。",
          "link": "https://panewslab.com/zh/articledetails/i63790y1.html",
          "publishedOn": "2024-07-02T03:09:32.000Z",
          "wordCount": 378,
          "title": "Obol Labs发布分布式验证客户端Charon的v1.0.0版本",
          "imageUrl": "https://image.panewslab.com/images/logo1.jpg"
        },
        {
          "id": "https://panewslab.com/zh/articledetails/87gtbsrj.html",
          "author": "PA一线",
          "description": "PANews 7月2日消息，韩国游戏巨头Nexon旗下NFT游戏项目MapleStory Universe在官方博客中表示，《MapleStory N》的首个先锋测试已开发测试者注册。先驱测试报名时间截止至7月7日，测试员提名公告将于7月18日发布，先锋测试时间为7月24日至8月2日。在先锋测试期间，参与者将有机会在今年晚些时候正式发布之前体验《MapleStory N》。测试将展示游戏的关键区块链元素，包括限量供应奖励系统和用户驱动定价系统。此外，测试人员还可以体验简单模式（入门等级50以上）和普通模式（入门等级90以上）中提供的Zakum Boss内容。\n《MapleStory N》是一款基于PC的MMORPG，将区块链技术与《冒险岛》 IP相结合。《MapleStory N》是第一款在MapleStory Universe中推出的游戏。\n此前去年12月消息，Nexon旗下NFT游戏项目MapleStory Universe宣布获得1亿美元投资。",
          "link": "https://panewslab.com/zh/articledetails/87gtbsrj.html",
          "publishedOn": "2024-07-02T03:02:42.000Z",
          "wordCount": 402,
          "title": "MapleStory Universe：《MapleStory N》的首个先锋测试已开发测试者注册",
          "imageUrl": "https://image.panewslab.com/images/logo1.jpg"
        },
        {
          "id": "https://panewslab.com/zh/articledetails/sifxsjcu.html",
          "author": "PA一线",
          "description": "PANews 7月2日消息，据福布斯报道，资产管理公司贝莱德宣布，将以32亿美元现金收购英国私人市场数据提供商Preqin，此举标志着贝莱德在私人市场数据领域的重大布局。通过此次收购，贝莱德计划将Preqin丰富的数据和研究资源与自身投资组合管理软件Aladdin的工作流功能深度融合，构建一个全面的私人市场投资平台。这一整合旨在提升投资透明度，简化私人市场投资流程，为投资者和基金经理提供更加便捷、高效的服务。\n目前，该收购交易已获双方同意，并预计在获得所有必要监管批准并满足交易惯常成交条件后于2024年底前完成。贝莱德已聘请巴克莱银行担任首席财务顾问，司各特律师事务所担任法律顾问；Preqin则指定高盛国际为独家财务顾问，麦法兰律师事务所担任法律顾问。\nThe ETF Store总裁Nate Geraci对此评论称，贝莱德疑似旨在利用这些数据最终ETF。",
          "link": "https://panewslab.com/zh/articledetails/sifxsjcu.html",
          "publishedOn": "2024-07-02T02:54:27.000Z",
          "wordCount": 347,
          "title": "贝莱德将以32亿美元现金收购英国私人市场数据提供商Preqin",
          "imageUrl": "https://image.panewslab.com/images/logo1.jpg"
        },
        {
          "id": "https://panewslab.com/zh/articledetails/5taeogxe.html",
          "author": "PA一线",
          "description": "PANews 7月2日消息，据链上分析师@ai_9684xtpa 监测，过去19小时Abraxas Capital Mgmt已偿还Spark Protocol所有借款，并提出70153枚ETH，价值2.44亿美元。其中52200枚ETH已充值进Bitfinex，钱包中仍剩余17957枚。",
          "link": "https://panewslab.com/zh/articledetails/5taeogxe.html",
          "publishedOn": "2024-07-02T02:44:17.000Z",
          "wordCount": 359,
          "title": "Abraxas Capital已偿还Spark所有借款并提出70153枚ETH，大部分已转入CEX",
          "imageUrl": "https://image.panewslab.com/images/logo1.jpg"
        },
        {
          "id": "https://panewslab.com/zh/articledetails/v3ou87b9.html",
          "author": "PA一线",
          "description": "PANews 7月2日消息，据Cryptoglobe报道，美国上市公司Kronos Advanced Technologies Inc（OTC：KNOS）宣布决定接受SHIB作为其空气净化器的支付方式。该公司在新闻稿中表示，此举使其成为“第一家接受SHIB代币的上市公司”。Kronos 表示，截至2024年，全球约有138万Shiba Inu钱包持有者。在公告中，Kronos将SHIB描述为一种获得了大量追随者的去中心化加密货币。该公司表示认识到这种支付方式的潜力，并希望为客户提供一种新的购买其产品的方式。\n据介绍，Kronos Advanced Technologies Inc成立于1980年，专注于空气净化与过滤系统的研发、制造与分销，旨在通过提供能够消除室内空气中过敏原、细菌、病毒及其他污染物的设备来解决空气质量问题，其产品线包括空气净化器及个人防护装备，如自消毒石墨烯空气净化装置。",
          "link": "https://panewslab.com/zh/articledetails/v3ou87b9.html",
          "publishedOn": "2024-07-02T02:42:01.000Z",
          "wordCount": 373,
          "title": "美国上市公司Kronos Advanced Technologies现已接受SHIB作为付款方式",
          "imageUrl": "https://image.panewslab.com/images/logo1.jpg"
        },
        {
          "id": "https://panewslab.com/zh/articledetails/nqud30z0.html",
          "author": "PA一线",
          "description": "PANews 7月2日消息，风险投资机构Paradigm政府关系负责人Alexander Grieve在X平台表示，今天美国SEC委员Mark Uyeda发表关于指数挂钩年金和注册市值调整年金注册规则的声明。在脚注中，他呼吁更新S-1表格，以更好地适应加密货币的独特性。这是Uyeda首次公开呼吁为加密资产量身定制披露制度。如果换一个管理者，美国SEC会将是一个截然不同的地方。",
          "link": "https://panewslab.com/zh/articledetails/nqud30z0.html",
          "publishedOn": "2024-07-02T02:36:56.000Z",
          "wordCount": 347,
          "title": "美国SEC委员呼吁更新S-1表格，以更好地适应加密货币的独特性",
          "imageUrl": "https://image.panewslab.com/images/logo1.jpg"
        },
        {
          "id": "https://panewslab.com/zh/articledetails/x44kayn5.html",
          "author": "PA一线",
          "description": "PANews 7月2日消息，据Decrypt报道，在加密游戏《Pixels》第二章游戏玩法发布之际，创始人Luke Barwikowski透露，工作室正在开发《Pixels》宇宙中的其他游戏，并与外部开发者合作拓展这一系列。Barwikowski表示，他的19人全职团队负责制定这些游戏的高层次方向，然后交给外部工作室开发。团队将在游戏上线前加入区块链和用户获取元素。\n他还暗示，未来可能会有基于Telegram的游戏推出，称这是一个有趣的生态系统，他们可能会尝试涉足。Barwikowski表示：“我们正在考虑可能在Telegram上再启动一个项目，那也许只是一些alpha测试版——但这就像是一个旁支实验。Telegram是一个有趣的生态系统……我们可能会在那里试水。”\n无论基于Telegram的《Pixels》变体是否成为现实，Barwikowski表示他热衷于扩展他们已开发的IP。现在，《Pixels》正在开发内部故事集，这将为未来的应用和实验奠定基础。",
          "link": "https://panewslab.com/zh/articledetails/x44kayn5.html",
          "publishedOn": "2024-07-02T02:33:17.000Z",
          "wordCount": 373,
          "title": "Pixels创始人计划推出更多加密游戏，并考虑尝试在Telegram上推出",
          "imageUrl": "https://image.panewslab.com/images/logo1.jpg"
        },
        {
          "id": "https://panewslab.com/zh/articledetails/4s25w1hq.html",
          "author": "PA一线",
          "description": "PANews 7月2日消息，据链上分析师@ai_9684xtpa监测，孙宇晨在九小时前通过两个地址从Justlend赎回2000万枚USDT，随后全部充值进了Bitfinex。",
          "link": "https://panewslab.com/zh/articledetails/4s25w1hq.html",
          "publishedOn": "2024-07-02T02:14:03.000Z",
          "wordCount": 341,
          "title": "孙宇晨凌晨从Justlend赎回2000万枚USDT，随后全部充值进Bitfinex",
          "imageUrl": "https://image.panewslab.com/images/logo1.jpg"
        },
        {
          "id": "https://panewslab.com/zh/articledetails/hvtrbbcl.html",
          "author": "PA一线",
          "description": "美国法警局选择Coinbase作为其数字资产托管和交易服务提供商\n据USMS公告，美国司法部下属的美国法警局选择Coinbase Prime作为其“Class 1”大市值数字资产的托管和交易服务提供商。Coinbase因其强大的安全记录和机构级加密服务能力脱颖而出。Coinbase Prime自三年前推出以来，已成为机构和大型加密资产持有者的首选平台。\n美国SEC已确认收到Hashdex加密指数ETF申请，将同时持有现货比特币和以太坊\nThe ETF Store总裁Nate Geraci在推特发文称，美国SEC已确认收到Hashdex Nasdaq Crypto Index US ETF的19b-4申请。该基金将同时持有现货比特币和以太坊。\nBinance.US：对美SEC诉讼继续进行的裁决已有准备，本案将进入进一步证据开示阶段\nBinance.US在X平台表示，法院裁定美国证券交易委员会（SEC）对其的诉讼将继续进行。公司对此已有所准备，并期待案件能在司法程序中顺利推进。Binance.US强调，其一直按照美国规则和法规为当地客户服务，并保持1:1的客户资产储备，拥有健全的合规和风险程序。公司表示，其一直遵循SEC的有限指导合规经营，但不幸成为SEC执法方式监管和政治动机过度监管的受害者。接下来，本案将进入进一步的证据开示阶段。在迄今为止长达11个月的证据开示过程中，SEC未发现Binance.US有任何不当行为。公司坚信SEC的诉讼无事实和法律依据，且委员会缺乏相应权力。Binance.US称其将继续为客户提供服务，并推出新的功能和更新，其业务基础稳固，为美国人提供数字资产访问渠道的承诺不会改变。\nSilvergate将支付6300万美元与美国SEC、美联储和加州监管机构达成和解\n据CoinDesk报道，加密友好银行Silvergate Bank母公司Silvergat…",
          "link": "https://panewslab.com/zh/articledetails/hvtrbbcl.html",
          "publishedOn": "2024-07-02T02:11:51.000Z",
          "wordCount": 710,
          "title": "昨夜今晨重要资讯（7月1日-7月2日）",
          "imageUrl": "https://cdn-img.panewslab.com/panews/2024/07/02/images/3I4smN4FPe.png"
        },
        {
          "id": "https://panewslab.com/zh/articledetails/0g6vx2ey.html",
          "author": "PA一线",
          "description": "PANews 7月2日消息，据官方公告，币安赚币上线LISTA定期产品，并推出该产品专属活动，活动期间申购LISTA定期产品的用户，享最高11.9%年化收益率。LISTA定期产品申购规则：适用于2024年07月02日18:00至2025年01月02日17:59（东八区时间）期间的申购。",
          "link": "https://panewslab.com/zh/articledetails/0g6vx2ey.html",
          "publishedOn": "2024-07-02T02:02:05.000Z",
          "wordCount": 339,
          "title": "币安赚币上线LISTA定期产品",
          "imageUrl": "https://image.panewslab.com/images/logo1.jpg"
        },
        {
          "id": "https://panewslab.com/zh/articledetails/sicuohds.html",
          "author": "PA一线",
          "description": "PANews 7月2日消息，由Amber Group孵化的高性能模块化金融系统edgeX即将推出永续合约DEX 作为MVP （最小可行产品）。edgeX exchange是一个高性能的、基于订单簿的去中心化永续合约交易所，计划于7月推出其测试网。即将宣布一项测试者活动。\nedgeX Labs由来自巴克莱银行、摩根士丹利、Bybit，火币的交易，技术和用户增长负责人创立，正在开发一个链上金融系统，旨在融合中心化金融（CeFi）的能力和性能与去中心化金融（DeFi）的安全性和透明度。",
          "link": "https://panewslab.com/zh/articledetails/sicuohds.html",
          "publishedOn": "2024-07-02T02:00:25.000Z",
          "wordCount": 361,
          "title": "由Amber Group孵化的模块化金融系统edgeX将推出永续合约DEX",
          "imageUrl": "https://image.panewslab.com/images/logo1.jpg"
        },
        {
          "id": "https://panewslab.com/zh/articledetails/uikw1ga6.html",
          "author": "PA一线",
          "description": "PANews 7月2日消息，据路透社报道，巴哈马央行行长John Rolle透露，该国目前正在制定相关法规，要求商业银行提供央行数字货币“沙元”的访问权限，以刺激其普及。Rolle表示，面对“沙元”使用率低迷，激励措施已转向强制措施，相关法规将在两年内出台，要求所有银行参与。\n然而，CBDC推广面临挑战，银行业担忧存款外流，且银行需大幅改造IT系统。目前，“沙元”流通占比不足1%，钱包充值额大幅下滑。类似问题也困扰其他CBDC国家，公众对其优势存疑，担忧政府监控加剧。\nRolle尔承认，提高“沙元”使用率的关键在于推动更多商家、餐馆及其他企业接受其为支付方式，而强制商业银行嵌入“沙元”系统或能助一臂之力。但他同时表示，巴哈马不太可能效仿印度，通过财务激励来推广CBDC，也不会如以色列所议，为“沙元”钱包提供利率吸引用户。",
          "link": "https://panewslab.com/zh/articledetails/uikw1ga6.html",
          "publishedOn": "2024-07-02T01:55:21.000Z",
          "wordCount": 354,
          "title": "巴哈马央行正制定法规，拟强制银行提供CBDC访问权限以刺激其普及",
          "imageUrl": "https://image.panewslab.com/images/logo1.jpg"
        },
        {
          "id": "https://panewslab.com/zh/articledetails/m91tjznx.html",
          "author": "PA一线",
          "description": "PANews 7月2日消息，PancakeSwap在官方博客中宣布，现已支持由Wormhole驱动的USDT原生转账功能。这一发展提升了USDT在以太坊、Arbitrum、Base和BNB Chain上PancakeSwap资金池中的流动性利用率，进一步扩展了PancakeSwap在传统去中心化交易所（DEX）Swap交易之外的角色。通过PancakeSwap资金池集成Wormhole的USDT原生转账功能，是提升流动性利用率和跨链功能的重要一步。",
          "link": "https://panewslab.com/zh/articledetails/m91tjznx.html",
          "publishedOn": "2024-07-02T01:42:19.000Z",
          "wordCount": 350,
          "title": "PancakeSwap已支持由Wormhole驱动的USDT原生转账功能",
          "imageUrl": "https://image.panewslab.com/images/logo1.jpg"
        }
      ]
    },
    {
      "title": "白话区块链 - 快讯",
      "feedUrl": "https://rsshub.app/hellobtc/news",
      "siteUrl": "https://www.hellobtc.com/news",
      "articles": [
        {
          "id": "https://www.hellobtc.com/news/202407/22471.html",
          "author": null,
          "description": "1. 彭博ETF分析师：GBTC和EETH上半年回报率分别为62%和44%。\n\n2. 以太坊和Tron上的USDT铸造量在6个月内从70亿美元降至10亿美元。\n\n3. Binance.US：对美SEC诉讼继续进行的裁决已有准备，本案将进入进一步证据开示阶段。\n\n4. 美国上市公司Kronos Advanced Technologies宣布支持SHIB支付方式。\n\n5. Arthur Hayes：新通胀周期已至，比特币将是最佳财富避风港。\n\n6. 币安CEO：USDC将继续在币安产品中提供给欧洲经济区用户。\n\n7. 报告：有迹象表明比特币的市场情绪正在转变。\n\n8. Coinbase首席政策官：加密货币PAC的支持重点是美国国会。\n\n9. 分析：Coinbase溢价指数显示比特币价格可能见底。",
          "link": "https://www.hellobtc.com/news/202407/22471.html",
          "publishedOn": "2024-07-02T01:15:00.000Z",
          "wordCount": 327,
          "title": "白话区块链早报:GBTC和EETH上半年回报率分别为62%和44%",
          "imageUrl": "https://www.hellobtc.com/d/file/202106/bff70034ff497aeca9460d3429e7d08f.jpg"
        },
        {
          "id": "https://www.hellobtc.com/news/202407/22470.html",
          "author": null,
          "description": "上周，Ishares比特币信托基金（IBIT）登陆智利主要金融市场圣地亚哥证券交易所。贝莱德智利国家负责人Silvia Fernandez表示，今年获得美国证券交易委员会（SEC）批准的现货比特币ETF工具现在将允许智利投资者购买“可访问且高效的数字资产，并将其纳入其投资组合。",
          "link": "https://www.hellobtc.com/news/202407/22470.html",
          "publishedOn": "2024-07-01T10:13:00.000Z",
          "wordCount": 306,
          "title": "贝莱德的比特币ETF开始在智利证券交易所交易",
          "imageUrl": "https://www.hellobtc.com/d/file/202106/bff70034ff497aeca9460d3429e7d08f.jpg"
        },
        {
          "id": "https://www.hellobtc.com/news/202407/22469.html",
          "author": null,
          "description": "日本Web3媒体CoinPost运营商日本Web3协会宣布，日本首相岸田文雄（Fumio Kishida）将在由WebX执行委员会策划和组织的国际Web3会议WebX上发表演讲。 WebX是亚洲最大的Web3会议之一，也是日本最大的Web3会议，来自世界各地的有前途的项目、公司、企业家、投资者和尖端技术（主要是Web3领域的技术）开发人员汇聚一堂。",
          "link": "https://www.hellobtc.com/news/202407/22469.html",
          "publishedOn": "2024-07-01T10:13:00.000Z",
          "wordCount": 306,
          "title": "日本首相岸田文雄将在Web3会议WebX上发表演讲",
          "imageUrl": "https://www.hellobtc.com/d/file/202106/bff70034ff497aeca9460d3429e7d08f.jpg"
        },
        {
          "id": "https://www.hellobtc.com/news/202407/22468.html",
          "author": null,
          "description": "港股行情数据显示，截止收盘，今日6只香港虚拟资产ETF成交额为1362.64万港元，其中：华夏比特币ETF（3042.HK）的交易额为640万港元，华夏以太币ETF（3046.HK）的交易额为210万港元，嘉实比特币ETF（3439.HK）的交易额为88.64万港元，嘉实以太币ETF（3179.HK）的交易额为161万港元，博时HashKey比特币ETF（3008.HK）的交易额为122万港元，博时HashKey以太币ETF（3009.HK）的交易额为141万港元。",
          "link": "https://www.hellobtc.com/news/202407/22468.html",
          "publishedOn": "2024-07-01T10:13:00.000Z",
          "wordCount": 308,
          "title": "6只香港虚拟资产ETF今日成交额为1362.64万港元",
          "imageUrl": "https://www.hellobtc.com/d/file/202106/bff70034ff497aeca9460d3429e7d08f.jpg"
        },
        {
          "id": "https://www.hellobtc.com/news/202407/22467.html",
          "author": null,
          "description": "日本上市公司Metaplanet在X平台称，额外购买20.20枚BTC。",
          "link": "https://www.hellobtc.com/news/202407/22467.html",
          "publishedOn": "2024-07-01T06:25:00.000Z",
          "wordCount": 305,
          "title": "日本上市公司Metaplanet再次增持20.20枚BTC",
          "imageUrl": "https://www.hellobtc.com/d/file/202106/bff70034ff497aeca9460d3429e7d08f.jpg"
        },
        {
          "id": "https://www.hellobtc.com/news/202407/22466.html",
          "author": null,
          "description": "马斯克表示，XAI的GROK 2大模型将于八月推出。",
          "link": "https://www.hellobtc.com/news/202407/22466.html",
          "publishedOn": "2024-07-01T04:57:00.000Z",
          "wordCount": 314,
          "title": "马斯克：XAI的GROK 2大模型将于八月推出",
          "imageUrl": "https://www.hellobtc.com/d/file/202106/bff70034ff497aeca9460d3429e7d08f.jpg"
        },
        {
          "id": "https://www.hellobtc.com/news/202407/22465.html",
          "author": null,
          "description": "The Data Nerd监测，在将30,000枚ETH质押到Spark后，该鲸鱼从Spark借入了5100万DAI，并换成了5200万USDC，然后将所有USDC 存入Binance。通过这种做法，他从Binance提取另外30,000枚ETH（约合1.017亿美元）。",
          "link": "https://www.hellobtc.com/news/202407/22465.html",
          "publishedOn": "2024-07-01T04:57:00.000Z",
          "wordCount": 308,
          "title": "此前质押3万枚ETH的巨鲸从Binance提取3万枚ETH",
          "imageUrl": "https://www.hellobtc.com/d/file/202106/bff70034ff497aeca9460d3429e7d08f.jpg"
        },
        {
          "id": "https://www.hellobtc.com/news/202407/22464.html",
          "author": null,
          "description": "Nansen首席执行官Alex Svanevik在X平台发文称，Base 采取的非常明智的举措是在以太坊上构建 L2，可以利用加密货币领域最强大的开发生态系统，以及Coinbase上1 亿以上终端用户分布。从品牌角度来看，Base对开发者来说高度“以太坊化”， 远比 BNB Chain 等更甚，后者在历史上吸引的开发者较少。大多数其他区块链必须在开发者或终端用户之间做出选择，但Base可能是目前在开发者和终端用户之间平衡最好的L2。",
          "link": "https://www.hellobtc.com/news/202407/22464.html",
          "publishedOn": "2024-07-01T04:57:00.000Z",
          "wordCount": 314,
          "title": "Nansen CEO：Base可能是目前在开发者和终端用户之间平衡最好的L2",
          "imageUrl": "https://www.hellobtc.com/d/file/202106/bff70034ff497aeca9460d3429e7d08f.jpg"
        },
        {
          "id": "https://www.hellobtc.com/news/202407/22463.html",
          "author": null,
          "description": "7月1日消息，LayerZero首席执行官Bryan Pellegrino发推回应代码质疑，称这些指控毫无依据。其表示，社区所引用的代码于2022年发布，且这些配置是应用程序的安全配置，而非协议配置。即使在最新版本中，应用程序仍可覆盖此限制，防止 LayerZero 通过配置负载限制为0来阻止消息传递。这不是漏洞，而是协议的设计原则，旨在确保技术轨道的抗审查性。",
          "link": "https://www.hellobtc.com/news/202407/22463.html",
          "publishedOn": "2024-07-01T04:57:00.000Z",
          "wordCount": 314,
          "title": "LayerZero CEO回应代码质疑：非漏洞，而是协议的设计原则",
          "imageUrl": "https://www.hellobtc.com/d/file/202106/bff70034ff497aeca9460d3429e7d08f.jpg"
        },
        {
          "id": "https://www.hellobtc.com/news/202407/22462.html",
          "author": null,
          "description": "Greeks.live发文称，本周是宏观大周，最核心的是周五的美国失业率与非农数据，沉寂多日的宏观市场卷土重来，每个工作日都有重要宏观事件。 加密方面，本周SEC大概率会对ETH ETF给出回应，虽然直接通过的可能性不大，但是利好消息是大概率的。季度交割刚结束，各主要期限IV都很低，是建仓是的好机会。 本周重磅事件： 7/1 周一 * 美国6月ISM制造业PMI 7/2 周二 * 美联储主席鲍威尔、欧洲央行行长拉加德和巴西央行行长内托在欧洲央行举行的中央银行论坛上发表讲话。 澳洲联储公布6月货币政策会议纪要 7/3 周三 ** 美国6月ADP就业人数 美国当周初请失业金人数 7/4 周四 ** 美联储公布货币政策会议纪要 英国举行大选 欧洲央行公布6月货币政策会议纪要 美国SEC或最早于今日批准以太坊现货ETF 7/5 周五 *** 美国6月失业率 美国6月非农就业人口",
          "link": "https://www.hellobtc.com/news/202407/22462.html",
          "publishedOn": "2024-07-01T04:56:00.000Z",
          "wordCount": 336,
          "title": "本周重点关注宏观数据与SEC对ETH ETF的回应",
          "imageUrl": "https://www.hellobtc.com/d/file/202106/bff70034ff497aeca9460d3429e7d08f.jpg"
        }
      ]
    },
    {
      "title": "深潮TechFlow - 快讯",
      "feedUrl": "https://rsshub.app/techflowpost/express",
      "siteUrl": "https://www.techflowpost.com/newsletter/index.html",
      "articles": [
        {
          "id": "https://www.techflowpost.com/newsletter/detail_51760.html",
          "author": null,
          "description": "深潮 TechFlow 消息，据DL News报道，DeFi 协议 Pendle 因多个市场到期，用户自上周三以来提取近 30 亿美元存款，总存款价值降至 37 亿美元，总锁仓价值（TVL）在过去一周内下降了 40%。\n\nKairos Research 创始人 Ian Unsworth 表示，这些流出主要是因为一些产品到期。Pendle 市场上的 Ether.Fi 的 eETH、Renzo 的 ezETH、Puffer 的 pufETH、Kelp 的 rsETH 和 Swell 的 rswETH 于 6 月 27 日到期，导致大量资金流出。Pendle 的资金流出也影响了相关协议 Zircuit，存款价值一周内下降 15%。",
          "link": "https://www.techflowpost.com/newsletter/detail_51760.html",
          "publishedOn": "2024-07-02T02:47:53.000Z",
          "wordCount": 540,
          "title": "Pendle因多个产品到期，TVL过去一周内下降40%",
          "imageUrl": "https://upload.techflowpost.com/upload/images/20230331/2023033111502613443948.png"
        },
        {
          "id": "https://www.techflowpost.com/newsletter/detail_51759.html",
          "author": null,
          "description": "深潮 TechFlow 消息，Startale Labs 首席执行官、Astar Network 创始人 Sota Watanabe 发布推文称，正在开发 L1 和 L2，并且对两者都有丰富的经验。可能是 L1，也可能是 L2。首要任务是 Astar 社区和 ASTR 的价值。",
          "link": "https://www.techflowpost.com/newsletter/detail_51759.html",
          "publishedOn": "2024-07-02T02:33:48.000Z",
          "wordCount": 505,
          "title": "Astar Network 创始人：正在开发L1/L2",
          "imageUrl": "https://upload.techflowpost.com/upload/images/20230331/2023033111502613443948.png"
        },
        {
          "id": "https://www.techflowpost.com/newsletter/detail_51758.html",
          "author": null,
          "description": "深潮 TechFlow 消息，据AI姨监测，孙宇晨在九小时前通过两个地址从 Justlend 赎回 2000 万枚 USDT，随后全部充值进 Bitfinex。",
          "link": "https://www.techflowpost.com/newsletter/detail_51758.html",
          "publishedOn": "2024-07-02T02:10:50.000Z",
          "wordCount": 479,
          "title": "孙宇晨9小时前从Justlend赎回2000万枚USDT后转入Bitfinex",
          "imageUrl": "https://upload.techflowpost.com/upload/images/20230331/2023033111502613443948.png"
        },
        {
          "id": "https://www.techflowpost.com/newsletter/detail_51757.html",
          "author": null,
          "description": "深潮 TechFlow 消息，Binance宣布在Simple Earn产品中添加Lista (LISTA)。在促销期间完成对 Simple Earn 锁定产品的 LISTA 的订阅，可获得高达 11.9%*的 APR 奖励。",
          "link": "https://www.techflowpost.com/newsletter/detail_51757.html",
          "publishedOn": "2024-07-02T02:03:12.000Z",
          "wordCount": 493,
          "title": "Binance 在简单收益锁定产品上添加 LISTA",
          "imageUrl": "https://upload.techflowpost.com/upload/images/20230331/2023033111502613443948.png"
        },
        {
          "id": "https://www.techflowpost.com/newsletter/detail_51756.html",
          "author": null,
          "description": "深潮 TechFlow 消息，专为 DePIN 生态提供 ESG 数据的预言机项目 Nubila 宣布启动新一轮融资，目前已筹集 250 万美元，IoTeX、VeChain 及 Boston Consulting Group 领投，OrangeDAO、MH Ventures、Future Money Group、SNZ Capital、DePINsurf、Kronos Research、Taisu Ventures、Bytetrade、WaterDrip、Deepin Lab、Assembly Partners、Cyber、Radiance Ventures 和 Genopets 参投。",
          "link": "https://www.techflowpost.com/newsletter/detail_51756.html",
          "publishedOn": "2024-07-02T02:01:07.000Z",
          "wordCount": 529,
          "title": "预言机项目 Nubila 已完成 250 万美元融资，IoTeX等领投",
          "imageUrl": "https://upload.techflowpost.com/upload/images/20230331/2023033111502613443948.png"
        },
        {
          "id": "https://www.techflowpost.com/newsletter/detail_51755.html",
          "author": null,
          "description": "深潮 TechFlow 消息，Solana生态NFT平台Metaplex 宣布其 DAO 进入新阶段。6月，Metaplex 协议将 50% 的5月费用（4,490 SOL）和部分历史费用（5,510 SOL）用于购买 $MPLX，总计向 Metaplex DAO 贡献了 380 万 $MPLX。6月协议共产生 8,735 SOL 费用。\n\n此前消息，Solana上NFT平台Metaplex推出NFT标准Core，50%的协议费用将购买MPLX。",
          "link": "https://www.techflowpost.com/newsletter/detail_51755.html",
          "publishedOn": "2024-07-02T01:53:06.000Z",
          "wordCount": 507,
          "title": "Metaplex于6月花费1万枚SOL回购MPLX，向Metaplex DAO贡献380万MPLX",
          "imageUrl": "https://upload.techflowpost.com/upload/images/20230331/2023033111502613443948.png"
        },
        {
          "id": "https://www.techflowpost.com/newsletter/detail_51754.html",
          "author": null,
          "description": "深潮 TechFlow 消息，Robinhood宣布收购人工智能投资研究平台Pluto Capital Inc.，加速智能数据驱动投资时代。\n\nPluto创始人兼CEO Jacob Sansbury已加入Robinhood团队，加速产品规划，并帮助整合AI能力。",
          "link": "https://www.techflowpost.com/newsletter/detail_51754.html",
          "publishedOn": "2024-07-02T01:36:34.000Z",
          "wordCount": 482,
          "title": "Robinhood 收购人工智能投资研究平台 Pluto",
          "imageUrl": "https://upload.techflowpost.com/upload/images/20230331/2023033111502613443948.png"
        },
        {
          "id": "https://www.techflowpost.com/newsletter/detail_51753.html",
          "author": null,
          "description": "深潮 TechFlow 消息， 据彭博社报道，资产管理公司贝莱德将以32亿美元现金收购私人资本数据库提供商Preqin，此次收购增强了贝莱德在快速增长的私人资产市场中监督风险和分析数据的能力，并扩展了其Aladdin技术系统。\n\n该交易预计将在今年年底前完成，但需获得监管部门和其他必要的批准。",
          "link": "https://www.techflowpost.com/newsletter/detail_51753.html",
          "publishedOn": "2024-07-02T01:33:29.000Z",
          "wordCount": 469,
          "title": "贝莱德将以32亿美元收购私人资本数据库提供商Preqin",
          "imageUrl": "https://upload.techflowpost.com/upload/images/20230331/2023033111502613443948.png"
        },
        {
          "id": "https://www.techflowpost.com/newsletter/detail_51752.html",
          "author": null,
          "description": "深潮 TechFlow 消息，热门加密游戏 Pixels 在迁移至以太坊游戏网络 Ronin 并推出代币后，吸引了数百万玩家。创始人 Luke Barwikowski 透露，团队正开发 Pixels 宇宙中的其他游戏，并与外部开发者合作。\n\nBarwikowski 表示，团队设定方向后交由外部开发，再添加区块链元素。他还提到可能会在 Telegram 上推出游戏，探索该平台的潜力。Pixels 正在开发内部故事背景，并计划推出移动应用，尝试 iOS 和 Android 上的激励下载模式。",
          "link": "https://www.techflowpost.com/newsletter/detail_51752.html",
          "publishedOn": "2024-07-02T01:27:06.000Z",
          "wordCount": 502,
          "title": "链游Pixels创始人：正与其他团队合作开发更多Pixels游戏，并考虑基于Telegram的项目",
          "imageUrl": "https://upload.techflowpost.com/upload/images/20230331/2023033111502613443948.png"
        },
        {
          "id": "https://www.techflowpost.com/newsletter/detail_51751.html",
          "author": null,
          "description": "深潮 TechFlow 消息， 根据 CryptoQuant 的数据，比特币网络的算力下降已降至自2022年12月以来的最低水平，当时正值 FTX 崩溃和熊市最深处。\n\n根据 CryptoQuant 的数据，当前比特币真实算力降幅为 -7.6%，这可能表明去中心化资产的价格已见底。\n\n其他指标如比特币交易所储备、矿工位置指数（MPI）和比特币矿工储备也支持市场见底的观点，均显示出低卖压的迹象。",
          "link": "https://www.techflowpost.com/newsletter/detail_51751.html",
          "publishedOn": "2024-07-02T01:19:04.000Z",
          "wordCount": 494,
          "title": "比特币哈希率下降至 2022 年 12 月以来的最低水平",
          "imageUrl": "https://upload.techflowpost.com/upload/images/20230331/2023033111502613443948.png"
        },
        {
          "id": "https://www.techflowpost.com/newsletter/detail_51750.html",
          "author": null,
          "description": "深潮 TechFlow 消息，Binance.US 称法院决定 SEC 对其案件将继续进行。Binance.US 表示已做好准备，并期待司法程序推进。\n\nBinance.US 强调，其成立是为美国客户服务，遵守美国法规，保持 1:1 储备，拥有强大的合规和风险管理程序。尽管 SEC 在 11 个月的调查中未发现不当行为，但仍采取了过度监管。\n\nBinance.US 对其立场充满信心，认为 SEC 的案件缺乏事实和法律支持，并相信法院最终将验证这一立场。同时，Binance.US 将继续为客户和社区提供服务，并推出新功能和更新。",
          "link": "https://www.techflowpost.com/newsletter/detail_51750.html",
          "publishedOn": "2024-07-02T01:13:26.000Z",
          "wordCount": 504,
          "title": "Binance.US：已做好SEC诉讼继续进行的准备，SEC 的指控没有事实或法律依据",
          "imageUrl": "https://upload.techflowpost.com/upload/images/20230331/2023033111502613443948.png"
        },
        {
          "id": "https://www.techflowpost.com/newsletter/detail_51749.html",
          "author": null,
          "description": "深潮 TechFlow 消息，稳定币发行商 Paxos获得新加坡央行的全面批准，可以发行稳定币，并与星展银行合作。\n\nPaxos的新加坡实体现在被允许作为主要支付机构提供“数字支付代币服务”。此外，Paxos还宣布与星展银行合作处理现金管理需求和保管稳定币储备。这一合作将扩大星展银行在数字资产生态系统中的参与。",
          "link": "https://www.techflowpost.com/newsletter/detail_51749.html",
          "publishedOn": "2024-07-02T01:05:25.000Z",
          "wordCount": 470,
          "title": "Paxos获新加坡央行的全面批准发行稳定币，并将与星展银行合作",
          "imageUrl": "https://upload.techflowpost.com/upload/images/20230331/2023033111502613443948.png"
        },
        {
          "id": "https://www.techflowpost.com/newsletter/detail_51748.html",
          "author": null,
          "description": "深潮 TechFlow 消息，The ETF Store 总裁 Nate Geraci 在 X 平台发布的文件显示，美国证券交易委员会（SEC）已确认收到 Hashdex Nasdaq Crypto Index US ETF 的 19b-4 表格申请，该产品将同时持有现货比特币（BTC）和以太坊（ETH）。\n\n此前消息，彭博 ETF 分析师 James Seyffart 表示，Hashdex提交以太坊和比特币双重 ETF 申请。",
          "link": "https://www.techflowpost.com/newsletter/detail_51748.html",
          "publishedOn": "2024-07-02T01:00:08.000Z",
          "wordCount": 522,
          "title": "SEC已确认收到Hashdex提交的以太坊和比特币双重 ETF 申请",
          "imageUrl": "https://upload.techflowpost.com/upload/images/20230331/2023033111502613443948.png"
        },
        {
          "id": "https://www.techflowpost.com/newsletter/detail_51747.html",
          "author": null,
          "description": "深潮 TechFlow 消息，Fantom 宣布第三个 Sonic 治理提案获得通过。该提案将在 Sonic 网络上线六个月后，开始按比例铸造新代币，用于营销、生态系统增长和合作。\n\n启动与 2 亿美元 FTM Sonic Labs 创新基金合作的项目，并加速 Sonic Labs 改进的资助计划，其中包括：\n\n\n \n Sonic Spark：为早期创始人和新一代开发者提供创新支持。\n \n \n \nSonic University：为大学生提供资源和指导，帮助他们在 Sonic 上构建 dApps。\n \n \n \n此外，创新的年度销毁机制确保所有新铸造的代币都用于网络增长，未使用的代币将被销毁。\n \n\n\n此外，如果社区决定在六年内每年将通货膨胀率控制在 1.5%，那么每年将铸造47,625,000枚代币。如果Sonic Labs当年仅使用500万枚代币，Sonic Foundation将销毁剩余代币。",
          "link": "https://www.techflowpost.com/newsletter/detail_51747.html",
          "publishedOn": "2024-07-02T00:53:48.000Z",
          "wordCount": 516,
          "title": "Fantom通过“在Sonic网络上线六个月后按比例铸造新代币，确保网络的持续增长和创新”的提案",
          "imageUrl": "https://upload.techflowpost.com/upload/images/20230331/2023033111502613443948.png"
        },
        {
          "id": "https://www.techflowpost.com/newsletter/detail_51746.html",
          "author": null,
          "description": "深潮 TechFlow 消息，据余烬监测，某鲸鱼/机构凌晨 1:40 将 1,800 BTC (价值约1.14亿美元) 转进币安后，BTC 价格随后便开始下跌，由 $63.8K 回调至现在的 $62.9K。\n\n该鲸鱼/机构此前在 6/20-21 期间从币安和 OKX 提出 6,725 BTC (价值约4.37亿美元)。\n\n不过可能是对行情的不看好，他从 6/27 开始将 BTC 转入币安。在最近 5 天里以 $62.3K 的均价向币安转移了 3,481 BTC (2.17亿美元)。 他还持有 7,867 枚 BTC (4.94亿美元)。",
          "link": "https://www.techflowpost.com/newsletter/detail_51746.html",
          "publishedOn": "2024-07-02T00:29:14.000Z",
          "wordCount": 535,
          "title": "某鲸鱼/机构凌晨将1.14亿美元BTC转入币安，仍持有4.94亿美元BTC",
          "imageUrl": "https://upload.techflowpost.com/upload/images/20230331/2023033111502613443948.png"
        },
        {
          "id": "https://www.techflowpost.com/newsletter/detail_51745.html",
          "author": null,
          "description": "深潮 TechFlow 消息，Polkadot 上半年财库花费 8700 万美元（1100 万 DOT），其中 13% 通过执行机构（赏金和集体）支出。\n\n财库管理资产总额为 2.45 亿美元（3800 万 DOT），其中 1.88 亿美元（2900 万 DOT）为流动资产。\n\n800 万美元为 USDT 和 USDC 稳定币，另有 250 万 DOT（1600 万美元）用于持续购买稳定币。\n\n2450 万美元（380 万 DOT）用于战略性计划如营销、DeFi 工具、游戏和业务发展等，640 万美元（100 万 DOT）用于游戏领域的空投。\n\n此外，Polkadot 提供了 160 万 DOT（约 1000 万美元）作为流动性注入 DeFi 市场。\n\n按目前每 6 个月 8700 万美元的消耗速度计算，Polkadot 的资金还可维持大约 2 年。但由于加密货币资产的波动性，这一预测存在不确定性。",
          "link": "https://www.techflowpost.com/newsletter/detail_51745.html",
          "publishedOn": "2024-07-02T00:26:05.000Z",
          "wordCount": 564,
          "title": "Polkadot财库上半年拨款8700万美元，剩余资金还可维持约2年",
          "imageUrl": "https://upload.techflowpost.com/upload/images/20230331/2023033111502613443948.png"
        },
        {
          "id": "https://www.techflowpost.com/newsletter/detail_51744.html",
          "author": null,
          "description": "深潮 TechFlow 消息，因内部管理失误和向投资者披露虚假信息，Silvergate Capital Corp. 同意支付 6300 万美元以和解美国和加州监管机构的指控。\n\nSilvergate、前 CEO Alan Lane 和前 COO Kathleen Fraher 同意支付罚款，并接受五年内不得担任其他上市公司高管的禁令。罚款包括联邦储备的 4300 万美元和加州的 2000 万美元。SEC 也施加了 5000 万美元的罚款，但可能会被其他罚款抵消。\n\n此前消息，SEC 指控 Silvergate 未能检测到其主要客户 FTX 的近 90 亿美元可疑转账，并未能对其核心产品 Silvergate Exchange Network 进行适当监控。Silvergate 发言人表示，这些和解是该银行有序清算的一部分，并成功结束了各项调查。",
          "link": "https://www.techflowpost.com/newsletter/detail_51744.html",
          "publishedOn": "2024-07-02T00:08:40.000Z",
          "wordCount": 545,
          "title": "加密友好银行 Silvergate 同意支付 6300 万美元与SEC等达成和解",
          "imageUrl": "https://upload.techflowpost.com/upload/images/20230331/2023033111502613443948.png"
        },
        {
          "id": "https://www.techflowpost.com/newsletter/detail_51743.html",
          "author": null,
          "description": "深潮 TechFlow 消息，据官方消息，模块化游戏Layer1 Tabi在X平台发布了与知名Coser Yami合作的魔性视频。视频风格洗脑魔性，迅速引起热议。 \n\nYami是一位拥有近500万粉丝的知名Coser和模特，以其《工作细胞》中的“血小板”COS作品爆红网络。此外，Yami还是《Artery Gear: Fusion》中Nio的官方Coser。",
          "link": "https://www.techflowpost.com/newsletter/detail_51743.html",
          "publishedOn": "2024-07-02T00:01:49.000Z",
          "wordCount": 480,
          "title": "模块化游戏Layer1 Tabi公布与知名Coser合作视频",
          "imageUrl": "https://upload.techflowpost.com/upload/images/20230331/2023033111502613443948.png"
        },
        {
          "id": "https://www.techflowpost.com/newsletter/detail_51742.html",
          "author": null,
          "description": "深潮 TechFlow 消息，据路透社报道，美国证券交易委员会（SEC）在一家联邦法院起诉加密银行Silvergate Capital，指控其证券欺诈。\n\nSEC表示，在2022年FTX崩溃后，Silvergate关于其银行保密制度、反洗钱合规计划以及糟糕的财务状况误导了投资者。与此同时，该银行未能监测到FTX和其关联实体近90亿美元的可疑转账。",
          "link": "https://www.techflowpost.com/newsletter/detail_51742.html",
          "publishedOn": "2024-07-02T00:00:50.000Z",
          "wordCount": 470,
          "title": "SEC起诉加密银行Silvergate证券欺诈",
          "imageUrl": "https://upload.techflowpost.com/upload/images/20230331/2023033111502613443948.png"
        },
        {
          "id": "https://www.techflowpost.com/newsletter/detail_51741.html",
          "author": null,
          "description": "深潮 TechFlow 消息，据 Lookonchain 监测，7 月 1 日 9 只 ETF 增持 526 枚比特币（+3300 万美元）。Blackrock 增持 1366 枚比特币（+8590 万美元），目前持有 306,979 枚比特币（193 亿美元）。Grayscale 减持 198 枚比特币（-1240 万美元），目前持有 275,758 枚比特币（173.4 亿美元）。",
          "link": "https://www.techflowpost.com/newsletter/detail_51741.html",
          "publishedOn": "2024-07-01T16:00:06.000Z",
          "wordCount": 534,
          "title": "今日9只 ETF 增持526枚 BTC，价值约 3300 万美元",
          "imageUrl": "https://upload.techflowpost.com/upload/images/20230331/2023033111502613443948.png"
        }
      ]
    }
  ],
  "cliVersion": "1.15.1"
}