{
  "sources": [
    {
      "title": "Web3世界",
      "feedUrl": "https://www.web3sj.com/feed/",
      "siteUrl": "https://www.web3sj.com",
      "articles": [
        {
          "id": "https://www.web3sj.com/?p=123966",
          "author": "Gao",
          "description": "Solana 的原生代币 SOL 价格 目前148.03 美元。在 9 月 29 日达到 161.80 美元的峰值，创下七周以来的最高水平后，两天内下跌了 9%。这一调整反映了更广泛的山寨币市值（不包括稳定币），该市值在 9 月底达到约 8000 亿美元，然后在 10 月 1 日跌至 7390 亿美元。",
          "link": "https://www.web3sj.com/news/123966/",
          "publishedOn": "2024-10-05T14:22:14.000Z",
          "wordCount": 967,
          "title": "Solana DApps数量一周内增长了46%——180美元的SOL是下一站吗？",
          "imageUrl": "https://www.web3sj.com/wp-content/uploads/2024/10/1728138113258.png"
        },
        {
          "id": "https://www.web3sj.com/?p=123961",
          "author": "Gao",
          "description": "该基金仅向合格投资者开放，是 Grayscale 单一资产加密投资产品套件的补充。8 月，Grayscale 推出了三只信托基金，分别投资 Sky（以前的 MakerDAO）、Bittensor 和 Sui 的原生协议代币。",
          "link": "https://www.web3sj.com/definews/123961/",
          "publishedOn": "2024-10-05T14:19:46.000Z",
          "wordCount": 900,
          "title": "Grayscale推出Aave投资基金",
          "imageUrl": "https://www.web3sj.com/wp-content/uploads/2024/10/17281379544581.png"
        },
        {
          "id": "https://www.web3sj.com/?p=123949",
          "author": "Gao",
          "description": "我之所以改变主意，是因为我在加密货币投资中最重要的原则就是保持开放的心态，愿意尝试新事物。成为极端主义者（只信仰一种投资策略或币种）是很危险的，但识别并投资那些极端主义社区却可能带来巨大的回报。",
          "link": "https://www.web3sj.com/news/123949/",
          "publishedOn": "2024-10-05T14:16:52.000Z",
          "wordCount": 940,
          "title": "透析Memecoins:下一步是什么？",
          "imageUrl": "https://www.web3sj.com/wp-content/uploads/2024/10/17281377791711.png"
        },
        {
          "id": "https://www.web3sj.com/?p=123937",
          "author": "Gao",
          "description": "正如 Tether CEO Paolo Ardoino 所言，USDT 最初只是“一种加密货币”，但随着时间的发展，其使用范围早已超出“加密货币”的范畴，而是成为了一种“应用广泛的数字美元”，具体而言，其已经被广泛应用于跨境支付、生活消费以及加密货币兑换等多种场景。",
          "link": "https://www.web3sj.com/news/123937/",
          "publishedOn": "2024-10-05T14:13:41.000Z",
          "wordCount": 1241,
          "title": "“第一稳定币”USDT市值创新高，揭秘Tether背后的千亿商业帝国",
          "imageUrl": "https://www.web3sj.com/wp-content/uploads/2024/10/1728137525300.png"
        },
        {
          "id": "https://www.web3sj.com/?p=123928",
          "author": "Gao",
          "description": "写在前面：9 月 21 日，为期两天的 BeWater Growth Hacker Camp 第二期在新加坡圆满落幕。在本次活动中，来自 Web3 领域顶级项目与 VC 的导师们深…",
          "link": "https://www.web3sj.com/nftnews/123928/",
          "publishedOn": "2024-10-05T14:05:52.000Z",
          "wordCount": 1070,
          "title": "Crypto增长论｜StepN 联创 Yawn：NFT与熟人社交的未来",
          "imageUrl": "https://www.web3sj.com/wp-content/uploads/2024/10/1728136957632.png"
        },
        {
          "id": "https://www.web3sj.com/?p=123925",
          "author": "Gao",
          "description": "Bitwise 将推出比特币和国债轮换策略 ETF（BITC）。比特币现货ETF历史累计净流入已达184.99亿美元，ETF 净资产比率达4.68%。TON 社区宣布启动 Memelandia 计划。",
          "link": "https://www.web3sj.com/news/123925/",
          "publishedOn": "2024-10-05T13:36:57.000Z",
          "wordCount": 1000,
          "title": "Web3世界日报（2024-10.5）",
          "imageUrl": "https://www.web3sj.com/wp-content/uploads/2024/10/2024100513345181.jpg"
        },
        {
          "id": "https://www.web3sj.com/?p=123910",
          "author": "Gao",
          "description": "9 月 30 日，BTC 上涨势头显露衰竭之后，从 6.5 万美元一路下探，今日甚至一度跌破 6 万美元关口，最低报价 59828 美元。以太坊也跟随比特币起伏波动，自 2700 美元后，一路下跌至 2300 美元上方，离 2100 美元近在咫尺，险些创下数月以来新低。部分山寨币自 9 月中旬以来的涨幅，也很快被抹去大半。",
          "link": "https://www.web3sj.com/transaction/123910/",
          "publishedOn": "2024-10-04T13:53:47.000Z",
          "wordCount": 916,
          "title": "市场猛涨后迎来大回调，都是地缘政治惹的祸？",
          "imageUrl": "https://www.web3sj.com/wp-content/uploads/2024/10/1728049984.png"
        },
        {
          "id": "https://www.web3sj.com/?p=123907",
          "author": "Gao",
          "description": "实际上，每项创新技术都会经历波澜起伏。直接将「某些技术的用例不当」推断为「这项技术本身不好」是不对的，因为技术本身并没有好坏之分。",
          "link": "https://www.web3sj.com/news/123907/",
          "publishedOn": "2024-10-04T13:50:32.000Z",
          "wordCount": 1009,
          "title": "a16z合伙人：如何看待「Crypto 已死」的论调？",
          "imageUrl": "https://www.web3sj.com/wp-content/uploads/2024/10/17280497181.png"
        },
        {
          "id": "https://www.web3sj.com/?p=123903",
          "author": "Gao",
          "description": "加密世界永远不缺口水战争，只是没有想到这一次斯诺登加入了战局。 没错，这里所说的是斯诺登就是前美国国家安全局举报人，被加密行业视为反抗中心化权威的代表人物。最近，在新加坡举行的 T…",
          "link": "https://www.web3sj.com/news/123903/",
          "publishedOn": "2024-10-04T13:47:48.000Z",
          "wordCount": 806,
          "title": "斯诺登质疑Solana过于中心化，Helius CEO强势反击",
          "imageUrl": "https://www.web3sj.com/wp-content/uploads/2024/10/17280496391.png"
        },
        {
          "id": "https://www.web3sj.com/?p=123894",
          "author": "Gao",
          "description": "在当前竞争激烈的加密市场中，护城河的概念不再局限于传统的流动性与 TVL。随着 DeFi 应用的迅速发展，仅依靠流动性优势已不足以在长期中立于不败之地。本文深入探讨了加密应用如何通过品牌、用户体验的差异化以及持续推出新功能，来建立真正具有防御力的护城河。",
          "link": "https://www.web3sj.com/news/123894/",
          "publishedOn": "2024-10-04T13:43:55.000Z",
          "wordCount": 911,
          "title": "加密项目如何才能拥有护城河？",
          "imageUrl": "https://www.web3sj.com/wp-content/uploads/2024/10/17280494121.png"
        }
      ]
    },
    {
      "title": "白话区块链 - 快讯",
      "feedUrl": "https://rsshub.app/hellobtc/news",
      "siteUrl": "https://www.hellobtc.com/news",
      "articles": [
        {
          "id": "https://www.hellobtc.com/news/202409/22992.html",
          "author": null,
          "description": "LayerZero 基金会宣布将与 a16z Crypto、Animoca Brands、Atrum、Delphi Ventures、Faction、Franklin Templeton、King River、Lightspeed、PayPal Ventures 和 Spartan 等合作推出 lzCatalyst 计划，旨在向围绕 LayerZero 构建的新型全链应用提供总计最高 3 亿美元的投资。",
          "link": "https://www.hellobtc.com/news/202409/22992.html",
          "publishedOn": "2024-09-18T01:48:00.000Z",
          "wordCount": 324,
          "title": "LayerZero与a16z等合作推出lzCatalyst 计划，旨在向全链Dapp提供最高3亿美元的投资",
          "imageUrl": "https://www.hellobtc.com/d/file/202106/bff70034ff497aeca9460d3429e7d08f.jpg"
        },
        {
          "id": "https://www.hellobtc.com/news/202409/22991.html",
          "author": null,
          "description": "9月18日消息，Animoca Brands联创Yat Siu表示，中国香港是加密风投和链游开发商Animoca Brands Corp.潜在上市的“有力竞争者”。Siu在新加坡举行的一次会议上接受采访时表示，部分原因是该公司的总部设在新加坡，随着官员们寻求发展一个加密中心，与数字资产相关的活动已经扩大。但他周三表示，任何IPO计划都可能需要“几年时间才能真正形成”，目前的重点是打造业务。 Siu上个月对《南华早报》表示，在二级市场上，Animoca股份估值在15亿至30亿美元之间。相比之下，该公司在2022年的一轮融资中估值为59亿美元。Siu补充称，该公司不寻求筹集新资金。",
          "link": "https://www.hellobtc.com/news/202409/22991.html",
          "publishedOn": "2024-09-18T01:48:00.000Z",
          "wordCount": 313,
          "title": "Animoca Brands联创：香港是Animoca Brands进行IPO的“有力竞争者”选择",
          "imageUrl": "https://www.hellobtc.com/d/file/202106/bff70034ff497aeca9460d3429e7d08f.jpg"
        },
        {
          "id": "https://www.hellobtc.com/news/202409/22990.html",
          "author": null,
          "description": "1. Bitwise CIO：以太坊低迷并非生死攸关，逆向押注或具潜力。\n\n2. 摩根大通CEO承认区块链具有价值，但仍对加密货币持怀疑态度。\n\n3. 马斯克斥资支持共和党候选人，料对众议院控制权归属产生重要影响。\n\n4. 比特币创逾一个月最大盘中涨幅，受美联储降息前景提振。\n\n5. 美众议院金融服务委员会主席：相信加密市场结构法案将于年底获批。\n\n6. CryptoQuant：CEX比特币存款地址数量降至近几年最低水平，或表明抛压有所减轻。\n\n7. 美SEC指控NanoBit和CoinW6涉嫌利用社媒进行加密货币“关系投资骗局”。\n\n8. 据CME“美联储观察”：美联储本周降息50个基点的概率为63%。\n\n9. 穆迪：DePIN技术潜力巨大但面临多重挑战。\n\n10. Base单日交易量超过450万笔，创下新高。\n\n11. Chainalysis报告：溢价指数上升推动韩国加密市场增长。",
          "link": "https://www.hellobtc.com/news/202409/22990.html",
          "publishedOn": "2024-09-18T00:49:00.000Z",
          "wordCount": 326,
          "title": "白话区块链早报：Bitwise CIO表示以太坊低迷并非生死攸关，逆向押注或具潜力",
          "imageUrl": "https://www.hellobtc.com/d/file/202106/bff70034ff497aeca9460d3429e7d08f.jpg"
        },
        {
          "id": "https://www.hellobtc.com/news/202409/22989.html",
          "author": null,
          "description": "9月18日消息，谷歌云（Google Cloud）于X发文表示，基于支持Web3开发者的承诺，其宣布推出新的区块链RPC（远程过程调用）服务预览版，细节如下： 1、为开发人员提供一种与区块链数据交互的简化方式； 2、提供可扩展的可靠解决方案，消除了管理节点基础设施的复杂性； 3、免费层，每秒100次请求+每天100万次请求。",
          "link": "https://www.hellobtc.com/news/202409/22989.html",
          "publishedOn": "2024-09-18T00:44:00.000Z",
          "wordCount": 302,
          "title": "谷歌云推出新区块链RPC服务预览版",
          "imageUrl": "https://www.hellobtc.com/d/file/202106/bff70034ff497aeca9460d3429e7d08f.jpg"
        },
        {
          "id": "https://www.hellobtc.com/news/202409/22988.html",
          "author": null,
          "description": "桥水基金创始人达利欧表示，美联储降息25个基点将是正确的；如果考虑到抵押贷款，则需要降息50个基点。",
          "link": "https://www.hellobtc.com/news/202409/22988.html",
          "publishedOn": "2024-09-18T00:44:00.000Z",
          "wordCount": 302,
          "title": "桥水基金创始人达利欧：美联储降息25个基点将是正确的",
          "imageUrl": "https://www.hellobtc.com/d/file/202106/bff70034ff497aeca9460d3429e7d08f.jpg"
        },
        {
          "id": "https://www.hellobtc.com/news/202409/22987.html",
          "author": null,
          "description": "9月18日消息，加密行业参与者成立了一个名为“去中心化人工智能协会”（Decentralized AI Society，简称DAIS）的非营利组织，致力于解决人工智能（AI）行业垄断的可能性。 该小组由Michael Casey领导，他曾是CoinDesk的首席内容官，也是Consensus的主席。DAIS的8个创始成员包括CETIAI、Filecoin Foundation、Bloq、Hypercycle、Morpheus、Hemi、Odyssey和Lumerin。",
          "link": "https://www.hellobtc.com/news/202409/22987.html",
          "publishedOn": "2024-09-18T00:44:00.000Z",
          "wordCount": 305,
          "title": "Filecoin Foundation等行业参与者成立去中心化人工智能协会",
          "imageUrl": "https://www.hellobtc.com/d/file/202106/bff70034ff497aeca9460d3429e7d08f.jpg"
        },
        {
          "id": "https://www.hellobtc.com/news/202409/22986.html",
          "author": null,
          "description": "据链上分析师@ai_9684xtpa监测，ETH/BTC汇率多头James Fickel过去8小时累计将11338枚WETH出售为WBTC，约2678万美元，卖出均价2362美元，目前他还存有142,103枚stETH并借出1,308枚WBTC，健康度3.42。",
          "link": "https://www.hellobtc.com/news/202409/22986.html",
          "publishedOn": "2024-09-18T00:43:00.000Z",
          "wordCount": 303,
          "title": "ETH/BTC多头James Fickel过去8小时将11338枚WETH出售为WBTC，约2678万美元",
          "imageUrl": "https://www.hellobtc.com/d/file/202106/bff70034ff497aeca9460d3429e7d08f.jpg"
        },
        {
          "id": "https://www.hellobtc.com/news/202409/22985.html",
          "author": null,
          "description": "澳洲联储助理主席琼斯表示，将启动关于批发层面的央行数字货币(CBDC)和代币化商业银行存款的行业项目。致力于为期三年的数字货币研究项目。我们会优先考虑批发央行数字货币。批发央行数字货币相比于零售央行数字货币具有更大的经济效益。零售央行数字货币的推出将由政府决定，需通过立法。",
          "link": "https://www.hellobtc.com/news/202409/22985.html",
          "publishedOn": "2024-09-18T00:43:00.000Z",
          "wordCount": 307,
          "title": "澳洲联储：会优先考虑批发CBDC",
          "imageUrl": "https://www.hellobtc.com/d/file/202106/bff70034ff497aeca9460d3429e7d08f.jpg"
        },
        {
          "id": "https://www.hellobtc.com/news/202409/22984.html",
          "author": null,
          "description": "穆迪首次发布关于DePIN（去中心化物理基础设施）的报告指出，该技术有助于现有网络扩展和创新，但模糊的监管环境可能阻碍其广泛应用。报告称，DePIN通过结合区块链与现实世界网络，如电信、存储等，可提高网络可靠性并降低运营成本。然而，技术推广面临诸多挑战，包括监管不明确、网络安全风险及巨大的基础设施投资需求。报告还提到Helium作为该领域的成功案例，吸引了超过35万用户参与。",
          "link": "https://www.hellobtc.com/news/202409/22984.html",
          "publishedOn": "2024-09-18T00:43:00.000Z",
          "wordCount": 297,
          "title": "穆迪：DePIN技术潜力巨大但面临多重挑战",
          "imageUrl": "https://www.hellobtc.com/d/file/202106/bff70034ff497aeca9460d3429e7d08f.jpg"
        },
        {
          "id": "https://www.hellobtc.com/news/202409/22983.html",
          "author": null,
          "description": "比特币Layer2网络Stacks正在与基于Move语言的Layer1网络Aptos集成，本次合作将使sBTC引入Aptos网络。",
          "link": "https://www.hellobtc.com/news/202409/22983.html",
          "publishedOn": "2024-09-17T15:50:00.000Z",
          "wordCount": 298,
          "title": "Stacks集成Aptos，将sBTC引入Aptos网络",
          "imageUrl": "https://www.hellobtc.com/d/file/202106/bff70034ff497aeca9460d3429e7d08f.jpg"
        }
      ]
    }
  ],
  "cliVersion": "1.15.1"
}