{
  "sources": [
    {
      "title": "DeFi之道",
      "feedUrl": "https://www.defidaonews.com/feed",
      "siteUrl": "https://www.defidaonews.com",
      "articles": [
        {
          "id": "https://www.defidaonews.com/article/6833148",
          "author": "元宇宙日爆",
          "description": "AIGC正全面渗入人类的视听体验。",
          "link": "https://www.defidaonews.com/article/6833148",
          "publishedOn": "2023-09-18T02:26:58.000Z",
          "wordCount": 150,
          "title": "剧情反转，抵制AI音乐的华纳签了位虚拟歌手",
          "imageUrl": "https://appserversrc.8btc.cn/DBADA82E83F535A509DA39CCFDC9590F/1695004009/FjNwmnjIBH-Z_QLW-NHoyixVzR_9.png?imageView2/1/w/500/h/300"
        },
        {
          "id": "https://www.defidaonews.com/article/6831550",
          "author": "王佳健",
          "description": "这只视频，你分得出是AI还是人做的，算我输。",
          "link": "https://www.defidaonews.com/article/6831550",
          "publishedOn": "2023-09-01T05:30:25.000Z",
          "wordCount": 129,
          "title": "全流程AI制作的视频广告来了，成本接近传统手法的千分之一……",
          "imageUrl": "https://appserversrc.8btc.cn/DBE9D93AA7E674C9030F14534C053990/1693545485/Fke0RpyPV14Nm3vLi0IonxULAZxQ.png?imageView2/1/w/500/h/300"
        }
      ]
    },
    {
      "title": "Web3世界",
      "feedUrl": "https://www.web3sj.com/feed/",
      "siteUrl": "https://www.web3sj.com",
      "articles": [
        {
          "id": "https://www.web3sj.com/?p=89102",
          "author": "Gao",
          "description": "Aave社区正对“GHO流动性策略升级”ARFC提案进行投票。灰度已提交第二个以太坊期货ETF申请，追踪以太坊期货合约。Arbitrum奥德赛活动下周将重新上线，为其7周。",
          "link": "https://www.web3sj.com/news/89102/",
          "publishedOn": "2023-09-20T11:35:55.000Z",
          "wordCount": 930,
          "title": "Web3世界日报（2023-9.20）",
          "imageUrl": "https://www.web3sj.com/wp-content/uploads/2023/09/2023092011341945.jpg"
        },
        {
          "id": "https://www.web3sj.com/?p=89090",
          "author": "Gao",
          "description": "在 Token 2049 活动中 Telegram CTO John Hyman 与 TON 基金会总裁 Steven Yun 一起出席演讲，Steven Yun 表示，未来建立在 TON 区块链上的项目有着优先参加 Telegram 的广告平台 Telegram Ads 的机会。Steven 甚至还说「Telegram 只会和 TON 区块链整合」。",
          "link": "https://www.web3sj.com/project/89090/",
          "publishedOn": "2023-09-20T09:19:51.000Z",
          "wordCount": 1286,
          "title": "TON的重生之路：与Telegram再续前缘，8亿用户或将实现Web3大规模应用",
          "imageUrl": "https://www.web3sj.com/wp-content/uploads/2023/09/1695201576751.png"
        },
        {
          "id": "https://www.web3sj.com/?p=89079",
          "author": "Gao",
          "description": "在 2022 年的 ETH Seoul 大会上，以太坊的联合创始人 Vitalik Buterin 表达了他对 ZK-rollups 在 Layer 2 扩展竞争中获胜的信心。时至 2023 年，zkSync Era 已成为 ZK-rollups 领域的重要焦点之一。",
          "link": "https://www.web3sj.com/project/89079/",
          "publishedOn": "2023-09-20T09:10:26.000Z",
          "wordCount": 1350,
          "title": "解锁zkSync Era：开创全新的Layer2扩展时代？",
          "imageUrl": "https://www.web3sj.com/wp-content/uploads/2023/09/0b869b7c9c19adc6fdabfd1e93de7724.jpg"
        },
        {
          "id": "https://www.web3sj.com/?p=89073",
          "author": "Gao",
          "description": "早期许多协议採用了简单的挖矿和提供流动性的经济模型，将代币视为一种简单的激励手段，用于吸引用户参与和追求短期获利。然而，这种激励方式虽然直接，但缺乏有效的再分配机制。以去中心化交易所（DEX）为例，当代币发行和所有手续费直接分配给流动性提供者时，缺乏对流动性提供者的长期激励。",
          "link": "https://www.web3sj.com/definews/89073/",
          "publishedOn": "2023-09-20T08:41:58.000Z",
          "wordCount": 985,
          "title": "探讨DeFi经济模型：激励模式的设计与演进",
          "imageUrl": "https://www.web3sj.com/wp-content/uploads/2023/09/1695199294783.png"
        },
        {
          "id": "https://www.web3sj.com/?p=89068",
          "author": "Gao",
          "description": "Atman，一个深受赛博朋克精神启发的竞技game-fi项目，已经在游戏界树立了独特的标志。这款游戏以“公平”为核心，利用去中心化赛事服务合约和NFT-Mod资产编辑，力争实现基于DAO的用户的自治生态社区，结合了social-fi与e-sports的特色。它的愿景是让每位用户都有机会共享收益，成为新世界秩序中的一名创造者。",
          "link": "https://www.web3sj.com/gamefinews/89068/",
          "publishedOn": "2023-09-20T08:37:38.000Z",
          "wordCount": 848,
          "title": "自Alpha测试凯旋，卡牌链游Atman能否在熊市给出漂亮答卷？",
          "imageUrl": "https://www.web3sj.com/wp-content/uploads/2023/09/image-26.png"
        },
        {
          "id": "https://www.web3sj.com/?p=89065",
          "author": "Gao",
          "description": "在 web3 开发的前十年中，安全性和可用性往往处于权衡范围的两端，因此开发人员或企业想要构建良好的用户体验极其困难。如何从 Web2 转入 Web3？技术堡垒该如何突破？面对大部分企业的迷茫，a16z 给出了答案——选择 Bastion。",
          "link": "https://www.web3sj.com/news/89065/",
          "publishedOn": "2023-09-20T07:41:15.000Z",
          "wordCount": 1080,
          "title": "Bastion：a16z领投的「Web3 协调器」如何让企业无缝接加密世界？",
          "imageUrl": "https://www.web3sj.com/wp-content/uploads/2023/09/5-1695191498987.webp"
        },
        {
          "id": "https://www.web3sj.com/?p=89057",
          "author": "Gao",
          "description": "Aave 是以太坊上借贷龙头，现部署在 Polygon、Arbitrum、Optimism 等 9 条链上。该项目成立于 2017 年，初始版本为点对点借贷，后因借贷撮合效率低下而改版，借鉴 Compound 资金池借贷模型提供高流动性。Aave 当前为 V3 版本，该版本的目的是为提供更高的资本效率、更高的安全性和跨链借贷功能。",
          "link": "https://www.web3sj.com/definews/89057/",
          "publishedOn": "2023-09-20T07:33:43.000Z",
          "wordCount": 1087,
          "title": "LD Capital：Aave短期资金面分析",
          "imageUrl": "https://www.web3sj.com/wp-content/uploads/2023/09/1695195209609.png"
        },
        {
          "id": "https://www.web3sj.com/?p=89041",
          "author": "Gao",
          "description": "随着 CP 和 Layer 2 相继发展超链网络，其生态代币会在这其中发挥着什么样的作用，或者超链网络的发展给这些代币带来了哪些更多的可能性呢？为了讨论代币的未来发展趋势，本文先梳理了各自的代币模型，分析异同；再深入讨论各自的方案可能给代币带来的潜在影响，并挖掘出对应的投资价值等等。那么接下来，就让我们一起看看他们代币经济模型如何充分激发各自的潜能。",
          "link": "https://www.web3sj.com/news/89041/",
          "publishedOn": "2023-09-20T07:30:29.000Z",
          "wordCount": 1989,
          "title": "做Layer1还是Layer2?",
          "imageUrl": "https://www.web3sj.com/wp-content/uploads/2023/09/1695195011528.png"
        },
        {
          "id": "https://www.web3sj.com/?p=89037",
          "author": "Gao",
          "description": "LUKSO 表示，这种集成意味着用户将可以直接与通用配置文件和游戏中灵活的非同质化通证（NFT）进行交互。LUKSO 中的通用配置文件具有互操作性，代表着经过验证的数字身份，让用户可以控制自己的在线头像和数字资产。",
          "link": "https://www.web3sj.com/gamefinews/89037/",
          "publishedOn": "2023-09-20T06:46:50.000Z",
          "wordCount": 879,
          "title": "由ERC-20标准制定者联创的LUKSO入驻虚幻引擎，打破区块链游戏壁垒",
          "imageUrl": "https://www.web3sj.com/wp-content/uploads/2023/09/5cb85cd10c5eb0bb2e65646f123106a0.png"
        },
        {
          "id": "https://www.web3sj.com/?p=89030",
          "author": "Gao",
          "description": "社区提出给生态系统提供 ARB 激励的新治理提案获得支持并不奇怪，此前 Camelot 的提案在大量争议后被拒绝。经过大量讨论，社区得出的结论是以 5 千万 ARB 激励生态系统，这可能会对整个生态系统产生积极影响。",
          "link": "https://www.web3sj.com/news/89030/",
          "publishedOn": "2023-09-20T06:31:37.000Z",
          "wordCount": 957,
          "title": "Arbitrum：当下被低估的L2先驱，生态项目将迎来爆发",
          "imageUrl": "https://www.web3sj.com/wp-content/uploads/2023/09/1695191484602.png"
        }
      ]
    },
    {
      "title": "PANews - 快讯",
      "feedUrl": "https://rsshub.app/panewslab/news",
      "siteUrl": "https://panewslab.com/zh/news/index.html",
      "articles": [
        {
          "id": "https://panewslab.com/zh/articledetails/d0oyrk5w.html",
          "author": "PA一线",
          "description": "PANews 9月21日消息，据The Block报道，PayPal旗下支付平台Venmo将很快提供PayPal美元稳定币PYUSD。PayPal在一份新闻稿中指出，PYUSD将在“未来几周”上线。用户将能够通过PayPal、Venmo或兼容的外部钱包购买和发送PYUSD。Venmo是PayPal的子公司，于2021年开始提供加密货币购买服务。8月7日，PayPal与加密基础设施公司Paxos合作推出了PYUSD，完全由美元存款、短期国债和类似现金等价物支持。此后PayPal增加了加密货币兑换美元的服务，用户从9月11日开始可以将数字货币兑换成美元。",
          "link": "https://panewslab.com/zh/articledetails/d0oyrk5w.html",
          "publishedOn": "2023-09-20T20:03:12.000Z",
          "wordCount": 348,
          "title": "支付应用Venmo将在未来几周上线稳定币PYUSD",
          "imageUrl": "https://image.panewslab.com/images/logo1.jpg"
        },
        {
          "id": "https://panewslab.com/zh/articledetails/lkbi7hr1.html",
          "author": "PA一线",
          "description": "PANews 9月21日消息，据Cointelegraph报道，加密交易所JPEX已向澳大利亚证券投资委员会（ASIC）提交了注销申请。JPEX声称公司的所有成员都同意注销，公司不再经营业务，其资产不超过1000澳元，并且没有负债。9月13日，在新加坡举行的Token2049会议期间，香港警方逮捕了六名JPEX员工，指控他们经营无牌加密交易所。香港证券及期货事务监察委员会(SFC)当天表示，它收到了1000多份针对JPEX平台的投诉，损失超过10亿港元。公司网站目前已无法访问。此前JPEX发布了一份用户补偿计划，声称用户将在9月21日之前按照“一比一”的比例获得赔偿，他们的资产将被兑换为JPEX去中心化自治组织的股份。该交易所还表示，由于SFC的调查，第三方托管人“恶意冻结”了平台资产，导致了一场“前所未有的灾难”。",
          "link": "https://panewslab.com/zh/articledetails/lkbi7hr1.html",
          "publishedOn": "2023-09-20T19:50:17.000Z",
          "wordCount": 337,
          "title": "加密交易所JPEX已在澳大利亚申请注销登记",
          "imageUrl": "https://image.panewslab.com/images/logo1.jpg"
        },
        {
          "id": "https://panewslab.com/zh/articledetails/nb1lw53l.html",
          "author": "PA一线",
          "description": "PANews 9月21日消息，据官方消息，Optimism正出于资金管理目的进行私人代币销售，将向7名购买者出售大约1.16亿枚OP代币。这些代币有两年的锁定期。在锁定期间，购买者将能够将代币委托给无关联的第三方参与治理。这些代币来自OP代币金库的未分配部分，占初始OP代币供应的30%。从今天开始，将会有几笔交易用于发送这些代币。这是计划中的交易，希望社区对此知情。",
          "link": "https://panewslab.com/zh/articledetails/nb1lw53l.html",
          "publishedOn": "2023-09-20T19:30:30.000Z",
          "wordCount": 344,
          "title": "Optimism正出于资金管理目的出售1.16亿枚OP代币",
          "imageUrl": "https://image.panewslab.com/images/logo1.jpg"
        },
        {
          "id": "https://panewslab.com/zh/articledetails/2s5mmf00.html",
          "author": "PA一线",
          "description": "PANews 9月21日消息，美联储主席鲍威尔在货币政策新闻发布会上表示，坚决专注于双重使命。FOMC坚决致力于将通胀率降到2%，实现这一目标还有很长的路要走。目前的政策立场是限制性的。鉴于已经取得的进展，FOMC决定维持利率不变。保持利率不变不意味着我们已经达到我们所寻求的限制性立场，我们希望看到令人信服的证据，证明我们已经达到了适当的水平。我们将会逐次会议做出决策，如果合适，准备进一步提高利率。大多数政策制定者认为今年再次加息更有可能是合适的。",
          "link": "https://panewslab.com/zh/articledetails/2s5mmf00.html",
          "publishedOn": "2023-09-20T18:46:11.000Z",
          "wordCount": 343,
          "title": "美联储主席鲍威尔：坚决致力于将通胀率降到2%，如果合适将进一步加息",
          "imageUrl": "https://image.panewslab.com/images/logo1.jpg"
        },
        {
          "id": "https://panewslab.com/zh/articledetails/ke74qv1z.html",
          "author": "PA一线",
          "description": "PANews 9月21日消息，Balancer在推特就最新的DNS攻击发布更新称，可以确认该域现在是安全的并重新由Balancer DAO控制。app.balancer.fi和其他balancer.fi子域名可以安全使用。经过调查，很明显这是一次针对EuroDNS（用于 .fi顶级域名的域名注册商）的社会工程攻击，Balancer正在探索弃用 .fi TLD，以便转向更安全的注册商，并建议使用TLD的其他项目也这样做。据此前消息，Balancer遭遇BGP或DNS劫持攻击，已损失约23.8万美元。",
          "link": "https://panewslab.com/zh/articledetails/ke74qv1z.html",
          "publishedOn": "2023-09-20T18:15:52.000Z",
          "wordCount": 360,
          "title": "Balancer：确认前端目前安全并重新由Balancer DAO控制",
          "imageUrl": "https://image.panewslab.com/images/logo1.jpg"
        },
        {
          "id": "https://panewslab.com/zh/articledetails/xktf905i.html",
          "author": "PA一线",
          "description": "PANews 9月21日消息，美联储将基准利率维持在5.25%-5.50%区间不变，符合市场预期。根据美联储FOMC声明，12位官员预计今年还会加息一次，7位官员预计维持不变。美联储点阵图显示，2026年利率预期中值为2.9%，高于2.5%的长期预期。",
          "link": "https://panewslab.com/zh/articledetails/xktf905i.html",
          "publishedOn": "2023-09-20T18:06:41.000Z",
          "wordCount": 341,
          "title": "美联储维持利率不变",
          "imageUrl": "https://image.panewslab.com/images/logo1.jpg"
        },
        {
          "id": "https://panewslab.com/zh/articledetails/z4ujimxp.html",
          "author": "PA一线",
          "description": "PANews 9月21日消息，由 Gear Protocol 提供支持，亦获得波卡创始人 Gavin Wood 支持的去中心化 Layer-1 网络 Vara Network 的主网已上线。Vara Network 利用 Actor 模型和持久内存等概念来提高速度并缩短延迟，并为智能合约引入了并行处理和单独的内存空间，为游戏、金融等领域的开发提供了支持。\n相关阅读：对话 Gear｜波卡生态下一代 WASM 智能合约平台",
          "link": "https://panewslab.com/zh/articledetails/z4ujimxp.html",
          "publishedOn": "2023-09-20T16:31:56.000Z",
          "wordCount": 407,
          "title": "Layer 1网络Vara Network主网已上线",
          "imageUrl": "https://image.panewslab.com/images/logo1.jpg"
        },
        {
          "id": "https://panewslab.com/zh/articledetails/6jn3zdla.html",
          "author": "PA一线",
          "description": "PANews 9月21日消息，据The Block报道，由Qredo孵化的混合加密货币交易所Ankex正从 alpha 阶段转向 beta 阶段，在稍后全面公开测试版发布之前，将分阶段添加该技术的测试人员。据公告称，该平台专为高频交易者打造，最初提供以稳定币 USDC 结算交易的能力。\nAnkex首席执行官MichaelMoro表示，Ankex目前正在以种子阶段投资的形式寻求外部资本。他补充说，虽然最初用户需要打开 Qredo 钱包才能开始在 Ankex 上进行交易，但最终目标是它变得“与钱包无关”。",
          "link": "https://panewslab.com/zh/articledetails/6jn3zdla.html",
          "publishedOn": "2023-09-20T16:12:54.000Z",
          "wordCount": 385,
          "title": "混合加密交易所Ankex转向beta阶段，稍后将包括公开测试",
          "imageUrl": "https://image.panewslab.com/images/logo1.jpg"
        },
        {
          "id": "https://panewslab.com/zh/articledetails/9qds2k2z.html",
          "author": "PA一线",
          "description": "PANews 9月21日消息，Coinbase 将在 Vara 网络上添加对 Vara (VARA) 的支持。如果满足流动性条件，预计交易将于今天晚些时候开始。一旦该资产供应充足，VARA-USD 交易对上的交易将分阶段启动。",
          "link": "https://panewslab.com/zh/articledetails/9qds2k2z.html",
          "publishedOn": "2023-09-20T16:02:12.000Z",
          "wordCount": 372,
          "title": "Coinbase将上架Vara (VARA)",
          "imageUrl": "https://image.panewslab.com/images/logo1.jpg"
        }
      ]
    },
    {
      "title": "白话区块链 - 快讯",
      "feedUrl": "https://rsshub.app/hellobtc/news",
      "siteUrl": "https://www.hellobtc.com/news",
      "articles": [
        {
          "id": "https://www.hellobtc.com/news/202309/21252.html",
          "author": null,
          "description": "1.friend.tech“Keys”总市值突破1亿美元，接近Azuki总市值的两倍。\n\n2.数据：Base网络TVL超越zkSync Era，已达5.38亿美元。\n\n3.Chainalysis：印度成为全球第二大加密市场，年交易额近2689亿美元。\n\n4.香港署理总督察：JPEX案中不排除更多人被捕，拟充公6700万港元可疑犯罪所得。\n\n5.Coinbase发起草根运动，推动美国立法。\n\n6.三部门印发加强反洗钱协作配合意见，全面推进打击治理洗钱犯罪。\n\n7.Arbitrum奥德赛将于下周重新上线，与Galxe合作并持续7周。\n\n8.数据：Base自上线以来已产生超过420万美元的排序器利润。\n\n9.Mark Cuban将其加密被盗事件归咎于谷歌搜索中的盗版MetaMask。\n\n10.ZachXBT：截止目前，Balancer被盗资金约23.8万美元。\n\n11.新加坡金管局第四次执法报告：2023年和24年将把解决数字资产生态系统中不当行为作为执法重点。",
          "link": "https://www.hellobtc.com/news/202309/21252.html",
          "publishedOn": "2023-09-20T03:02:00.000Z",
          "wordCount": 325,
          "title": "白话区块链早报：friend.tech“Keys”总市值突破1亿美元，接近Azuki总市值的两倍",
          "imageUrl": "https://www.hellobtc.com/d/file/202106/bff70034ff497aeca9460d3429e7d08f.jpg"
        },
        {
          "id": "https://www.hellobtc.com/news/202309/21251.html",
          "author": null,
          "description": "1.外媒：加密KOL“BITCOINLFG”披露资管巨头贝莱德已购入1.22万枚BTC。\n\n2.Sui Network：网络活跃账户已超600万个。\n\n3.香港数码港总裁任景信：入驻Web3企业超过190家，已成立Web3学院。\n\n4.数据：Binance.US 8月交易量较去年1月下降98%。\n\n5.马斯克考虑向所有推特用户收费。\n\n6.美众议员Emmer：数字资产将成为2024年大选的关键问题。",
          "link": "https://www.hellobtc.com/news/202309/21251.html",
          "publishedOn": "2023-09-19T02:49:00.000Z",
          "wordCount": 318,
          "title": "白话区块链早报：资管巨头贝莱德已购入1.22万枚BTC",
          "imageUrl": "https://www.hellobtc.com/d/file/202106/bff70034ff497aeca9460d3429e7d08f.jpg"
        },
        {
          "id": "https://www.hellobtc.com/news/202309/21250.html",
          "author": null,
          "description": "Circle的首席执行官Jeremy Allaire对稳定币法很快通过表示怀疑。Allaire表示，虽然美国对监管稳定币的重要性达成了共识，但不认为最近提出的《支付稳定币透明度法案》会被签署成为法律。",
          "link": "https://www.hellobtc.com/news/202309/21250.html",
          "publishedOn": "2023-09-19T02:25:00.000Z",
          "wordCount": 310,
          "title": "Circle的首席执行官：稳定币法案不太可能签署成为法律",
          "imageUrl": "https://www.hellobtc.com/d/file/202106/bff70034ff497aeca9460d3429e7d08f.jpg"
        },
        {
          "id": "https://www.hellobtc.com/news/202309/21249.html",
          "author": null,
          "description": "第九届区块链全球峰会于上海正式召开，香港数码港总裁任景信表示，截至目前入驻香港数码港的Web3企业数量已经超过190家。此外，任景信还表示，数码港已成立了一家Web3学院，旨在进行公众培训和大学合作计划。",
          "link": "https://www.hellobtc.com/news/202309/21249.html",
          "publishedOn": "2023-09-19T02:25:00.000Z",
          "wordCount": 314,
          "title": "香港数码港总裁任景信：入驻Web3企业超过190家，已成立Web3学院",
          "imageUrl": "https://www.hellobtc.com/d/file/202106/bff70034ff497aeca9460d3429e7d08f.jpg"
        },
        {
          "id": "https://www.hellobtc.com/news/202309/21248.html",
          "author": null,
          "description": "香港电脑商会主席许健生宣布已发起成立本地Web 3.0组织WebX产业联盟“WebXIA”，旨在推动香港Web 3.0开发者积极与监管机构和政策制定者合作，以向监管机构解释相关技术和潜在好处，倡导构建一个即可支持创新又能保护消费者且维护金融稳定的监管环境，并为企业转型提供支持。此外，许健生建议香港必须举办一些像Token2049这样的活动来彰显国际化地位。（PCMmarket）",
          "link": "https://www.hellobtc.com/news/202309/21248.html",
          "publishedOn": "2023-09-19T02:24:00.000Z",
          "wordCount": 315,
          "title": "香港电脑商会主席发起成立本地Web 3.0组织WebX产业联盟“WebXIA”",
          "imageUrl": "https://www.hellobtc.com/d/file/202106/bff70034ff497aeca9460d3429e7d08f.jpg"
        },
        {
          "id": "https://www.hellobtc.com/news/202309/21247.html",
          "author": null,
          "description": "9月19日消息，数据显示，一个休眠近6年的比特币巨鲸地址于06:12转出其持有的全部2099.99枚BTC（约5630.9万美元）。按照比特币当前价格计算，该巨鲸浮盈已超4451万美元。",
          "link": "https://www.hellobtc.com/news/202309/21247.html",
          "publishedOn": "2023-09-19T02:24:00.000Z",
          "wordCount": 308,
          "title": "休眠近6年巨鲸转移近2100枚BTC，浮盈超4450万美元",
          "imageUrl": "https://www.hellobtc.com/d/file/202106/bff70034ff497aeca9460d3429e7d08f.jpg"
        },
        {
          "id": "https://www.hellobtc.com/news/202309/21246.html",
          "author": null,
          "description": "总部位于旧金山的风险投资公司Blockchain Capital为两只新的加密货币投资基金筹集了5.8亿美元。 该公司成立于2013年，今天宣布推出第六只早期风险基金和第一只机会基金，筹集资金总额达5.8亿美元。支付巨头Visa是支持方之一。 据悉，Visa和PayPal还投资了Blockchain Capital的第五支3亿美元基金，该基金于2021年关闭。",
          "link": "https://www.hellobtc.com/news/202309/21246.html",
          "publishedOn": "2023-09-18T15:39:00.000Z",
          "wordCount": 319,
          "title": "Blockchain Capital为两只新加密投资基金筹集5.8亿美元",
          "imageUrl": "https://www.hellobtc.com/d/file/202106/bff70034ff497aeca9460d3429e7d08f.jpg"
        },
        {
          "id": "https://www.hellobtc.com/news/202309/21245.html",
          "author": null,
          "description": "香港立法会议员吴杰庄在社交媒体宣布，今日已在香港立法会大楼接待以太坊基金会研究员Justin Drake，向其介绍了香港的立法程序，参观了立法会部份设施。解释了由政府撰写政策以至广泛的公众咨询，到立法会三读立法的过程，也和他讨论了香港的Web3.0和稳定币政策并邀请Justin Drake给香港政府提相关意见。此外，吴杰庄表示已托Justin Drake转达诚意邀请包括Vitalik在内的以太坊基金会其他核心成员考察香港、了解香港情况。",
          "link": "https://www.hellobtc.com/news/202309/21245.html",
          "publishedOn": "2023-09-18T15:39:00.000Z",
          "wordCount": 323,
          "title": "吴杰庄：已接待以太坊基金会研究员Justin Drake，托其邀请Vitalik Buterin考察香港",
          "imageUrl": "https://www.hellobtc.com/d/file/202106/bff70034ff497aeca9460d3429e7d08f.jpg"
        },
        {
          "id": "https://www.hellobtc.com/news/202309/21244.html",
          "author": null,
          "description": "Andreessen Horowitz(a16z)两位前高管共同创立加密初创公司Bastion获得由a16z crypto领投的价值2500万美元种子轮融资。投资者还包括野村集团的Laser Digital Ventures、Robot Ventures和加密影响者Packy McCormick的Not Boring Capital等。 创始人Riyaz Faizullabhoy和Nassim Eddequiouaq分别是a16z风险投资公司加密部门的前首席技术官和首席安全官，他们正在寻求克服传统公司进入基于区块链的新去中心化互联网版本的障碍，即“web3”。他们计划按照全球法规处理加密货币托管和钱包，以及数字交易执行。",
          "link": "https://www.hellobtc.com/news/202309/21244.html",
          "publishedOn": "2023-09-18T15:38:00.000Z",
          "wordCount": 318,
          "title": "加密初创公司Bastion完成2500万美元融资，a16z领投",
          "imageUrl": "https://www.hellobtc.com/d/file/202106/bff70034ff497aeca9460d3429e7d08f.jpg"
        },
        {
          "id": "https://www.hellobtc.com/news/202309/21243.html",
          "author": null,
          "description": "9月18日消息，花旗集团（Citigroup Inc.）宣布推出代币服务“Citi Token Services”。新产品将客户存款转化为数字代币，可立即发送至全球任何地方。该服务由花旗的财务和贸易解决方案部门提供，迄今为止，该部门一直致力于使用该服务来提高现金管理和贸易融资能力。 声明称，对于花旗集团的新产品，该公司将依赖该银行拥有和管理的私人区块链。客户无需设置自己的数字钱包，而是可以通过银行现有的系统访问该服务。",
          "link": "https://www.hellobtc.com/news/202309/21243.html",
          "publishedOn": "2023-09-18T15:38:00.000Z",
          "wordCount": 317,
          "title": "花旗推出代币服务，可将客户存款转化为数字代币",
          "imageUrl": "https://www.hellobtc.com/d/file/202106/bff70034ff497aeca9460d3429e7d08f.jpg"
        }
      ]
    }
  ],
  "cliVersion": "1.15.1"
}